Workbook

Sheet CETES
A1: Plazo (actual) dias | B1: 28 | C1: 91 | D1: 182 | E1: 364 | F1: 728 | H1: periodo | I1: Frecuencia | J1: MONTO | K1: Cantidad CETES | L1: Total Invertido | M1: Remanente | N1: Ganancia Bruta | O1: Impuesto | P1: Ganancia Real | Q1: Total a fin de Periodo | R1: Precio CETE | S1: PLAZO | T1: Tasa (Annual) | U1: =_xlfn.CONCAT("Tasa / ",S$2," dias") -> Tasa / 28 dias | V1: ISR (Anual) | W1: =_xlfn.CONCAT("ISR / ",S$2," dias") -> ISR / 28 dias
B2: 1mes | C2: 3meses | D2: 6meses | E2: 1anio | F2: 2anios | H2: 1 | I2: =HLOOKUP(S2,B1:F2,2) -> 1mes | J2: 1000 | K2: =ROUNDDOWN(J2/$R$2,0) -> 100 | L2: =K2*$R$2 -> 993 | M2: =J2-L2 -> 7 | N2: =L2*$U$2 -> 6.2559 | O2: =L2*$W$2 -> 0.38087671 | P2: =N2-O2 -> 5.8750233 | Q2: =L2+M2+P2 -> 1005.875 | R2: =HLOOKUP(S2,B1:F5,5) -> 9.93 | S2: 28 | T2: =HLOOKUP(S2,B1:F5,4) -> 0.081 | U2: =(T2/360)*S2 -> 0.0063 | V2: 0.005 | W2: =(V2/365)*S2 -> 0.00038356164
A3: Valor de Redencion ( C) | B3: 10 | C3: 10 | D3: 10 | E3: 10 | F3: 10 | H3: 2 | I3: =I2 -> 1mes | J3: =Q2 -> 1005.875 | K3: =ROUNDDOWN(J3/$R$2,0) -> 101 | L3: =K3*$R$2 -> 1002.93 | M3: =J3-L3 -> 2.9450233 | N3: =L3*$U$2 -> 6.318459 | O3: =L3*$W$2 -> 0.38468548 | P3: =N3-O3 -> 5.9337735 | Q3: =L3+M3+P3 -> 1011.8088 | U3: *sobre 360 dias | W3: *sobre 365 dias
A4: Tasa Nominal | B4: {=LOOKUP(2,1/('28dias'!3:3<>""),'28dias'!3:3)/100} -> 0.081 | C4: {=LOOKUP(2,1/('91dias'!3:3<>""),'91dias'!3:3)/100} -> 0.0809 | D4: {=LOOKUP(2,1/('182dias'!3:3<>""),'182dias'!3:3)/100} -> 0.0804 | E4: {=LOOKUP(2,1/('364dias'!3:3<>""),'364dias'!3:3)/100} -> 0.0833 | F4: {=LOOKUP(2,1/('728dias'!3:3<>""),'728dias'!3:3)/100} -> 0.0849 | H4: 3 | I4: =I3 -> 1mes | J4: =Q3 -> 1011.8088 | K4: =ROUNDDOWN(J4/$R$2,0) -> 101 | L4: =K4*$R$2 -> 1002.93 | M4: =J4-L4 -> 8.8787968 | N4: =L4*$U$2 -> 6.318459 | O4: =L4*$W$2 -> 0.38468548 | P4: =N4-O4 -> 5.9337735 | Q4: =L4+M4+P4 -> 1017.7426
A5: Precio Real | B5: 9.93 | C5: 9.79 | D5: 9.62 | E5: 9.22 | F5: 8.57 | H5: 4 | I5: =I4 -> 1mes | J5: =Q4 -> 1017.7426 | K5: =ROUNDDOWN(J5/$R$2,0) -> 102 | L5: =K5*$R$2 -> 1012.86 | M5: =J5-L5 -> 4.8825703 | N5: =L5*$U$2 -> 6.381018 | O5: =L5*$W$2 -> 0.38849425 | P5: =N5-O5 -> 5.9925238 | Q5: =L5+M5+P5 -> 1023.7351
H6: 5 | I6: =I5 -> 1mes | J6: =Q5 -> 1023.7351 | K6: =ROUNDDOWN(J6/$R$2,0) -> 103 | L6: =K6*$R$2 -> 1022.79 | M6: =J6-L6 -> 0.94509408 | N6: =L6*$U$2 -> 6.443577 | O6: =L6*$W$2 -> 0.39230301 | P6: =N6-O6 -> 6.051274 | Q6: =L6+M6+P6 -> 1029.7864
H7: 6 | I7: =I6 -> 1mes | J7: =Q6 -> 1029.7864 | K7: =ROUNDDOWN(J7/$R$2,0) -> 103 | L7: =K7*$R$2 -> 1022.79 | M7: =J7-L7 -> 6.9963681 | N7: =L7*$U$2 -> 6.443577 | O7: =L7*$W$2 -> 0.39230301 | P7: =N7-O7 -> 6.051274 | Q7: =L7+M7+P7 -> 1035.8376
A8: Total sobre $1000 a un anio | B8: 1072.9678 | C8: 1078.9595 | D8: 1077.0777 | E8: 1078.9033 | H8: 7 | I8: =I7 -> 1mes | J8: =Q7 -> 1035.8376 | K8: =ROUNDDOWN(J8/$R$2,0) -> 104 | L8: =K8*$R$2 -> 1032.72 | M8: =J8-L8 -> 3.1176421 | N8: =L8*$U$2 -> 6.506136 | O8: =L8*$W$2 -> 0.39611178 | P8: =N8-O8 -> 6.1100242 | Q8: =L8+M8+P8 -> 1041.9477
H9: 8 | I9: =I8 -> 1mes | J9: =Q8 -> 1041.9477 | K9: =ROUNDDOWN(J9/$R$2,0) -> 104 | L9: =K9*$R$2 -> 1032.72 | M9: =J9-L9 -> 9.2276663 | N9: =L9*$U$2 -> 6.506136 | O9: =L9*$W$2 -> 0.39611178 | P9: =N9-O9 -> 6.1100242 | Q9: =L9+M9+P9 -> 1048.0577
A10: Total sobre $1000 a dos anios | B10: 1151.2818 | C10: 1163.935 | D10: 1160.3951 | E10: 1164.3818 | F10: 1160.7632 | H10: 9 | I10: =I9 -> 1mes | J10: =Q9 -> 1048.0577 | K10: =ROUNDDOWN(J10/$R$2,0) -> 105 | L10: =K10*$R$2 -> 1042.65 | M10: =J10-L10 -> 5.4076905 | N10: =L10*$U$2 -> 6.568695 | O10: =L10*$W$2 -> 0.39992055 | P10: =N10-O10 -> 6.1687745 | Q10: =L10+M10+P10 -> 1054.2265
A11: https://www.banxico.org.mx/SieInternet/consultarDirectorioInternetAction.do?accion=consultarCuadro&idCuadro=CF107&sector=22&locale=es#:~:text=8.12-,8.10,-Mostrar%20elementos%20de | H11: 10 | I11: =I10 -> 1mes | J11: =Q10 -> 1054.2265 | K11: =ROUNDDOWN(J11/$R$2,0) -> 106 | L11: =K11*$R$2 -> 1052.58 | M11: =J11-L11 -> 1.6464649 | N11: =L11*$U$2 -> 6.631254 | O11: =L11*$W$2 -> 0.40372932 | P11: =N11-O11 -> 6.2275247 | Q11: =L11+M11+P11 -> 1060.454
H12: 11 | I12: =I11 -> 1mes | J12: =Q11 -> 1060.454 | K12: =ROUNDDOWN(J12/$R$2,0) -> 106 | L12: =K12*$R$2 -> 1052.58 | M12: =J12-L12 -> 7.8739896 | N12: =L12*$U$2 -> 6.631254 | O12: =L12*$W$2 -> 0.40372932 | P12: =N12-O12 -> 6.2275247 | Q12: =L12+M12+P12 -> 1066.6815
B13: Conclusion: | H13: 12 | I13: =I12 -> 1mes | J13: =Q12 -> 1066.6815 | K13: =ROUNDDOWN(J13/$R$2,0) -> 107 | L13: =K13*$R$2 -> 1062.51 | M13: =J13-L13 -> 4.1715143 | N13: =L13*$U$2 -> 6.693813 | O13: =L13*$W$2 -> 0.40753808 | P13: =N13-O13 -> 6.2862749 | Q13: =L13+M13+P13 -> 1072.9678
B14: Conviene Invertir en periodos de 364 dias (1 anio) | H14: 13 | I14: =I13 -> 1mes | J14: =Q13 -> 1072.9678 | K14: =ROUNDDOWN(J14/$R$2,0) -> 108 | L14: =K14*$R$2 -> 1072.44 | M14: =J14-L14 -> 0.52778923 | N14: =L14*$U$2 -> 6.756372 | O14: =L14*$W$2 -> 0.41134685 | P14: =N14-O14 -> 6.3450252 | Q14: =L14+M14+P14 -> 1079.3128
B15: En 1 anio la diferencia es minima comparado con la de 91 dias | H15: 14 | I15: =I14 -> 1mes | J15: =Q14 -> 1079.3128 | K15: =ROUNDDOWN(J15/$R$2,0) -> 108 | L15: =K15*$R$2 -> 1072.44 | M15: =J15-L15 -> 6.8728144 | N15: =L15*$U$2 -> 6.756372 | O15: =L15*$W$2 -> 0.41134685 | P15: =N15-O15 -> 6.3450252 | Q15: =L15+M15+P15 -> 1085.6578
B16: A 2 anios es la mejor opcion invertir en 364 dias. | H16: 15 | I16: =I15 -> 1mes | J16: =Q15 -> 1085.6578 | K16: =ROUNDDOWN(J16/$R$2,0) -> 109 | L16: =K16*$R$2 -> 1082.37 | M16: =J16-L16 -> 3.2878395 | N16: =L16*$U$2 -> 6.818931 | O16: =L16*$W$2 -> 0.41515562 | P16: =N16-O16 -> 6.4037754 | Q16: =L16+M16+P16 -> 1092.0616
H17: 16 | I17: =I16 -> 1mes | J17: =Q16 -> 1092.0616 | K17: =ROUNDDOWN(J17/$R$2,0) -> 109 | L17: =K17*$R$2 -> 1082.37 | M17: =J17-L17 -> 9.6916149 | N17: =L17*$U$2 -> 6.818931 | O17: =L17*$W$2 -> 0.41515562 | P17: =N17-O17 -> 6.4037754 | Q17: =L17+M17+P17 -> 1098.4654
H18: 17 | I18: =I17 -> 1mes | J18: =Q17 -> 1098.4654 | K18: =ROUNDDOWN(J18/$R$2,0) -> 110 | L18: =K18*$R$2 -> 1092.3 | M18: =J18-L18 -> 6.1653903 | N18: =L18*$U$2 -> 6.88149 | O18: =L18*$W$2 -> 0.41896438 | P18: =N18-O18 -> 6.4625256 | Q18: =L18+M18+P18 -> 1104.9279
H19: 18 | I19: =I18 -> 1mes | J19: =Q18 -> 1104.9279 | K19: =ROUNDDOWN(J19/$R$2,0) -> 111 | L19: =K19*$R$2 -> 1102.23 | M19: =J19-L19 -> 2.6979159 | N19: =L19*$U$2 -> 6.944049 | O19: =L19*$W$2 -> 0.42277315 | P19: =N19-O19 -> 6.5212758 | Q19: =L19+M19+P19 -> 1111.4492
H20: 19 | I20: =I19 -> 1mes | J20: =Q19 -> 1111.4492 | K20: =ROUNDDOWN(J20/$R$2,0) -> 111 | L20: =K20*$R$2 -> 1102.23 | M20: =J20-L20 -> 9.2191918 | N20: =L20*$U$2 -> 6.944049 | O20: =L20*$W$2 -> 0.42277315 | P20: =N20-O20 -> 6.5212758 | Q20: =L20+M20+P20 -> 1117.9705
H21: 20 | I21: =I20 -> 1mes | J21: =Q20 -> 1117.9705 | K21: =ROUNDDOWN(J21/$R$2,0) -> 112 | L21: =K21*$R$2 -> 1112.16 | M21: =J21-L21 -> 5.8104676 | N21: =L21*$U$2 -> 7.006608 | O21: =L21*$W$2 -> 0.42658192 | P21: =N21-O21 -> 6.5800261 | Q21: =L21+M21+P21 -> 1124.5505
H22: 21 | I22: =I21 -> 1mes | J22: =Q21 -> 1124.5505 | K22: =ROUNDDOWN(J22/$R$2,0) -> 113 | L22: =K22*$R$2 -> 1122.09 | M22: =J22-L22 -> 2.4604937 | N22: =L22*$U$2 -> 7.069167 | O22: =L22*$W$2 -> 0.43039068 | P22: =N22-O22 -> 6.6387763 | Q22: =L22+M22+P22 -> 1131.1893
H23: 22 | I23: =I22 -> 1mes | J23: =Q22 -> 1131.1893 | K23: =ROUNDDOWN(J23/$R$2,0) -> 113 | L23: =K23*$R$2 -> 1122.09 | M23: =J23-L23 -> 9.09927 | N23: =L23*$U$2 -> 7.069167 | O23: =L23*$W$2 -> 0.43039068 | P23: =N23-O23 -> 6.6387763 | Q23: =L23+M23+P23 -> 1137.828
A24: CALCULO DEL PRECIO DEL BONO (para confirmar los precios de CETES directo) | H24: 23 | I24: =I23 -> 1mes | J24: =Q23 -> 1137.828 | K24: =ROUNDDOWN(J24/$R$2,0) -> 114 | L24: =K24*$R$2 -> 1132.02 | M24: =J24-L24 -> 5.8080463 | N24: =L24*$U$2 -> 7.131726 | O24: =L24*$W$2 -> 0.43419945 | P24: =N24-O24 -> 6.6975265 | Q24: =L24+M24+P24 -> 1144.5256
H25: 24 | I25: =I24 -> 1mes | J25: =Q24 -> 1144.5256 | K25: =ROUNDDOWN(J25/$R$2,0) -> 115 | L25: =K25*$R$2 -> 1141.95 | M25: =J25-L25 -> 2.5755729 | N25: =L25*$U$2 -> 7.194285 | O25: =L25*$W$2 -> 0.43800822 | P25: =N25-O25 -> 6.7562768 | Q25: =L25+M25+P25 -> 1151.2818
A26: Opcion 1: | B26: Precio del Bono por Formula Simple:
A28: dias al anio con base en el PLAZO | B28: =B1*12 -> 336 | C28: =C1*4 -> 364 | D28: =D1*2 -> 364 | E28: =E1*1 -> 364 | F28: =F1/2 -> 364
A29: P = | B29: =B3/((1+B4)^(B1/B28)) -> 9.9353047 | C29: =C3/((1+C4)^(C1/C28)) -> 9.807394 | D29: =D3/((1+D4)^(D1/D28)) -> 9.620723 | E29: =E3/((1+E4)^(E1/E28)) -> 9.2310533 | F29: =F3/((1+F4)^(F1/F28)) -> 8.4961189
A30: diferencia con el Precio CETES directo | B30: =B5-B29 -> -0.005304732 | C30: =C5-C29 -> -0.017393952 | D30: =D5-D29 -> -0.00072303605 | E30: =E5-E29 -> -0.011053263 | F30: =F5-F29 -> 0.073881099
A34: Opcion 2: | B34: Precio Bono por P_t-bill Formula:
A36: Usando la regla del banquero de 360 dias por anio
A37: d: tasa descuento efectiva | B37: =B4/(1+((B1/360)*B4)) -> 0.080492895 | C37: =C4/(1+((C1/360)*C4)) -> 0.079278771 | D37: =D4/(1+((D1/360)*D4)) -> 0.077259653 | E37: =E4/(1+((E1/360)*E4)) -> 0.076829032 | F37: =F4/(1+((F1/360)*F4)) -> 0.072459645
A40: P_t-bill = | B40: =B3*(1-((B1/360)*B37)) -> 9.9373944 | C40: =C3*(1-((C1/360)*C37)) -> 9.7996009 | D40: =D3*(1-((D1/360)*D37)) -> 9.6094095 | E40: =E3*(1-((E1/360)*E37)) -> 9.2231731 | F40: =F3*(1-((F1/360)*F37)) -> 8.534705
A41: diferencia con el Precio CETES directo | B41: =B5-B40 -> -0.0073944152 | C41: =C5-C40 -> -0.009600884 | D41: =D5-D40 -> 0.010590466 | E41: =E5-E40 -> -0.00317312 | F41: =F5-F40 -> 0.035295045

Sheet 28dias
A1: Column1 | B1: Column2 | C1: Column3
A2: 22/05/2025 | B2: 29/05/2025 | C2: 05/06/2025
A3: 8.15000 | B3: 8.12000 | C3: 8.10000

Sheet 91dias
A1: Column1 | B1: Column2 | C1: Column3
A2: 22/05/2025 | B2: 29/05/2025 | C2: 05/06/2025
A3: 8.24000 | B3: 8.14000 | C3: 8.09000

Sheet 182dias
A1: Column1 | B1: Column2 | C1: Column3
A2: 22/05/2025 | B2: 29/05/2025 | C2: 05/06/2025
A3: 8.16000 | B3: 8.12000 | C3: 8.04000

Sheet 364dias
A1: Column1 | B1: Column2 | C1: Column3
A2: 22/05/2025 | B2: 29/05/2025 | C2: 05/06/2025
B3: 8.33000

Sheet 728dias
A1: Column1 | B1: Column2 | C1: Column3
A2: 22/05/2025 | B2: 29/05/2025 | C2: 05/06/2025
A3: 8.55000 | C3: 8.49000
