Workbook

Sheet Principal
B2: Informacion del Prestamo (Datos de Entrada) | I2: Resumen del Prestamo "Mortgage"
C4: Instrucciones: | J4: Prestamo | P4: =D21 -> 228158.7
C5: 1) Ingresar datos en celdas color verde
C6: 2) Usar controles
C7: 3) ver resultados en color amarillo y graficos | J7: Pago Mensual del Mortgage o credito: Capital mas Intereses | P7: ='Flujos Mensuales'!T9 -> 1517.9455
C9: Precio | D9: 249900 | J9: =IF(D19>=0.2,"","Pago Mensual del Seguro del credito") -> Pago Mensual del Seguro del credito | P9: =IF(D19>=0.2,"",D27/12) -> 247.17192
C11: Termino (años) | D11: 30 | J11: =IF(D25="Mensual","Pago Mensual de Impuestos (incluido en el credito) 2o año ","") -> Pago Mensual de Impuestos (incluido en el credito) 2o año | P11: =IF(D25="Mensual",'Flujos Mensuales'!H26,"") -> 352.08456
C13: Tasa de interes | D13: =F13/2/1000 -> 0.07 | F13: 140 | J13: =IF($D$19<0.2,IF($D$25="Mensual","Pago Mensual (2o año): Capital + Intereses + Seguro + Impuestos","Pago Mensual (2o año): Capital + Intereses + Seguro"),IF($D$25="Mensual","Pago Mensual (2o año): Capital + Intereses + Impuestos","Pago Mensual (2o año): Capital + Intereses")) -> Pago Mensual (2o año): Capital + Intereses + Seguro + Impuestos | P13: =IF($D$19>=0.2,'Flujos Mensuales'!W8,'Flujos Mensuales'!W7) -> 2117.202
C15: Gastos de Cierre | D15: =0.1*D9 -> 24990 | E15: 1% del Precio | J15: Pago Mensual Utilities 2o año | P15: ='Flujos Mensuales'!P26 -> 35.0975
C17: Subtotal | D17: =D9+D15 -> 274890 | J17: =IF(D30="Mensual","Pago Mensual de Mantenimientos Mayores (a partir del 2do año)","") -> Pago Mensual de Mantenimientos Mayores (a partir del 2do año) | P17: =IF(D30="Mensual",'Flujos Mensuales'!O26,"") -> 217.76179
C19: Anticipo | D19: =F19/100 -> 0.17 | E19: =D17*D19 -> 46731.3 | F19: 17 | J19: Pago TOTAL Mensual a partir del 2do año | P19: ='Flujos Mensuales'!Q26 -> 2370.0613
K20: Capital + Intereses (Mortgage)
C21: Total a Financiar (prestamo) | D21: =D17-(D17*D19) -> 228158.7 | K21: Seguro del Prestamo (si aplica)
K22: Impuestos (si se elige mensual)
C23: Impuesto Anual estimados 2025 | D23: =MAX(catalogos!D3:D8) -> 4196.1949 | K23: Mantenimientos Mayores
K24: Utilities
C25: Forma de Pago de Impuestos | D25: Mensual | E25: =IF(D25="Mensual"," Incluido en la Mensualidad","") -> Incluido en la Mensualidad
J26: =IF(D25="Anual","Pago Anual de Impuestos a inicio del 2o año","") | P26: =IF(D25="Anual",D23,"")
C27: Seguro del Credito Anual estimado 2025 | D27: =IF(D19>=0.2,0,0.013*D21) -> 2966.0631 | E27: 1.3% del Total a financiar
E28: si el anticipo es menor al 20% | J28: =IF(D30="Anual","Pago Anual Mantenimientos Mayores (a partir del 2do año)","") | P28: =IF(D30="Anual",'Flujos Mensuales'!O37,"")
C30: Costos de Mantenimiento | D30: Mensual | E30: =IF(D30="Mensual"," Prorrateado Mensualmente","") -> Prorrateado Mensualmente | J30: =IF(AND(D25="Mensual",D30="Mensual"),"","Total de Pagos Anuales Adicionales a partir del 2o año") | P30: {=IF(SUMPRODUCT(--ISNUMBER(P26:P28),P26:P28)=0,"",SUMPRODUCT(--ISNUMBER(P26:P28),P26:P28))}
B33: Utilities y otros gastos mensuales diferentes a Rentar | I33: Pagos Totales
C35: Gas & Electricity | D35: 0 | J35: Total a Pagar de Capital | P35: ='Flujos Mensuales'!E6 -> 228158.7
C36: Trash | D36: 0
C37: Hot Water | D37: 0 | J37: Total a Pagar de Intereses | P37: ='Flujos Mensuales'!D6 -> 318301.69
C38: Water | D38: 0
C39: Sewer | D39: 0 | J39: Total a Pagar del Credito: Capital + Intereses | P39: ='Flujos Mensuales'!C6 -> 546460.39
C40: Sal para el hielo (5 meses prorrateados) | D40: =(25*5)/12 -> 10.416667 | E40: Propio de Comprar
C41: Jardineria (7 meses prorrateados) | D41: =(15*7)/12 -> 8.75 | E41: Propio de Comprar | J41: Total a Pagar de Impuestos | P41: ='Flujos Mensuales'!H6 -> 139344.44
C42: Seguro de la propiedad | D42: =187/12 -> 15.583333 | E42: Propio de Comprar
C43: Internet | D43: 0 | J43: =IF(D19>=0.2,"","Total a Pagar del Seguro") -> Total a Pagar del Seguro | P43: =IF(D19>=0.2,"",'Flujos Mensuales'!K6) -> 6179.2981
C44: TOTAL | D44: =SUM(D35:D43) -> 34.75
J45: TOTAL a Pagar: Capital + Intereses + Impuestos + Seguro | P45: ='Flujos Mensuales'!L6 -> 691984.12
J47: Total a Pagar de Mantenimientos Mayores en 30 años | P47: =SUM('Flujos Anuales'!J9:J39) -> 161255.13
J49: Total a Pagar de Utilities en 30 años | P49: =SUM('Flujos Anuales'!K9:K39) -> 15067.353
J51: Total de Pagos en 30 años | P51: =SUM('Flujos Anuales'!L9:L39) -> 915037.91
J53: Break point (Equity >= Cash Outflow) | P53: {=MATCH(TRUE,'Flujos Anuales'!G9:G49>'Flujos Anuales'!M9:M49,0)-1} -> 29
P54: años

Sheet Flujos Mensuales
S1: SISTEMA DE AMORTIZACION GRADUAL o "frances" - MENSUAL
B2: Flujos Mensuales | S2: tasa de interes annual | T2: =Principal!D13 -> 0.07 | V2: Impuestos Anuales | W2: =Principal!D23 -> 4196.1949
S3: frecuencia de capitalizacion | T3: 12 | V3: Incremento Impuesto Annual (promedio) | W3: ='Property Tax Zillow'!G27 -> 0.0068680893
S4: tasa efectiva | T4: =T2/T3 -> 0.0058333333 | V4: Seguro Anual | W4: =Principal!D27 -> 2966.0631
F5: Comprobacion | S5: periodos (n de pagos) | T5: =Principal!D11*12 -> 360 | V5: Seguro Mensual | W5: =W4/12 -> 247.17192
C6: =SUM(C14:C374) -> 546460.39 | D6: =SUM(D14:D374) -> 318301.69 | E6: =SUM(E14:E374) -> 228158.7 | F6: =E6+D6 -> 546460.39 | H6: =SUM(H14:H374) -> 139344.44 | K6: =SUM(K14:K374) -> 6179.2981 | L6: =SUM(L14:L374) -> 691984.12 | M6: Comprobacion | S6: credito | T6: =Principal!D21 -> 228158.7 | V6: Saldo minimo para no pagar seguro del credito | W6: =Principal!D17*0.2 -> 54978
C7: El total de lo | D7: Los intereses pagados | E7: El capital pagado | F7: capital + intereses | H7: Total Pago Impuestos | K7: Total Pago Seguro | L7: Total de Pagos mensuales | M7: =F6+H6+K6 -> 691984.12 | S7: factor de descuento (V) | T7: =1/(1+T4) -> 0.9942005 | V7: Pago total Mensual con seguro el 1er año | W7: =L26 -> 2117.202
C8: pagado al banco | M8: capital + intereses + impuestos + seguro | S8: anualidad (a_n*12) anualidades vencidas | T8: =(1-T7^T5)/T4 -> 150.30757 | V8: Pago total Mensual sin seguro el 1er año | W8: =W7-W5 -> 1870.0301
C9: incluye capital | S9: rentas (mensuales) fijas | T9: =T6/T8 -> 1517.9455
C10: e intereses
B12: Tabla de Amortizacion | H12: Impuestos y Seguro | O12: Mantto. Y Utilities
B13: Periodo (mes) | C13: Renta (Mensual) (pagos iguales) | D13: Interes (van bajando) | E13: Pago a Capital Amortizacion (va aumentando) | F13: Saldo Insoluto o Remaining Principal (va bajando) | H13: Impuestos | I13: OCULTAR variable temporal (renta+impuestos+seguro) | J13: OCULTAR variable temporal Pago Total Acumulado con seguro hasta cubrir el 20% | K13: Seguro Mensual | L13: Pago Total Mensual (credito, impuestos, seguro del credito) | M13: Año | N13: Pago Annual Mortgage (Intereses, Capital, impuestos, seguro del credito) | O13: Mantenimiento Mayor | P13: Utilities y otros | Q13: Pago Total Mensual
B14: 0 | C14: 0 | D14: 0 | E14: 0 | F14: =T6 -> 228158.7 | H14: 0 | I14: 0 | J14: =SUM(I14) -> 0 | K14: 0 | L14: 0 | M14: =ROUNDDOWN(B14/12,0) -> 0 | N14: =SUM(L14:L25) -> 23262.804 | O14: =IF(Principal!$D$30="Anual",IF(MOD(B14+1,12)=0,VLOOKUP(M14,'Flujos Anuales'!$B$8:$K$39,9),0),VLOOKUP(M14,'Flujos Anuales'!$B$8:$K$39,9)/12) -> 0 | P14: 0 | Q14: =L14+O14+P14 -> 0
B15: 1 | C15: =$T$9 -> 1517.9455 | D15: =F14*$T$4 -> 1330.9258 | E15: =C15-D15 -> 187.01977 | F15: =F14-E15 -> 227971.68 | H15: =IF(Principal!$D$25="Anual",IF(MOD(B15+1,12)=0,$W$2*((1+$W$3)^M15),0),$W$2*((1+$W$3)^M15)/12) -> 349.68291 | I15: =C15+H15+$W$5 -> 2114.8004 | J15: =SUM($I$14:I15) -> 2114.8004 | K15: =IF(J15>=$W$6,0,$W$5) -> 247.17192 | L15: =IF(K15=$W$5,I15,I15-$W$5) -> 2114.8004 | M15: =ROUNDDOWN(B15/12,0) -> 0 | O15: =IF(Principal!$D$30="Anual",IF(MOD(B15+1,12)=0,VLOOKUP(M15,'Flujos Anuales'!$B$8:$K$39,9),0),VLOOKUP(M15,'Flujos Anuales'!$B$8:$K$39,9)/12) -> 0 | P15: =VLOOKUP(M15,'Flujos Anuales'!$B$8:$K$39,10)/12 -> 34.75 | Q15: =L15+O15+P15 -> 2149.5504
B16: 2 | C16: =$T$9 -> 1517.9455 | D16: =F15*$T$4 -> 1329.8348 | E16: =C16-D16 -> 188.11072 | F16: =F15-E16 -> 227783.57 | H16: =IF(Principal!$D$25="Anual",IF(MOD(B16+1,12)=0,$W$2*((1+$W$3)^M16),0),$W$2*((1+$W$3)^M16)/12) -> 349.68291 | I16: =C16+H16+$W$5 -> 2114.8004 | J16: =SUM($I$14:I16) -> 4229.6007 | K16: =IF(J16>=$W$6,0,$W$5) -> 247.17192 | L16: =IF(K16=$W$5,I16,I16-$W$5) -> 2114.8004 | M16: =ROUNDDOWN(B16/12,0) -> 0 | O16: =IF(Principal!$D$30="Anual",IF(MOD(B16+1,12)=0,VLOOKUP(M16,'Flujos Anuales'!$B$8:$K$39,9),0),VLOOKUP(M16,'Flujos Anuales'!$B$8:$K$39,9)/12) -> 0 | P16: =VLOOKUP(M16,'Flujos Anuales'!$B$8:$K$39,10)/12 -> 34.75 | Q16: =L16+O16+P16 -> 2149.5504
B17: 3 | C17: =$T$9 -> 1517.9455 | D17: =F16*$T$4 -> 1328.7375 | E17: =C17-D17 -> 189.20804 | F17: =F16-E17 -> 227594.36 | H17: =IF(Principal!$D$25="Anual",IF(MOD(B17+1,12)=0,$W$2*((1+$W$3)^M17),0),$W$2*((1+$W$3)^M17)/12) -> 349.68291 | I17: =C17+H17+$W$5 -> 2114.8004 | J17: =SUM($I$14:I17) -> 6344.4011 | K17: =IF(J17>=$W$6,0,$W$5) -> 247.17192 | L17: =IF(K17=$W$5,I17,I17-$W$5) -> 2114.8004 | M17: =ROUNDDOWN(B17/12,0) -> 0 | O17: =IF(Principal!$D$30="Anual",IF(MOD(B17+1,12)=0,VLOOKUP(M17,'Flujos Anuales'!$B$8:$K$39,9),0),VLOOKUP(M17,'Flujos Anuales'!$B$8:$K$39,9)/12) -> 0 | P17: =VLOOKUP(M17,'Flujos Anuales'!$B$8:$K$39,10)/12 -> 34.75 | Q17: =L17+O17+P17 -> 2149.5504
B18: 4 | C18: =$T$9 -> 1517.9455 | D18: =F17*$T$4 -> 1327.6338 | E18: =C18-D18 -> 190.31175 | F18: =F17-E18 -> 227404.05 | H18: =IF(Principal!$D$25="Anual",IF(MOD(B18+1,12)=0,$W$2*((1+$W$3)^M18),0),$W$2*((1+$W$3)^M18)/12) -> 349.68291 | I18: =C18+H18+$W$5 -> 2114.8004 | J18: =SUM($I$14:I18) -> 8459.2014 | K18: =IF(J18>=$W$6,0,$W$5) -> 247.17192 | L18: =IF(K18=$W$5,I18,I18-$W$5) -> 2114.8004 | M18: =ROUNDDOWN(B18/12,0) -> 0 | O18: =IF(Principal!$D$30="Anual",IF(MOD(B18+1,12)=0,VLOOKUP(M18,'Flujos Anuales'!$B$8:$K$39,9),0),VLOOKUP(M18,'Flujos Anuales'!$B$8:$K$39,9)/12) -> 0 | P18: =VLOOKUP(M18,'Flujos Anuales'!$B$8:$K$39,10)/12 -> 34.75 | Q18: =L18+O18+P18 -> 2149.5504
B19: 5 | C19: =$T$9 -> 1517.9455 | D19: =F18*$T$4 -> 1326.5236 | E19: =C19-D19 -> 191.4219 | F19: =F18-E19 -> 227212.63 | H19: =IF(Principal!$D$25="Anual",IF(MOD(B19+1,12)=0,$W$2*((1+$W$3)^M19),0),$W$2*((1+$W$3)^M19)/12) -> 349.68291 | I19: =C19+H19+$W$5 -> 2114.8004 | J19: =SUM($I$14:I19) -> 10574.002 | K19: =IF(J19>=$W$6,0,$W$5) -> 247.17192 | L19: =IF(K19=$W$5,I19,I19-$W$5) -> 2114.8004 | M19: =ROUNDDOWN(B19/12,0) -> 0 | O19: =IF(Principal!$D$30="Anual",IF(MOD(B19+1,12)=0,VLOOKUP(M19,'Flujos Anuales'!$B$8:$K$39,9),0),VLOOKUP(M19,'Flujos Anuales'!$B$8:$K$39,9)/12) -> 0 | P19: =VLOOKUP(M19,'Flujos Anuales'!$B$8:$K$39,10)/12 -> 34.75 | Q19: =L19+O19+P19 -> 2149.5504
B20: 6 | C20: =$T$9 -> 1517.9455 | D20: =F19*$T$4 -> 1325.407 | E20: =C20-D20 -> 192.53853 | F20: =F19-E20 -> 227020.09 | H20: =IF(Principal!$D$25="Anual",IF(MOD(B20+1,12)=0,$W$2*((1+$W$3)^M20),0),$W$2*((1+$W$3)^M20)/12) -> 349.68291 | I20: =C20+H20+$W$5 -> 2114.8004 | J20: =SUM($I$14:I20) -> 12688.802 | K20: =IF(J20>=$W$6,0,$W$5) -> 247.17192 | L20: =IF(K20=$W$5,I20,I20-$W$5) -> 2114.8004 | M20: =ROUNDDOWN(B20/12,0) -> 0 | O20: =IF(Principal!$D$30="Anual",IF(MOD(B20+1,12)=0,VLOOKUP(M20,'Flujos Anuales'!$B$8:$K$39,9),0),VLOOKUP(M20,'Flujos Anuales'!$B$8:$K$39,9)/12) -> 0 | P20: =VLOOKUP(M20,'Flujos Anuales'!$B$8:$K$39,10)/12 -> 34.75 | Q20: =L20+O20+P20 -> 2149.5504
B21: 7 | C21: =$T$9 -> 1517.9455 | D21: =F20*$T$4 -> 1324.2839 | E21: =C21-D21 -> 193.66167 | F21: =F20-E21 -> 226826.43 | H21: =IF(Principal!$D$25="Anual",IF(MOD(B21+1,12)=0,$W$2*((1+$W$3)^M21),0),$W$2*((1+$W$3)^M21)/12) -> 349.68291 | I21: =C21+H21+$W$5 -> 2114.8004 | J21: =SUM($I$14:I21) -> 14803.603 | K21: =IF(J21>=$W$6,0,$W$5) -> 247.17192 | L21: =IF(K21=$W$5,I21,I21-$W$5) -> 2114.8004 | M21: =ROUNDDOWN(B21/12,0) -> 0 | O21: =IF(Principal!$D$30="Anual",IF(MOD(B21+1,12)=0,VLOOKUP(M21,'Flujos Anuales'!$B$8:$K$39,9),0),VLOOKUP(M21,'Flujos Anuales'!$B$8:$K$39,9)/12) -> 0 | P21: =VLOOKUP(M21,'Flujos Anuales'!$B$8:$K$39,10)/12 -> 34.75 | Q21: =L21+O21+P21 -> 2149.5504
B22: 8 | C22: =$T$9 -> 1517.9455 | D22: =F21*$T$4 -> 1323.1542 | E22: =C22-D22 -> 194.79136 | F22: =F21-E22 -> 226631.64 | H22: =IF(Principal!$D$25="Anual",IF(MOD(B22+1,12)=0,$W$2*((1+$W$3)^M22),0),$W$2*((1+$W$3)^M22)/12) -> 349.68291 | I22: =C22+H22+$W$5 -> 2114.8004 | J22: =SUM($I$14:I22) -> 16918.403 | K22: =IF(J22>=$W$6,0,$W$5) -> 247.17192 | L22: =IF(K22=$W$5,I22,I22-$W$5) -> 2114.8004 | M22: =ROUNDDOWN(B22/12,0) -> 0 | O22: =IF(Principal!$D$30="Anual",IF(MOD(B22+1,12)=0,VLOOKUP(M22,'Flujos Anuales'!$B$8:$K$39,9),0),VLOOKUP(M22,'Flujos Anuales'!$B$8:$K$39,9)/12) -> 0 | P22: =VLOOKUP(M22,'Flujos Anuales'!$B$8:$K$39,10)/12 -> 34.75 | Q22: =L22+O22+P22 -> 2149.5504
B23: 9 | C23: =$T$9 -> 1517.9455 | D23: =F22*$T$4 -> 1322.0179 | E23: =C23-D23 -> 195.92765 | F23: =F22-E23 -> 226435.71 | H23: =IF(Principal!$D$25="Anual",IF(MOD(B23+1,12)=0,$W$2*((1+$W$3)^M23),0),$W$2*((1+$W$3)^M23)/12) -> 349.68291 | I23: =C23+H23+$W$5 -> 2114.8004 | J23: =SUM($I$14:I23) -> 19033.203 | K23: =IF(J23>=$W$6,0,$W$5) -> 247.17192 | L23: =IF(K23=$W$5,I23,I23-$W$5) -> 2114.8004 | M23: =ROUNDDOWN(B23/12,0) -> 0 | O23: =IF(Principal!$D$30="Anual",IF(MOD(B23+1,12)=0,VLOOKUP(M23,'Flujos Anuales'!$B$8:$K$39,9),0),VLOOKUP(M23,'Flujos Anuales'!$B$8:$K$39,9)/12) -> 0 | P23: =VLOOKUP(M23,'Flujos Anuales'!$B$8:$K$39,10)/12 -> 34.75 | Q23: =L23+O23+P23 -> 2149.5504
B24: 10 | C24: =$T$9 -> 1517.9455 | D24: =F23*$T$4 -> 1320.875 | E24: =C24-D24 -> 197.07056 | F24: =F23-E24 -> 226238.64 | H24: =IF(Principal!$D$25="Anual",IF(MOD(B24+1,12)=0,$W$2*((1+$W$3)^M24),0),$W$2*((1+$W$3)^M24)/12) -> 349.68291 | I24: =C24+H24+$W$5 -> 2114.8004 | J24: =SUM($I$14:I24) -> 21148.004 | K24: =IF(J24>=$W$6,0,$W$5) -> 247.17192 | L24: =IF(K24=$W$5,I24,I24-$W$5) -> 2114.8004 | M24: =ROUNDDOWN(B24/12,0) -> 0 | O24: =IF(Principal!$D$30="Anual",IF(MOD(B24+1,12)=0,VLOOKUP(M24,'Flujos Anuales'!$B$8:$K$39,9),0),VLOOKUP(M24,'Flujos Anuales'!$B$8:$K$39,9)/12) -> 0 | P24: =VLOOKUP(M24,'Flujos Anuales'!$B$8:$K$39,10)/12 -> 34.75 | Q24: =L24+O24+P24 -> 2149.5504
B25: 11 | C25: =$T$9 -> 1517.9455 | D25: =F24*$T$4 -> 1319.7254 | E25: =C25-D25 -> 198.22014 | F25: =F24-E25 -> 226040.42 | H25: =IF(Principal!$D$25="Anual",IF(MOD(B25+1,12)=0,$W$2*((1+$W$3)^M25),0),$W$2*((1+$W$3)^M25)/12) -> 349.68291 | I25: =C25+H25+$W$5 -> 2114.8004 | J25: =SUM($I$14:I25) -> 23262.804 | K25: =IF(J25>=$W$6,0,$W$5) -> 247.17192 | L25: =IF(K25=$W$5,I25,I25-$W$5) -> 2114.8004 | M25: =ROUNDDOWN(B25/12,0) -> 0 | O25: =IF(Principal!$D$30="Anual",IF(MOD(B25+1,12)=0,VLOOKUP(M25,'Flujos Anuales'!$B$8:$K$39,9),0),VLOOKUP(M25,'Flujos Anuales'!$B$8:$K$39,9)/12) -> 0 | P25: =VLOOKUP(M25,'Flujos Anuales'!$B$8:$K$39,10)/12 -> 34.75 | Q25: =L25+O25+P25 -> 2149.5504
B26: 12 | C26: =$T$9 -> 1517.9455 | D26: =F25*$T$4 -> 1318.5691 | E26: =C26-D26 -> 199.37642 | F26: =F25-E26 -> 225841.04 | H26: =IF(Principal!$D$25="Anual",IF(MOD(B26+1,12)=0,$W$2*((1+$W$3)^M26),0),$W$2*((1+$W$3)^M26)/12) -> 352.08456 | I26: =C26+H26+$W$5 -> 2117.202 | J26: =SUM($I$14:I26) -> 25380.006 | K26: =IF(J26>=$W$6,0,$W$5) -> 247.17192 | L26: =IF(K26=$W$5,I26,I26-$W$5) -> 2117.202 | M26: =ROUNDDOWN(B26/12,0) -> 1 | N26: =SUM(L26:L37) -> 25406.424 | O26: =IF(Principal!$D$30="Anual",IF(MOD(B26+1,12)=0,VLOOKUP(M26,'Flujos Anuales'!$B$8:$K$39,9),0),VLOOKUP(M26,'Flujos Anuales'!$B$8:$K$39,9)/12) -> 217.76179 | P26: =VLOOKUP(M26,'Flujos Anuales'!$B$8:$K$39,10)/12 -> 35.0975 | Q26: =L26+O26+P26 -> 2370.0613
B27: 13 | C27: =$T$9 -> 1517.9455 | D27: =F26*$T$4 -> 1317.4061 | E27: =C27-D27 -> 200.53945 | F27: =F26-E27 -> 225640.5 | H27: =IF(Principal!$D$25="Anual",IF(MOD(B27+1,12)=0,$W$2*((1+$W$3)^M27),0),$W$2*((1+$W$3)^M27)/12) -> 352.08456 | I27: =C27+H27+$W$5 -> 2117.202 | J27: =SUM($I$14:I27) -> 27497.208 | K27: =IF(J27>=$W$6,0,$W$5) -> 247.17192 | L27: =IF(K27=$W$5,I27,I27-$W$5) -> 2117.202 | M27: =ROUNDDOWN(B27/12,0) -> 1 | O27: =IF(Principal!$D$30="Anual",IF(MOD(B27+1,12)=0,VLOOKUP(M27,'Flujos Anuales'!$B$8:$K$39,9),0),VLOOKUP(M27,'Flujos Anuales'!$B$8:$K$39,9)/12) -> 217.76179 | P27: =VLOOKUP(M27,'Flujos Anuales'!$B$8:$K$39,10)/12 -> 35.0975 | Q27: =L27+O27+P27 -> 2370.0613
B28: 14 | C28: =$T$9 -> 1517.9455 | D28: =F27*$T$4 -> 1316.2363 | E28: =C28-D28 -> 201.70926 | F28: =F27-E28 -> 225438.79 | H28: =IF(Principal!$D$25="Anual",IF(MOD(B28+1,12)=0,$W$2*((1+$W$3)^M28),0),$W$2*((1+$W$3)^M28)/12) -> 352.08456 | I28: =C28+H28+$W$5 -> 2117.202 | J28: =SUM($I$14:I28) -> 29614.41 | K28: =IF(J28>=$W$6,0,$W$5) -> 247.17192 | L28: =IF(K28=$W$5,I28,I28-$W$5) -> 2117.202 | M28: =ROUNDDOWN(B28/12,0) -> 1 | O28: =IF(Principal!$D$30="Anual",IF(MOD(B28+1,12)=0,VLOOKUP(M28,'Flujos Anuales'!$B$8:$K$39,9),0),VLOOKUP(M28,'Flujos Anuales'!$B$8:$K$39,9)/12) -> 217.76179 | P28: =VLOOKUP(M28,'Flujos Anuales'!$B$8:$K$39,10)/12 -> 35.0975 | Q28: =L28+O28+P28 -> 2370.0613
B29: 15 | C29: =$T$9 -> 1517.9455 | D29: =F28*$T$4 -> 1315.0596 | E29: =C29-D29 -> 202.8859 | F29: =F28-E29 -> 225235.91 | H29: =IF(Principal!$D$25="Anual",IF(MOD(B29+1,12)=0,$W$2*((1+$W$3)^M29),0),$W$2*((1+$W$3)^M29)/12) -> 352.08456 | I29: =C29+H29+$W$5 -> 2117.202 | J29: =SUM($I$14:I29) -> 31731.612 | K29: =IF(J29>=$W$6,0,$W$5) -> 247.17192 | L29: =IF(K29=$W$5,I29,I29-$W$5) -> 2117.202 | M29: =ROUNDDOWN(B29/12,0) -> 1 | O29: =IF(Principal!$D$30="Anual",IF(MOD(B29+1,12)=0,VLOOKUP(M29,'Flujos Anuales'!$B$8:$K$39,9),0),VLOOKUP(M29,'Flujos Anuales'!$B$8:$K$39,9)/12) -> 217.76179 | P29: =VLOOKUP(M29,'Flujos Anuales'!$B$8:$K$39,10)/12 -> 35.0975 | Q29: =L29+O29+P29 -> 2370.0613
B30: 16 | C30: =$T$9 -> 1517.9455 | D30: =F29*$T$4 -> 1313.8761 | E30: =C30-D30 -> 204.0694 | F30: =F29-E30 -> 225031.84 | H30: =IF(Principal!$D$25="Anual",IF(MOD(B30+1,12)=0,$W$2*((1+$W$3)^M30),0),$W$2*((1+$W$3)^M30)/12) -> 352.08456 | I30: =C30+H30+$W$5 -> 2117.202 | J30: =SUM($I$14:I30) -> 33848.814 | K30: =IF(J30>=$W$6,0,$W$5) -> 247.17192 | L30: =IF(K30=$W$5,I30,I30-$W$5) -> 2117.202 | M30: =ROUNDDOWN(B30/12,0) -> 1 | O30: =IF(Principal!$D$30="Anual",IF(MOD(B30+1,12)=0,VLOOKUP(M30,'Flujos Anuales'!$B$8:$K$39,9),0),VLOOKUP(M30,'Flujos Anuales'!$B$8:$K$39,9)/12) -> 217.76179 | P30: =VLOOKUP(M30,'Flujos Anuales'!$B$8:$K$39,10)/12 -> 35.0975 | Q30: =L30+O30+P30 -> 2370.0613
B31: 17 | C31: =$T$9 -> 1517.9455 | D31: =F30*$T$4 -> 1312.6857 | E31: =C31-D31 -> 205.25981 | F31: =F30-E31 -> 224826.58 | H31: =IF(Principal!$D$25="Anual",IF(MOD(B31+1,12)=0,$W$2*((1+$W$3)^M31),0),$W$2*((1+$W$3)^M31)/12) -> 352.08456 | I31: =C31+H31+$W$5 -> 2117.202 | J31: =SUM($I$14:I31) -> 35966.016 | K31: =IF(J31>=$W$6,0,$W$5) -> 247.17192 | L31: =IF(K31=$W$5,I31,I31-$W$5) -> 2117.202 | M31: =ROUNDDOWN(B31/12,0) -> 1 | O31: =IF(Principal!$D$30="Anual",IF(MOD(B31+1,12)=0,VLOOKUP(M31,'Flujos Anuales'!$B$8:$K$39,9),0),VLOOKUP(M31,'Flujos Anuales'!$B$8:$K$39,9)/12) -> 217.76179 | P31: =VLOOKUP(M31,'Flujos Anuales'!$B$8:$K$39,10)/12 -> 35.0975 | Q31: =L31+O31+P31 -> 2370.0613
B32: 18 | C32: =$T$9 -> 1517.9455 | D32: =F31*$T$4 -> 1311.4884 | E32: =C32-D32 -> 206.45715 | F32: =F31-E32 -> 224620.12 | H32: =IF(Principal!$D$25="Anual",IF(MOD(B32+1,12)=0,$W$2*((1+$W$3)^M32),0),$W$2*((1+$W$3)^M32)/12) -> 352.08456 | I32: =C32+H32+$W$5 -> 2117.202 | J32: =SUM($I$14:I32) -> 38083.218 | K32: =IF(J32>=$W$6,0,$W$5) -> 247.17192 | L32: =IF(K32=$W$5,I32,I32-$W$5) -> 2117.202 | M32: =ROUNDDOWN(B32/12,0) -> 1 | O32: =IF(Principal!$D$30="Anual",IF(MOD(B32+1,12)=0,VLOOKUP(M32,'Flujos Anuales'!$B$8:$K$39,9),0),VLOOKUP(M32,'Flujos Anuales'!$B$8:$K$39,9)/12) -> 217.76179 | P32: =VLOOKUP(M32,'Flujos Anuales'!$B$8:$K$39,10)/12 -> 35.0975 | Q32: =L32+O32+P32 -> 2370.0613
B33: 19 | C33: =$T$9 -> 1517.9455 | D33: =F32*$T$4 -> 1310.284 | E33: =C33-D33 -> 207.66149 | F33: =F32-E33 -> 224412.46 | H33: =IF(Principal!$D$25="Anual",IF(MOD(B33+1,12)=0,$W$2*((1+$W$3)^M33),0),$W$2*((1+$W$3)^M33)/12) -> 352.08456 | I33: =C33+H33+$W$5 -> 2117.202 | J33: =SUM($I$14:I33) -> 40200.42 | K33: =IF(J33>=$W$6,0,$W$5) -> 247.17192 | L33: =IF(K33=$W$5,I33,I33-$W$5) -> 2117.202 | M33: =ROUNDDOWN(B33/12,0) -> 1 | O33: =IF(Principal!$D$30="Anual",IF(MOD(B33+1,12)=0,VLOOKUP(M33,'Flujos Anuales'!$B$8:$K$39,9),0),VLOOKUP(M33,'Flujos Anuales'!$B$8:$K$39,9)/12) -> 217.76179 | P33: =VLOOKUP(M33,'Flujos Anuales'!$B$8:$K$39,10)/12 -> 35.0975 | Q33: =L33+O33+P33 -> 2370.0613
B34: 20 | C34: =$T$9 -> 1517.9455 | D34: =F33*$T$4 -> 1309.0727 | E34: =C34-D34 -> 208.87285 | F34: =F33-E34 -> 224203.59 | H34: =IF(Principal!$D$25="Anual",IF(MOD(B34+1,12)=0,$W$2*((1+$W$3)^M34),0),$W$2*((1+$W$3)^M34)/12) -> 352.08456 | I34: =C34+H34+$W$5 -> 2117.202 | J34: =SUM($I$14:I34) -> 42317.622 | K34: =IF(J34>=$W$6,0,$W$5) -> 247.17192 | L34: =IF(K34=$W$5,I34,I34-$W$5) -> 2117.202 | M34: =ROUNDDOWN(B34/12,0) -> 1 | O34: =IF(Principal!$D$30="Anual",IF(MOD(B34+1,12)=0,VLOOKUP(M34,'Flujos Anuales'!$B$8:$K$39,9),0),VLOOKUP(M34,'Flujos Anuales'!$B$8:$K$39,9)/12) -> 217.76179 | P34: =VLOOKUP(M34,'Flujos Anuales'!$B$8:$K$39,10)/12 -> 35.0975 | Q34: =L34+O34+P34 -> 2370.0613
B35: 21 | C35: =$T$9 -> 1517.9455 | D35: =F34*$T$4 -> 1307.8543 | E35: =C35-D35 -> 210.09127 | F35: =F34-E35 -> 223993.49 | H35: =IF(Principal!$D$25="Anual",IF(MOD(B35+1,12)=0,$W$2*((1+$W$3)^M35),0),$W$2*((1+$W$3)^M35)/12) -> 352.08456 | I35: =C35+H35+$W$5 -> 2117.202 | J35: =SUM($I$14:I35) -> 44434.824 | K35: =IF(J35>=$W$6,0,$W$5) -> 247.17192 | L35: =IF(K35=$W$5,I35,I35-$W$5) -> 2117.202 | M35: =ROUNDDOWN(B35/12,0) -> 1 | O35: =IF(Principal!$D$30="Anual",IF(MOD(B35+1,12)=0,VLOOKUP(M35,'Flujos Anuales'!$B$8:$K$39,9),0),VLOOKUP(M35,'Flujos Anuales'!$B$8:$K$39,9)/12) -> 217.76179 | P35: =VLOOKUP(M35,'Flujos Anuales'!$B$8:$K$39,10)/12 -> 35.0975 | Q35: =L35+O35+P35 -> 2370.0613
B36: 22 | C36: =$T$9 -> 1517.9455 | D36: =F35*$T$4 -> 1306.6287 | E36: =C36-D36 -> 211.3168 | F36: =F35-E36 -> 223782.18 | H36: =IF(Principal!$D$25="Anual",IF(MOD(B36+1,12)=0,$W$2*((1+$W$3)^M36),0),$W$2*((1+$W$3)^M36)/12) -> 352.08456 | I36: =C36+H36+$W$5 -> 2117.202 | J36: =SUM($I$14:I36) -> 46552.026 | K36: =IF(J36>=$W$6,0,$W$5) -> 247.17192 | L36: =IF(K36=$W$5,I36,I36-$W$5) -> 2117.202 | M36: =ROUNDDOWN(B36/12,0) -> 1 | O36: =IF(Principal!$D$30="Anual",IF(MOD(B36+1,12)=0,VLOOKUP(M36,'Flujos Anuales'!$B$8:$K$39,9),0),VLOOKUP(M36,'Flujos Anuales'!$B$8:$K$39,9)/12) -> 217.76179 | P36: =VLOOKUP(M36,'Flujos Anuales'!$B$8:$K$39,10)/12 -> 35.0975 | Q36: =L36+O36+P36 -> 2370.0613
B37: 23 | C37: =$T$9 -> 1517.9455 | D37: =F36*$T$4 -> 1305.396 | E37: =C37-D37 -> 212.54949 | F37: =F36-E37 -> 223569.63 | H37: =IF(Principal!$D$25="Anual",IF(MOD(B37+1,12)=0,$W$2*((1+$W$3)^M37),0),$W$2*((1+$W$3)^M37)/12) -> 352.08456 | I37: =C37+H37+$W$5 -> 2117.202 | J37: =SUM($I$14:I37) -> 48669.228 | K37: =IF(J37>=$W$6,0,$W$5) -> 247.17192 | L37: =IF(K37=$W$5,I37,I37-$W$5) -> 2117.202 | M37: =ROUNDDOWN(B37/12,0) -> 1 | O37: =IF(Principal!$D$30="Anual",IF(MOD(B37+1,12)=0,VLOOKUP(M37,'Flujos Anuales'!$B$8:$K$39,9),0),VLOOKUP(M37,'Flujos Anuales'!$B$8:$K$39,9)/12) -> 217.76179 | P37: =VLOOKUP(M37,'Flujos Anuales'!$B$8:$K$39,10)/12 -> 35.0975 | Q37: =L37+O37+P37 -> 2370.0613
B38: 24 | C38: =$T$9 -> 1517.9455 | D38: =F37*$T$4 -> 1304.1562 | E38: =C38-D38 -> 213.78936 | F38: =F37-E38 -> 223355.84 | H38: =IF(Principal!$D$25="Anual",IF(MOD(B38+1,12)=0,$W$2*((1+$W$3)^M38),0),$W$2*((1+$W$3)^M38)/12) -> 354.50271 | I38: =C38+H38+$W$5 -> 2119.6202 | J38: =SUM($I$14:I38) -> 50788.848 | K38: =IF(J38>=$W$6,0,$W$5) -> 247.17192 | L38: =IF(K38=$W$5,I38,I38-$W$5) -> 2119.6202 | M38: =ROUNDDOWN(B38/12,0) -> 2 | N38: =SUM(L38:L49) -> 22963.723 | O38: =IF(Principal!$D$30="Anual",IF(MOD(B38+1,12)=0,VLOOKUP(M38,'Flujos Anuales'!$B$8:$K$39,9),0),VLOOKUP(M38,'Flujos Anuales'!$B$8:$K$39,9)/12) -> 227.70803 | P38: =VLOOKUP(M38,'Flujos Anuales'!$B$8:$K$39,10)/12 -> 35.448475 | Q38: =L38+O38+P38 -> 2382.7767
B39: 25 | C39: =$T$9 -> 1517.9455 | D39: =F38*$T$4 -> 1302.9091 | E39: =C39-D39 -> 215.03646 | F39: =F38-E39 -> 223140.8 | H39: =IF(Principal!$D$25="Anual",IF(MOD(B39+1,12)=0,$W$2*((1+$W$3)^M39),0),$W$2*((1+$W$3)^M39)/12) -> 354.50271 | I39: =C39+H39+$W$5 -> 2119.6202 | J39: =SUM($I$14:I39) -> 52908.468 | K39: =IF(J39>=$W$6,0,$W$5) -> 247.17192 | L39: =IF(K39=$W$5,I39,I39-$W$5) -> 2119.6202 | M39: =ROUNDDOWN(B39/12,0) -> 2 | O39: =IF(Principal!$D$30="Anual",IF(MOD(B39+1,12)=0,VLOOKUP(M39,'Flujos Anuales'!$B$8:$K$39,9),0),VLOOKUP(M39,'Flujos Anuales'!$B$8:$K$39,9)/12) -> 227.70803 | P39: =VLOOKUP(M39,'Flujos Anuales'!$B$8:$K$39,10)/12 -> 35.448475 | Q39: =L39+O39+P39 -> 2382.7767
B40: 26 | C40: =$T$9 -> 1517.9455 | D40: =F39*$T$4 -> 1301.6547 | E40: =C40-D40 -> 216.29084 | F40: =F39-E40 -> 222924.51 | H40: =IF(Principal!$D$25="Anual",IF(MOD(B40+1,12)=0,$W$2*((1+$W$3)^M40),0),$W$2*((1+$W$3)^M40)/12) -> 354.50271 | I40: =C40+H40+$W$5 -> 2119.6202 | J40: =SUM($I$14:I40) -> 55028.089 | K40: =IF(J40>=$W$6,0,$W$5) -> 0 | L40: =IF(K40=$W$5,I40,I40-$W$5) -> 1872.4482 | M40: =ROUNDDOWN(B40/12,0) -> 2 | O40: =IF(Principal!$D$30="Anual",IF(MOD(B40+1,12)=0,VLOOKUP(M40,'Flujos Anuales'!$B$8:$K$39,9),0),VLOOKUP(M40,'Flujos Anuales'!$B$8:$K$39,9)/12) -> 227.70803 | P40: =VLOOKUP(M40,'Flujos Anuales'!$B$8:$K$39,10)/12 -> 35.448475 | Q40: =L40+O40+P40 -> 2135.6047
B41: 27 | C41: =$T$9 -> 1517.9455 | D41: =F40*$T$4 -> 1300.393 | E41: =C41-D41 -> 217.55254 | F41: =F40-E41 -> 222706.96 | H41: =IF(Principal!$D$25="Anual",IF(MOD(B41+1,12)=0,$W$2*((1+$W$3)^M41),0),$W$2*((1+$W$3)^M41)/12) -> 354.50271 | I41: =C41+H41+$W$5 -> 2119.6202 | J41: =SUM($I$14:I41) -> 57147.709 | K41: =IF(J41>=$W$6,0,$W$5) -> 0 | L41: =IF(K41=$W$5,I41,I41-$W$5) -> 1872.4482 | M41: =ROUNDDOWN(B41/12,0) -> 2 | O41: =IF(Principal!$D$30="Anual",IF(MOD(B41+1,12)=0,VLOOKUP(M41,'Flujos Anuales'!$B$8:$K$39,9),0),VLOOKUP(M41,'Flujos Anuales'!$B$8:$K$39,9)/12) -> 227.70803 | P41: =VLOOKUP(M41,'Flujos Anuales'!$B$8:$K$39,10)/12 -> 35.448475 | Q41: =L41+O41+P41 -> 2135.6047
B42: 28 | C42: =$T$9 -> 1517.9455 | D42: =F41*$T$4 -> 1299.1239 | E42: =C42-D42 -> 218.82159 | F42: =F41-E42 -> 222488.14 | H42: =IF(Principal!$D$25="Anual",IF(MOD(B42+1,12)=0,$W$2*((1+$W$3)^M42),0),$W$2*((1+$W$3)^M42)/12) -> 354.50271 | I42: =C42+H42+$W$5 -> 2119.6202 | J42: =SUM($I$14:I42) -> 59267.329 | K42: =IF(J42>=$W$6,0,$W$5) -> 0 | L42: =IF(K42=$W$5,I42,I42-$W$5) -> 1872.4482 | M42: =ROUNDDOWN(B42/12,0) -> 2 | O42: =IF(Principal!$D$30="Anual",IF(MOD(B42+1,12)=0,VLOOKUP(M42,'Flujos Anuales'!$B$8:$K$39,9),0),VLOOKUP(M42,'Flujos Anuales'!$B$8:$K$39,9)/12) -> 227.70803 | P42: =VLOOKUP(M42,'Flujos Anuales'!$B$8:$K$39,10)/12 -> 35.448475 | Q42: =L42+O42+P42 -> 2135.6047
B43: 29 | C43: =$T$9 -> 1517.9455 | D43: =F42*$T$4 -> 1297.8475 | E43: =C43-D43 -> 220.09805 | F43: =F42-E43 -> 222268.04 | H43: =IF(Principal!$D$25="Anual",IF(MOD(B43+1,12)=0,$W$2*((1+$W$3)^M43),0),$W$2*((1+$W$3)^M43)/12) -> 354.50271 | I43: =C43+H43+$W$5 -> 2119.6202 | J43: =SUM($I$14:I43) -> 61386.949 | K43: =IF(J43>=$W$6,0,$W$5) -> 0 | L43: =IF(K43=$W$5,I43,I43-$W$5) -> 1872.4482 | M43: =ROUNDDOWN(B43/12,0) -> 2 | O43: =IF(Principal!$D$30="Anual",IF(MOD(B43+1,12)=0,VLOOKUP(M43,'Flujos Anuales'!$B$8:$K$39,9),0),VLOOKUP(M43,'Flujos Anuales'!$B$8:$K$39,9)/12) -> 227.70803 | P43: =VLOOKUP(M43,'Flujos Anuales'!$B$8:$K$39,10)/12 -> 35.448475 | Q43: =L43+O43+P43 -> 2135.6047
B44: 30 | C44: =$T$9 -> 1517.9455 | D44: =F43*$T$4 -> 1296.5636 | E44: =C44-D44 -> 221.38196 | F44: =F43-E44 -> 222046.66 | H44: =IF(Principal!$D$25="Anual",IF(MOD(B44+1,12)=0,$W$2*((1+$W$3)^M44),0),$W$2*((1+$W$3)^M44)/12) -> 354.50271 | I44: =C44+H44+$W$5 -> 2119.6202 | J44: =SUM($I$14:I44) -> 63506.569 | K44: =IF(J44>=$W$6,0,$W$5) -> 0 | L44: =IF(K44=$W$5,I44,I44-$W$5) -> 1872.4482 | M44: =ROUNDDOWN(B44/12,0) -> 2 | O44: =IF(Principal!$D$30="Anual",IF(MOD(B44+1,12)=0,VLOOKUP(M44,'Flujos Anuales'!$B$8:$K$39,9),0),VLOOKUP(M44,'Flujos Anuales'!$B$8:$K$39,9)/12) -> 227.70803 | P44: =VLOOKUP(M44,'Flujos Anuales'!$B$8:$K$39,10)/12 -> 35.448475 | Q44: =L44+O44+P44 -> 2135.6047
B45: 31 | C45: =$T$9 -> 1517.9455 | D45: =F44*$T$4 -> 1295.2722 | E45: =C45-D45 -> 222.67335 | F45: =F44-E45 -> 221823.98 | H45: =IF(Principal!$D$25="Anual",IF(MOD(B45+1,12)=0,$W$2*((1+$W$3)^M45),0),$W$2*((1+$W$3)^M45)/12) -> 354.50271 | I45: =C45+H45+$W$5 -> 2119.6202 | J45: =SUM($I$14:I45) -> 65626.189 | K45: =IF(J45>=$W$6,0,$W$5) -> 0 | L45: =IF(K45=$W$5,I45,I45-$W$5) -> 1872.4482 | M45: =ROUNDDOWN(B45/12,0) -> 2 | O45: =IF(Principal!$D$30="Anual",IF(MOD(B45+1,12)=0,VLOOKUP(M45,'Flujos Anuales'!$B$8:$K$39,9),0),VLOOKUP(M45,'Flujos Anuales'!$B$8:$K$39,9)/12) -> 227.70803 | P45: =VLOOKUP(M45,'Flujos Anuales'!$B$8:$K$39,10)/12 -> 35.448475 | Q45: =L45+O45+P45 -> 2135.6047
B46: 32 | C46: =$T$9 -> 1517.9455 | D46: =F45*$T$4 -> 1293.9732 | E46: =C46-D46 -> 223.97228 | F46: =F45-E46 -> 221600.01 | H46: =IF(Principal!$D$25="Anual",IF(MOD(B46+1,12)=0,$W$2*((1+$W$3)^M46),0),$W$2*((1+$W$3)^M46)/12) -> 354.50271 | I46: =C46+H46+$W$5 -> 2119.6202 | J46: =SUM($I$14:I46) -> 67745.809 | K46: =IF(J46>=$W$6,0,$W$5) -> 0 | L46: =IF(K46=$W$5,I46,I46-$W$5) -> 1872.4482 | M46: =ROUNDDOWN(B46/12,0) -> 2 | O46: =IF(Principal!$D$30="Anual",IF(MOD(B46+1,12)=0,VLOOKUP(M46,'Flujos Anuales'!$B$8:$K$39,9),0),VLOOKUP(M46,'Flujos Anuales'!$B$8:$K$39,9)/12) -> 227.70803 | P46: =VLOOKUP(M46,'Flujos Anuales'!$B$8:$K$39,10)/12 -> 35.448475 | Q46: =L46+O46+P46 -> 2135.6047
B47: 33 | C47: =$T$9 -> 1517.9455 | D47: =F46*$T$4 -> 1292.6667 | E47: =C47-D47 -> 225.27879 | F47: =F46-E47 -> 221374.73 | H47: =IF(Principal!$D$25="Anual",IF(MOD(B47+1,12)=0,$W$2*((1+$W$3)^M47),0),$W$2*((1+$W$3)^M47)/12) -> 354.50271 | I47: =C47+H47+$W$5 -> 2119.6202 | J47: =SUM($I$14:I47) -> 69865.43 | K47: =IF(J47>=$W$6,0,$W$5) -> 0 | L47: =IF(K47=$W$5,I47,I47-$W$5) -> 1872.4482 | M47: =ROUNDDOWN(B47/12,0) -> 2 | O47: =IF(Principal!$D$30="Anual",IF(MOD(B47+1,12)=0,VLOOKUP(M47,'Flujos Anuales'!$B$8:$K$39,9),0),VLOOKUP(M47,'Flujos Anuales'!$B$8:$K$39,9)/12) -> 227.70803 | P47: =VLOOKUP(M47,'Flujos Anuales'!$B$8:$K$39,10)/12 -> 35.448475 | Q47: =L47+O47+P47 -> 2135.6047
B48: 34 | C48: =$T$9 -> 1517.9455 | D48: =F47*$T$4 -> 1291.3526 | E48: =C48-D48 -> 226.59291 | F48: =F47-E48 -> 221148.14 | H48: =IF(Principal!$D$25="Anual",IF(MOD(B48+1,12)=0,$W$2*((1+$W$3)^M48),0),$W$2*((1+$W$3)^M48)/12) -> 354.50271 | I48: =C48+H48+$W$5 -> 2119.6202 | J48: =SUM($I$14:I48) -> 71985.05 | K48: =IF(J48>=$W$6,0,$W$5) -> 0 | L48: =IF(K48=$W$5,I48,I48-$W$5) -> 1872.4482 | M48: =ROUNDDOWN(B48/12,0) -> 2 | O48: =IF(Principal!$D$30="Anual",IF(MOD(B48+1,12)=0,VLOOKUP(M48,'Flujos Anuales'!$B$8:$K$39,9),0),VLOOKUP(M48,'Flujos Anuales'!$B$8:$K$39,9)/12) -> 227.70803 | P48: =VLOOKUP(M48,'Flujos Anuales'!$B$8:$K$39,10)/12 -> 35.448475 | Q48: =L48+O48+P48 -> 2135.6047
B49: 35 | C49: =$T$9 -> 1517.9455 | D49: =F48*$T$4 -> 1290.0308 | E49: =C49-D49 -> 227.9147 | F49: =F48-E49 -> 220920.23 | H49: =IF(Principal!$D$25="Anual",IF(MOD(B49+1,12)=0,$W$2*((1+$W$3)^M49),0),$W$2*((1+$W$3)^M49)/12) -> 354.50271 | I49: =C49+H49+$W$5 -> 2119.6202 | J49: =SUM($I$14:I49) -> 74104.67 | K49: =IF(J49>=$W$6,0,$W$5) -> 0 | L49: =IF(K49=$W$5,I49,I49-$W$5) -> 1872.4482 | M49: =ROUNDDOWN(B49/12,0) -> 2 | O49: =IF(Principal!$D$30="Anual",IF(MOD(B49+1,12)=0,VLOOKUP(M49,'Flujos Anuales'!$B$8:$K$39,9),0),VLOOKUP(M49,'Flujos Anuales'!$B$8:$K$39,9)/12) -> 227.70803 | P49: =VLOOKUP(M49,'Flujos Anuales'!$B$8:$K$39,10)/12 -> 35.448475 | Q49: =L49+O49+P49 -> 2135.6047
B50: 36 | C50: =$T$9 -> 1517.9455 | D50: =F49*$T$4 -> 1288.7013 | E50: =C50-D50 -> 229.24421 | F50: =F49-E50 -> 220690.98 | H50: =IF(Principal!$D$25="Anual",IF(MOD(B50+1,12)=0,$W$2*((1+$W$3)^M50),0),$W$2*((1+$W$3)^M50)/12) -> 356.93747 | I50: =C50+H50+$W$5 -> 2122.0549 | J50: =SUM($I$14:I50) -> 76226.725 | K50: =IF(J50>=$W$6,0,$W$5) -> 0 | L50: =IF(K50=$W$5,I50,I50-$W$5) -> 1874.883 | M50: =ROUNDDOWN(B50/12,0) -> 3 | N50: =SUM(L50:L61) -> 22498.596 | O50: =IF(Principal!$D$30="Anual",IF(MOD(B50+1,12)=0,VLOOKUP(M50,'Flujos Anuales'!$B$8:$K$39,9),0),VLOOKUP(M50,'Flujos Anuales'!$B$8:$K$39,9)/12) -> 238.10856 | P50: =VLOOKUP(M50,'Flujos Anuales'!$B$8:$K$39,10)/12 -> 35.80296 | Q50: =L50+O50+P50 -> 2148.7945
B51: 37 | C51: =$T$9 -> 1517.9455 | D51: =F50*$T$4 -> 1287.3641 | E51: =C51-D51 -> 230.58146 | F51: =F50-E51 -> 220460.4 | H51: =IF(Principal!$D$25="Anual",IF(MOD(B51+1,12)=0,$W$2*((1+$W$3)^M51),0),$W$2*((1+$W$3)^M51)/12) -> 356.93747 | I51: =C51+H51+$W$5 -> 2122.0549 | J51: =SUM($I$14:I51) -> 78348.78 | K51: =IF(J51>=$W$6,0,$W$5) -> 0 | L51: =IF(K51=$W$5,I51,I51-$W$5) -> 1874.883 | M51: =ROUNDDOWN(B51/12,0) -> 3 | O51: =IF(Principal!$D$30="Anual",IF(MOD(B51+1,12)=0,VLOOKUP(M51,'Flujos Anuales'!$B$8:$K$39,9),0),VLOOKUP(M51,'Flujos Anuales'!$B$8:$K$39,9)/12) -> 238.10856 | P51: =VLOOKUP(M51,'Flujos Anuales'!$B$8:$K$39,10)/12 -> 35.80296 | Q51: =L51+O51+P51 -> 2148.7945
B52: 38 | C52: =$T$9 -> 1517.9455 | D52: =F51*$T$4 -> 1286.019 | E52: =C52-D52 -> 231.92652 | F52: =F51-E52 -> 220228.47 | H52: =IF(Principal!$D$25="Anual",IF(MOD(B52+1,12)=0,$W$2*((1+$W$3)^M52),0),$W$2*((1+$W$3)^M52)/12) -> 356.93747 | I52: =C52+H52+$W$5 -> 2122.0549 | J52: =SUM($I$14:I52) -> 80470.835 | K52: =IF(J52>=$W$6,0,$W$5) -> 0 | L52: =IF(K52=$W$5,I52,I52-$W$5) -> 1874.883 | M52: =ROUNDDOWN(B52/12,0) -> 3 | O52: =IF(Principal!$D$30="Anual",IF(MOD(B52+1,12)=0,VLOOKUP(M52,'Flujos Anuales'!$B$8:$K$39,9),0),VLOOKUP(M52,'Flujos Anuales'!$B$8:$K$39,9)/12) -> 238.10856 | P52: =VLOOKUP(M52,'Flujos Anuales'!$B$8:$K$39,10)/12 -> 35.80296 | Q52: =L52+O52+P52 -> 2148.7945
B53: 39 | C53: =$T$9 -> 1517.9455 | D53: =F52*$T$4 -> 1284.6661 | E53: =C53-D53 -> 233.27943 | F53: =F52-E53 -> 219995.19 | H53: =IF(Principal!$D$25="Anual",IF(MOD(B53+1,12)=0,$W$2*((1+$W$3)^M53),0),$W$2*((1+$W$3)^M53)/12) -> 356.93747 | I53: =C53+H53+$W$5 -> 2122.0549 | J53: =SUM($I$14:I53) -> 82592.89 | K53: =IF(J53>=$W$6,0,$W$5) -> 0 | L53: =IF(K53=$W$5,I53,I53-$W$5) -> 1874.883 | M53: =ROUNDDOWN(B53/12,0) -> 3 | O53: =IF(Principal!$D$30="Anual",IF(MOD(B53+1,12)=0,VLOOKUP(M53,'Flujos Anuales'!$B$8:$K$39,9),0),VLOOKUP(M53,'Flujos Anuales'!$B$8:$K$39,9)/12) -> 238.10856 | P53: =VLOOKUP(M53,'Flujos Anuales'!$B$8:$K$39,10)/12 -> 35.80296 | Q53: =L53+O53+P53 -> 2148.7945
B54: 40 | C54: =$T$9 -> 1517.9455 | D54: =F53*$T$4 -> 1283.3053 | E54: =C54-D54 -> 234.64022 | F54: =F53-E54 -> 219760.55 | H54: =IF(Principal!$D$25="Anual",IF(MOD(B54+1,12)=0,$W$2*((1+$W$3)^M54),0),$W$2*((1+$W$3)^M54)/12) -> 356.93747 | I54: =C54+H54+$W$5 -> 2122.0549 | J54: =SUM($I$14:I54) -> 84714.945 | K54: =IF(J54>=$W$6,0,$W$5) -> 0 | L54: =IF(K54=$W$5,I54,I54-$W$5) -> 1874.883 | M54: =ROUNDDOWN(B54/12,0) -> 3 | O54: =IF(Principal!$D$30="Anual",IF(MOD(B54+1,12)=0,VLOOKUP(M54,'Flujos Anuales'!$B$8:$K$39,9),0),VLOOKUP(M54,'Flujos Anuales'!$B$8:$K$39,9)/12) -> 238.10856 | P54: =VLOOKUP(M54,'Flujos Anuales'!$B$8:$K$39,10)/12 -> 35.80296 | Q54: =L54+O54+P54 -> 2148.7945
B55: 41 | C55: =$T$9 -> 1517.9455 | D55: =F54*$T$4 -> 1281.9366 | E55: =C55-D55 -> 236.00896 | F55: =F54-E55 -> 219524.54 | H55: =IF(Principal!$D$25="Anual",IF(MOD(B55+1,12)=0,$W$2*((1+$W$3)^M55),0),$W$2*((1+$W$3)^M55)/12) -> 356.93747 | I55: =C55+H55+$W$5 -> 2122.0549 | J55: =SUM($I$14:I55) -> 86836.999 | K55: =IF(J55>=$W$6,0,$W$5) -> 0 | L55: =IF(K55=$W$5,I55,I55-$W$5) -> 1874.883 | M55: =ROUNDDOWN(B55/12,0) -> 3 | O55: =IF(Principal!$D$30="Anual",IF(MOD(B55+1,12)=0,VLOOKUP(M55,'Flujos Anuales'!$B$8:$K$39,9),0),VLOOKUP(M55,'Flujos Anuales'!$B$8:$K$39,9)/12) -> 238.10856 | P55: =VLOOKUP(M55,'Flujos Anuales'!$B$8:$K$39,10)/12 -> 35.80296 | Q55: =L55+O55+P55 -> 2148.7945
B56: 42 | C56: =$T$9 -> 1517.9455 | D56: =F55*$T$4 -> 1280.5598 | E56: =C56-D56 -> 237.38568 | F56: =F55-E56 -> 219287.16 | H56: =IF(Principal!$D$25="Anual",IF(MOD(B56+1,12)=0,$W$2*((1+$W$3)^M56),0),$W$2*((1+$W$3)^M56)/12) -> 356.93747 | I56: =C56+H56+$W$5 -> 2122.0549 | J56: =SUM($I$14:I56) -> 88959.054 | K56: =IF(J56>=$W$6,0,$W$5) -> 0 | L56: =IF(K56=$W$5,I56,I56-$W$5) -> 1874.883 | M56: =ROUNDDOWN(B56/12,0) -> 3 | O56: =IF(Principal!$D$30="Anual",IF(MOD(B56+1,12)=0,VLOOKUP(M56,'Flujos Anuales'!$B$8:$K$39,9),0),VLOOKUP(M56,'Flujos Anuales'!$B$8:$K$39,9)/12) -> 238.10856 | P56: =VLOOKUP(M56,'Flujos Anuales'!$B$8:$K$39,10)/12 -> 35.80296 | Q56: =L56+O56+P56 -> 2148.7945
B57: 43 | C57: =$T$9 -> 1517.9455 | D57: =F56*$T$4 -> 1279.1751 | E57: =C57-D57 -> 238.77043 | F57: =F56-E57 -> 219048.39 | H57: =IF(Principal!$D$25="Anual",IF(MOD(B57+1,12)=0,$W$2*((1+$W$3)^M57),0),$W$2*((1+$W$3)^M57)/12) -> 356.93747 | I57: =C57+H57+$W$5 -> 2122.0549 | J57: =SUM($I$14:I57) -> 91081.109 | K57: =IF(J57>=$W$6,0,$W$5) -> 0 | L57: =IF(K57=$W$5,I57,I57-$W$5) -> 1874.883 | M57: =ROUNDDOWN(B57/12,0) -> 3 | O57: =IF(Principal!$D$30="Anual",IF(MOD(B57+1,12)=0,VLOOKUP(M57,'Flujos Anuales'!$B$8:$K$39,9),0),VLOOKUP(M57,'Flujos Anuales'!$B$8:$K$39,9)/12) -> 238.10856 | P57: =VLOOKUP(M57,'Flujos Anuales'!$B$8:$K$39,10)/12 -> 35.80296 | Q57: =L57+O57+P57 -> 2148.7945
B58: 44 | C58: =$T$9 -> 1517.9455 | D58: =F57*$T$4 -> 1277.7823 | E58: =C58-D58 -> 240.16326 | F58: =F57-E58 -> 218808.23 | H58: =IF(Principal!$D$25="Anual",IF(MOD(B58+1,12)=0,$W$2*((1+$W$3)^M58),0),$W$2*((1+$W$3)^M58)/12) -> 356.93747 | I58: =C58+H58+$W$5 -> 2122.0549 | J58: =SUM($I$14:I58) -> 93203.164 | K58: =IF(J58>=$W$6,0,$W$5) -> 0 | L58: =IF(K58=$W$5,I58,I58-$W$5) -> 1874.883 | M58: =ROUNDDOWN(B58/12,0) -> 3 | O58: =IF(Principal!$D$30="Anual",IF(MOD(B58+1,12)=0,VLOOKUP(M58,'Flujos Anuales'!$B$8:$K$39,9),0),VLOOKUP(M58,'Flujos Anuales'!$B$8:$K$39,9)/12) -> 238.10856 | P58: =VLOOKUP(M58,'Flujos Anuales'!$B$8:$K$39,10)/12 -> 35.80296 | Q58: =L58+O58+P58 -> 2148.7945
B59: 45 | C59: =$T$9 -> 1517.9455 | D59: =F58*$T$4 -> 1276.3813 | E59: =C59-D59 -> 241.56421 | F59: =F58-E59 -> 218566.66 | H59: =IF(Principal!$D$25="Anual",IF(MOD(B59+1,12)=0,$W$2*((1+$W$3)^M59),0),$W$2*((1+$W$3)^M59)/12) -> 356.93747 | I59: =C59+H59+$W$5 -> 2122.0549 | J59: =SUM($I$14:I59) -> 95325.219 | K59: =IF(J59>=$W$6,0,$W$5) -> 0 | L59: =IF(K59=$W$5,I59,I59-$W$5) -> 1874.883 | M59: =ROUNDDOWN(B59/12,0) -> 3 | O59: =IF(Principal!$D$30="Anual",IF(MOD(B59+1,12)=0,VLOOKUP(M59,'Flujos Anuales'!$B$8:$K$39,9),0),VLOOKUP(M59,'Flujos Anuales'!$B$8:$K$39,9)/12) -> 238.10856 | P59: =VLOOKUP(M59,'Flujos Anuales'!$B$8:$K$39,10)/12 -> 35.80296 | Q59: =L59+O59+P59 -> 2148.7945
B60: 46 | C60: =$T$9 -> 1517.9455 | D60: =F59*$T$4 -> 1274.9722 | E60: =C60-D60 -> 242.97333 | F60: =F59-E60 -> 218323.69 | H60: =IF(Principal!$D$25="Anual",IF(MOD(B60+1,12)=0,$W$2*((1+$W$3)^M60),0),$W$2*((1+$W$3)^M60)/12) -> 356.93747 | I60: =C60+H60+$W$5 -> 2122.0549 | J60: =SUM($I$14:I60) -> 97447.274 | K60: =IF(J60>=$W$6,0,$W$5) -> 0 | L60: =IF(K60=$W$5,I60,I60-$W$5) -> 1874.883 | M60: =ROUNDDOWN(B60/12,0) -> 3 | O60: =IF(Principal!$D$30="Anual",IF(MOD(B60+1,12)=0,VLOOKUP(M60,'Flujos Anuales'!$B$8:$K$39,9),0),VLOOKUP(M60,'Flujos Anuales'!$B$8:$K$39,9)/12) -> 238.10856 | P60: =VLOOKUP(M60,'Flujos Anuales'!$B$8:$K$39,10)/12 -> 35.80296 | Q60: =L60+O60+P60 -> 2148.7945
B61: 47 | C61: =$T$9 -> 1517.9455 | D61: =F60*$T$4 -> 1273.5548 | E61: =C61-D61 -> 244.39068 | F61: =F60-E61 -> 218079.3 | H61: =IF(Principal!$D$25="Anual",IF(MOD(B61+1,12)=0,$W$2*((1+$W$3)^M61),0),$W$2*((1+$W$3)^M61)/12) -> 356.93747 | I61: =C61+H61+$W$5 -> 2122.0549 | J61: =SUM($I$14:I61) -> 99569.329 | K61: =IF(J61>=$W$6,0,$W$5) -> 0 | L61: =IF(K61=$W$5,I61,I61-$W$5) -> 1874.883 | M61: =ROUNDDOWN(B61/12,0) -> 3 | O61: =IF(Principal!$D$30="Anual",IF(MOD(B61+1,12)=0,VLOOKUP(M61,'Flujos Anuales'!$B$8:$K$39,9),0),VLOOKUP(M61,'Flujos Anuales'!$B$8:$K$39,9)/12) -> 238.10856 | P61: =VLOOKUP(M61,'Flujos Anuales'!$B$8:$K$39,10)/12 -> 35.80296 | Q61: =L61+O61+P61 -> 2148.7945
B62: 48 | C62: =$T$9 -> 1517.9455 | D62: =F61*$T$4 -> 1272.1292 | E62: =C62-D62 -> 245.81629 | F62: =F61-E62 -> 217833.48 | H62: =IF(Principal!$D$25="Anual",IF(MOD(B62+1,12)=0,$W$2*((1+$W$3)^M62),0),$W$2*((1+$W$3)^M62)/12) -> 359.38894 | I62: =C62+H62+$W$5 -> 2124.5064 | J62: =SUM($I$14:I62) -> 101693.84 | K62: =IF(J62>=$W$6,0,$W$5) -> 0 | L62: =IF(K62=$W$5,I62,I62-$W$5) -> 1877.3345 | M62: =ROUNDDOWN(B62/12,0) -> 4 | N62: =SUM(L62:L73) -> 22528.014 | O62: =IF(Principal!$D$30="Anual",IF(MOD(B62+1,12)=0,VLOOKUP(M62,'Flujos Anuales'!$B$8:$K$39,9),0),VLOOKUP(M62,'Flujos Anuales'!$B$8:$K$39,9)/12) -> 248.98414 | P62: =VLOOKUP(M62,'Flujos Anuales'!$B$8:$K$39,10)/12 -> 36.160989 | Q62: =L62+O62+P62 -> 2162.4796
B63: 49 | C63: =$T$9 -> 1517.9455 | D63: =F62*$T$4 -> 1270.6953 | E63: =C63-D63 -> 247.25022 | F63: =F62-E63 -> 217586.23 | H63: =IF(Principal!$D$25="Anual",IF(MOD(B63+1,12)=0,$W$2*((1+$W$3)^M63),0),$W$2*((1+$W$3)^M63)/12) -> 359.38894 | I63: =C63+H63+$W$5 -> 2124.5064 | J63: =SUM($I$14:I63) -> 103818.34 | K63: =IF(J63>=$W$6,0,$W$5) -> 0 | L63: =IF(K63=$W$5,I63,I63-$W$5) -> 1877.3345 | M63: =ROUNDDOWN(B63/12,0) -> 4 | O63: =IF(Principal!$D$30="Anual",IF(MOD(B63+1,12)=0,VLOOKUP(M63,'Flujos Anuales'!$B$8:$K$39,9),0),VLOOKUP(M63,'Flujos Anuales'!$B$8:$K$39,9)/12) -> 248.98414 | P63: =VLOOKUP(M63,'Flujos Anuales'!$B$8:$K$39,10)/12 -> 36.160989 | Q63: =L63+O63+P63 -> 2162.4796
B64: 50 | C64: =$T$9 -> 1517.9455 | D64: =F63*$T$4 -> 1269.253 | E64: =C64-D64 -> 248.69251 | F64: =F63-E64 -> 217337.54 | H64: =IF(Principal!$D$25="Anual",IF(MOD(B64+1,12)=0,$W$2*((1+$W$3)^M64),0),$W$2*((1+$W$3)^M64)/12) -> 359.38894 | I64: =C64+H64+$W$5 -> 2124.5064 | J64: =SUM($I$14:I64) -> 105942.85 | K64: =IF(J64>=$W$6,0,$W$5) -> 0 | L64: =IF(K64=$W$5,I64,I64-$W$5) -> 1877.3345 | M64: =ROUNDDOWN(B64/12,0) -> 4 | O64: =IF(Principal!$D$30="Anual",IF(MOD(B64+1,12)=0,VLOOKUP(M64,'Flujos Anuales'!$B$8:$K$39,9),0),VLOOKUP(M64,'Flujos Anuales'!$B$8:$K$39,9)/12) -> 248.98414 | P64: =VLOOKUP(M64,'Flujos Anuales'!$B$8:$K$39,10)/12 -> 36.160989 | Q64: =L64+O64+P64 -> 2162.4796
B65: 51 | C65: =$T$9 -> 1517.9455 | D65: =F64*$T$4 -> 1267.8023 | E65: =C65-D65 -> 250.14322 | F65: =F64-E65 -> 217087.4 | H65: =IF(Principal!$D$25="Anual",IF(MOD(B65+1,12)=0,$W$2*((1+$W$3)^M65),0),$W$2*((1+$W$3)^M65)/12) -> 359.38894 | I65: =C65+H65+$W$5 -> 2124.5064 | J65: =SUM($I$14:I65) -> 108067.35 | K65: =IF(J65>=$W$6,0,$W$5) -> 0 | L65: =IF(K65=$W$5,I65,I65-$W$5) -> 1877.3345 | M65: =ROUNDDOWN(B65/12,0) -> 4 | O65: =IF(Principal!$D$30="Anual",IF(MOD(B65+1,12)=0,VLOOKUP(M65,'Flujos Anuales'!$B$8:$K$39,9),0),VLOOKUP(M65,'Flujos Anuales'!$B$8:$K$39,9)/12) -> 248.98414 | P65: =VLOOKUP(M65,'Flujos Anuales'!$B$8:$K$39,10)/12 -> 36.160989 | Q65: =L65+O65+P65 -> 2162.4796
B66: 52 | C66: =$T$9 -> 1517.9455 | D66: =F65*$T$4 -> 1266.3431 | E66: =C66-D66 -> 251.60239 | F66: =F65-E66 -> 216835.79 | H66: =IF(Principal!$D$25="Anual",IF(MOD(B66+1,12)=0,$W$2*((1+$W$3)^M66),0),$W$2*((1+$W$3)^M66)/12) -> 359.38894 | I66: =C66+H66+$W$5 -> 2124.5064 | J66: =SUM($I$14:I66) -> 110191.86 | K66: =IF(J66>=$W$6,0,$W$5) -> 0 | L66: =IF(K66=$W$5,I66,I66-$W$5) -> 1877.3345 | M66: =ROUNDDOWN(B66/12,0) -> 4 | O66: =IF(Principal!$D$30="Anual",IF(MOD(B66+1,12)=0,VLOOKUP(M66,'Flujos Anuales'!$B$8:$K$39,9),0),VLOOKUP(M66,'Flujos Anuales'!$B$8:$K$39,9)/12) -> 248.98414 | P66: =VLOOKUP(M66,'Flujos Anuales'!$B$8:$K$39,10)/12 -> 36.160989 | Q66: =L66+O66+P66 -> 2162.4796
B67: 53 | C67: =$T$9 -> 1517.9455 | D67: =F66*$T$4 -> 1264.8755 | E67: =C67-D67 -> 253.07007 | F67: =F66-E67 -> 216582.72 | H67: =IF(Principal!$D$25="Anual",IF(MOD(B67+1,12)=0,$W$2*((1+$W$3)^M67),0),$W$2*((1+$W$3)^M67)/12) -> 359.38894 | I67: =C67+H67+$W$5 -> 2124.5064 | J67: =SUM($I$14:I67) -> 112316.37 | K67: =IF(J67>=$W$6,0,$W$5) -> 0 | L67: =IF(K67=$W$5,I67,I67-$W$5) -> 1877.3345 | M67: =ROUNDDOWN(B67/12,0) -> 4 | O67: =IF(Principal!$D$30="Anual",IF(MOD(B67+1,12)=0,VLOOKUP(M67,'Flujos Anuales'!$B$8:$K$39,9),0),VLOOKUP(M67,'Flujos Anuales'!$B$8:$K$39,9)/12) -> 248.98414 | P67: =VLOOKUP(M67,'Flujos Anuales'!$B$8:$K$39,10)/12 -> 36.160989 | Q67: =L67+O67+P67 -> 2162.4796
B68: 54 | C68: =$T$9 -> 1517.9455 | D68: =F67*$T$4 -> 1263.3992 | E68: =C68-D68 -> 254.54631 | F68: =F67-E68 -> 216328.18 | H68: =IF(Principal!$D$25="Anual",IF(MOD(B68+1,12)=0,$W$2*((1+$W$3)^M68),0),$W$2*((1+$W$3)^M68)/12) -> 359.38894 | I68: =C68+H68+$W$5 -> 2124.5064 | J68: =SUM($I$14:I68) -> 114440.87 | K68: =IF(J68>=$W$6,0,$W$5) -> 0 | L68: =IF(K68=$W$5,I68,I68-$W$5) -> 1877.3345 | M68: =ROUNDDOWN(B68/12,0) -> 4 | O68: =IF(Principal!$D$30="Anual",IF(MOD(B68+1,12)=0,VLOOKUP(M68,'Flujos Anuales'!$B$8:$K$39,9),0),VLOOKUP(M68,'Flujos Anuales'!$B$8:$K$39,9)/12) -> 248.98414 | P68: =VLOOKUP(M68,'Flujos Anuales'!$B$8:$K$39,10)/12 -> 36.160989 | Q68: =L68+O68+P68 -> 2162.4796
B69: 55 | C69: =$T$9 -> 1517.9455 | D69: =F68*$T$4 -> 1261.9144 | E69: =C69-D69 -> 256.03116 | F69: =F68-E69 -> 216072.15 | H69: =IF(Principal!$D$25="Anual",IF(MOD(B69+1,12)=0,$W$2*((1+$W$3)^M69),0),$W$2*((1+$W$3)^M69)/12) -> 359.38894 | I69: =C69+H69+$W$5 -> 2124.5064 | J69: =SUM($I$14:I69) -> 116565.38 | K69: =IF(J69>=$W$6,0,$W$5) -> 0 | L69: =IF(K69=$W$5,I69,I69-$W$5) -> 1877.3345 | M69: =ROUNDDOWN(B69/12,0) -> 4 | O69: =IF(Principal!$D$30="Anual",IF(MOD(B69+1,12)=0,VLOOKUP(M69,'Flujos Anuales'!$B$8:$K$39,9),0),VLOOKUP(M69,'Flujos Anuales'!$B$8:$K$39,9)/12) -> 248.98414 | P69: =VLOOKUP(M69,'Flujos Anuales'!$B$8:$K$39,10)/12 -> 36.160989 | Q69: =L69+O69+P69 -> 2162.4796
B70: 56 | C70: =$T$9 -> 1517.9455 | D70: =F69*$T$4 -> 1260.4208 | E70: =C70-D70 -> 257.52468 | F70: =F69-E70 -> 215814.62 | H70: =IF(Principal!$D$25="Anual",IF(MOD(B70+1,12)=0,$W$2*((1+$W$3)^M70),0),$W$2*((1+$W$3)^M70)/12) -> 359.38894 | I70: =C70+H70+$W$5 -> 2124.5064 | J70: =SUM($I$14:I70) -> 118689.89 | K70: =IF(J70>=$W$6,0,$W$5) -> 0 | L70: =IF(K70=$W$5,I70,I70-$W$5) -> 1877.3345 | M70: =ROUNDDOWN(B70/12,0) -> 4 | O70: =IF(Principal!$D$30="Anual",IF(MOD(B70+1,12)=0,VLOOKUP(M70,'Flujos Anuales'!$B$8:$K$39,9),0),VLOOKUP(M70,'Flujos Anuales'!$B$8:$K$39,9)/12) -> 248.98414 | P70: =VLOOKUP(M70,'Flujos Anuales'!$B$8:$K$39,10)/12 -> 36.160989 | Q70: =L70+O70+P70 -> 2162.4796
B71: 57 | C71: =$T$9 -> 1517.9455 | D71: =F70*$T$4 -> 1258.9186 | E71: =C71-D71 -> 259.0269 | F71: =F70-E71 -> 215555.59 | H71: =IF(Principal!$D$25="Anual",IF(MOD(B71+1,12)=0,$W$2*((1+$W$3)^M71),0),$W$2*((1+$W$3)^M71)/12) -> 359.38894 | I71: =C71+H71+$W$5 -> 2124.5064 | J71: =SUM($I$14:I71) -> 120814.39 | K71: =IF(J71>=$W$6,0,$W$5) -> 0 | L71: =IF(K71=$W$5,I71,I71-$W$5) -> 1877.3345 | M71: =ROUNDDOWN(B71/12,0) -> 4 | O71: =IF(Principal!$D$30="Anual",IF(MOD(B71+1,12)=0,VLOOKUP(M71,'Flujos Anuales'!$B$8:$K$39,9),0),VLOOKUP(M71,'Flujos Anuales'!$B$8:$K$39,9)/12) -> 248.98414 | P71: =VLOOKUP(M71,'Flujos Anuales'!$B$8:$K$39,10)/12 -> 36.160989 | Q71: =L71+O71+P71 -> 2162.4796
B72: 58 | C72: =$T$9 -> 1517.9455 | D72: =F71*$T$4 -> 1257.4076 | E72: =C72-D72 -> 260.53789 | F72: =F71-E72 -> 215295.06 | H72: =IF(Principal!$D$25="Anual",IF(MOD(B72+1,12)=0,$W$2*((1+$W$3)^M72),0),$W$2*((1+$W$3)^M72)/12) -> 359.38894 | I72: =C72+H72+$W$5 -> 2124.5064 | J72: =SUM($I$14:I72) -> 122938.9 | K72: =IF(J72>=$W$6,0,$W$5) -> 0 | L72: =IF(K72=$W$5,I72,I72-$W$5) -> 1877.3345 | M72: =ROUNDDOWN(B72/12,0) -> 4 | O72: =IF(Principal!$D$30="Anual",IF(MOD(B72+1,12)=0,VLOOKUP(M72,'Flujos Anuales'!$B$8:$K$39,9),0),VLOOKUP(M72,'Flujos Anuales'!$B$8:$K$39,9)/12) -> 248.98414 | P72: =VLOOKUP(M72,'Flujos Anuales'!$B$8:$K$39,10)/12 -> 36.160989 | Q72: =L72+O72+P72 -> 2162.4796
B73: 59 | C73: =$T$9 -> 1517.9455 | D73: =F72*$T$4 -> 1255.8878 | E73: =C73-D73 -> 262.0577 | F73: =F72-E73 -> 215033 | H73: =IF(Principal!$D$25="Anual",IF(MOD(B73+1,12)=0,$W$2*((1+$W$3)^M73),0),$W$2*((1+$W$3)^M73)/12) -> 359.38894 | I73: =C73+H73+$W$5 -> 2124.5064 | J73: =SUM($I$14:I73) -> 125063.41 | K73: =IF(J73>=$W$6,0,$W$5) -> 0 | L73: =IF(K73=$W$5,I73,I73-$W$5) -> 1877.3345 | M73: =ROUNDDOWN(B73/12,0) -> 4 | O73: =IF(Principal!$D$30="Anual",IF(MOD(B73+1,12)=0,VLOOKUP(M73,'Flujos Anuales'!$B$8:$K$39,9),0),VLOOKUP(M73,'Flujos Anuales'!$B$8:$K$39,9)/12) -> 248.98414 | P73: =VLOOKUP(M73,'Flujos Anuales'!$B$8:$K$39,10)/12 -> 36.160989 | Q73: =L73+O73+P73 -> 2162.4796
B74: 60 | C74: =$T$9 -> 1517.9455 | D74: =F73*$T$4 -> 1254.3592 | E74: =C74-D74 -> 263.58637 | F74: =F73-E74 -> 214769.41 | H74: =IF(Principal!$D$25="Anual",IF(MOD(B74+1,12)=0,$W$2*((1+$W$3)^M74),0),$W$2*((1+$W$3)^M74)/12) -> 361.85726 | I74: =C74+H74+$W$5 -> 2126.9747 | J74: =SUM($I$14:I74) -> 127190.38 | K74: =IF(J74>=$W$6,0,$W$5) -> 0 | L74: =IF(K74=$W$5,I74,I74-$W$5) -> 1879.8028 | M74: =ROUNDDOWN(B74/12,0) -> 5 | N74: =SUM(L74:L85) -> 22557.633 | O74: =IF(Principal!$D$30="Anual",IF(MOD(B74+1,12)=0,VLOOKUP(M74,'Flujos Anuales'!$B$8:$K$39,9),0),VLOOKUP(M74,'Flujos Anuales'!$B$8:$K$39,9)/12) -> 260.35646 | P74: =VLOOKUP(M74,'Flujos Anuales'!$B$8:$K$39,10)/12 -> 36.522599 | Q74: =L74+O74+P74 -> 2176.6818
B75: 61 | C75: =$T$9 -> 1517.9455 | D75: =F74*$T$4 -> 1252.8216 | E75: =C75-D75 -> 265.12396 | F75: =F74-E75 -> 214504.29 | H75: =IF(Principal!$D$25="Anual",IF(MOD(B75+1,12)=0,$W$2*((1+$W$3)^M75),0),$W$2*((1+$W$3)^M75)/12) -> 361.85726 | I75: =C75+H75+$W$5 -> 2126.9747 | J75: =SUM($I$14:I75) -> 129317.36 | K75: =IF(J75>=$W$6,0,$W$5) -> 0 | L75: =IF(K75=$W$5,I75,I75-$W$5) -> 1879.8028 | M75: =ROUNDDOWN(B75/12,0) -> 5 | O75: =IF(Principal!$D$30="Anual",IF(MOD(B75+1,12)=0,VLOOKUP(M75,'Flujos Anuales'!$B$8:$K$39,9),0),VLOOKUP(M75,'Flujos Anuales'!$B$8:$K$39,9)/12) -> 260.35646 | P75: =VLOOKUP(M75,'Flujos Anuales'!$B$8:$K$39,10)/12 -> 36.522599 | Q75: =L75+O75+P75 -> 2176.6818
B76: 62 | C76: =$T$9 -> 1517.9455 | D76: =F75*$T$4 -> 1251.275 | E76: =C76-D76 -> 266.67051 | F76: =F75-E76 -> 214237.62 | H76: =IF(Principal!$D$25="Anual",IF(MOD(B76+1,12)=0,$W$2*((1+$W$3)^M76),0),$W$2*((1+$W$3)^M76)/12) -> 361.85726 | I76: =C76+H76+$W$5 -> 2126.9747 | J76: =SUM($I$14:I76) -> 131444.33 | K76: =IF(J76>=$W$6,0,$W$5) -> 0 | L76: =IF(K76=$W$5,I76,I76-$W$5) -> 1879.8028 | M76: =ROUNDDOWN(B76/12,0) -> 5 | O76: =IF(Principal!$D$30="Anual",IF(MOD(B76+1,12)=0,VLOOKUP(M76,'Flujos Anuales'!$B$8:$K$39,9),0),VLOOKUP(M76,'Flujos Anuales'!$B$8:$K$39,9)/12) -> 260.35646 | P76: =VLOOKUP(M76,'Flujos Anuales'!$B$8:$K$39,10)/12 -> 36.522599 | Q76: =L76+O76+P76 -> 2176.6818
B77: 63 | C77: =$T$9 -> 1517.9455 | D77: =F76*$T$4 -> 1249.7194 | E77: =C77-D77 -> 268.22609 | F77: =F76-E77 -> 213969.39 | H77: =IF(Principal!$D$25="Anual",IF(MOD(B77+1,12)=0,$W$2*((1+$W$3)^M77),0),$W$2*((1+$W$3)^M77)/12) -> 361.85726 | I77: =C77+H77+$W$5 -> 2126.9747 | J77: =SUM($I$14:I77) -> 133571.3 | K77: =IF(J77>=$W$6,0,$W$5) -> 0 | L77: =IF(K77=$W$5,I77,I77-$W$5) -> 1879.8028 | M77: =ROUNDDOWN(B77/12,0) -> 5 | O77: =IF(Principal!$D$30="Anual",IF(MOD(B77+1,12)=0,VLOOKUP(M77,'Flujos Anuales'!$B$8:$K$39,9),0),VLOOKUP(M77,'Flujos Anuales'!$B$8:$K$39,9)/12) -> 260.35646 | P77: =VLOOKUP(M77,'Flujos Anuales'!$B$8:$K$39,10)/12 -> 36.522599 | Q77: =L77+O77+P77 -> 2176.6818
B78: 64 | C78: =$T$9 -> 1517.9455 | D78: =F77*$T$4 -> 1248.1548 | E78: =C78-D78 -> 269.79074 | F78: =F77-E78 -> 213699.6 | H78: =IF(Principal!$D$25="Anual",IF(MOD(B78+1,12)=0,$W$2*((1+$W$3)^M78),0),$W$2*((1+$W$3)^M78)/12) -> 361.85726 | I78: =C78+H78+$W$5 -> 2126.9747 | J78: =SUM($I$14:I78) -> 135698.28 | K78: =IF(J78>=$W$6,0,$W$5) -> 0 | L78: =IF(K78=$W$5,I78,I78-$W$5) -> 1879.8028 | M78: =ROUNDDOWN(B78/12,0) -> 5 | O78: =IF(Principal!$D$30="Anual",IF(MOD(B78+1,12)=0,VLOOKUP(M78,'Flujos Anuales'!$B$8:$K$39,9),0),VLOOKUP(M78,'Flujos Anuales'!$B$8:$K$39,9)/12) -> 260.35646 | P78: =VLOOKUP(M78,'Flujos Anuales'!$B$8:$K$39,10)/12 -> 36.522599 | Q78: =L78+O78+P78 -> 2176.6818
B79: 65 | C79: =$T$9 -> 1517.9455 | D79: =F78*$T$4 -> 1246.581 | E79: =C79-D79 -> 271.36452 | F79: =F78-E79 -> 213428.24 | H79: =IF(Principal!$D$25="Anual",IF(MOD(B79+1,12)=0,$W$2*((1+$W$3)^M79),0),$W$2*((1+$W$3)^M79)/12) -> 361.85726 | I79: =C79+H79+$W$5 -> 2126.9747 | J79: =SUM($I$14:I79) -> 137825.25 | K79: =IF(J79>=$W$6,0,$W$5) -> 0 | L79: =IF(K79=$W$5,I79,I79-$W$5) -> 1879.8028 | M79: =ROUNDDOWN(B79/12,0) -> 5 | O79: =IF(Principal!$D$30="Anual",IF(MOD(B79+1,12)=0,VLOOKUP(M79,'Flujos Anuales'!$B$8:$K$39,9),0),VLOOKUP(M79,'Flujos Anuales'!$B$8:$K$39,9)/12) -> 260.35646 | P79: =VLOOKUP(M79,'Flujos Anuales'!$B$8:$K$39,10)/12 -> 36.522599 | Q79: =L79+O79+P79 -> 2176.6818
B80: 66 | C80: =$T$9 -> 1517.9455 | D80: =F79*$T$4 -> 1244.998 | E80: =C80-D80 -> 272.94748 | F80: =F79-E80 -> 213155.29 | H80: =IF(Principal!$D$25="Anual",IF(MOD(B80+1,12)=0,$W$2*((1+$W$3)^M80),0),$W$2*((1+$W$3)^M80)/12) -> 361.85726 | I80: =C80+H80+$W$5 -> 2126.9747 | J80: =SUM($I$14:I80) -> 139952.23 | K80: =IF(J80>=$W$6,0,$W$5) -> 0 | L80: =IF(K80=$W$5,I80,I80-$W$5) -> 1879.8028 | M80: =ROUNDDOWN(B80/12,0) -> 5 | O80: =IF(Principal!$D$30="Anual",IF(MOD(B80+1,12)=0,VLOOKUP(M80,'Flujos Anuales'!$B$8:$K$39,9),0),VLOOKUP(M80,'Flujos Anuales'!$B$8:$K$39,9)/12) -> 260.35646 | P80: =VLOOKUP(M80,'Flujos Anuales'!$B$8:$K$39,10)/12 -> 36.522599 | Q80: =L80+O80+P80 -> 2176.6818
B81: 67 | C81: =$T$9 -> 1517.9455 | D81: =F80*$T$4 -> 1243.4058 | E81: =C81-D81 -> 274.53968 | F81: =F80-E81 -> 212880.75 | H81: =IF(Principal!$D$25="Anual",IF(MOD(B81+1,12)=0,$W$2*((1+$W$3)^M81),0),$W$2*((1+$W$3)^M81)/12) -> 361.85726 | I81: =C81+H81+$W$5 -> 2126.9747 | J81: =SUM($I$14:I81) -> 142079.2 | K81: =IF(J81>=$W$6,0,$W$5) -> 0 | L81: =IF(K81=$W$5,I81,I81-$W$5) -> 1879.8028 | M81: =ROUNDDOWN(B81/12,0) -> 5 | O81: =IF(Principal!$D$30="Anual",IF(MOD(B81+1,12)=0,VLOOKUP(M81,'Flujos Anuales'!$B$8:$K$39,9),0),VLOOKUP(M81,'Flujos Anuales'!$B$8:$K$39,9)/12) -> 260.35646 | P81: =VLOOKUP(M81,'Flujos Anuales'!$B$8:$K$39,10)/12 -> 36.522599 | Q81: =L81+O81+P81 -> 2176.6818
B82: 68 | C82: =$T$9 -> 1517.9455 | D82: =F81*$T$4 -> 1241.8044 | E82: =C82-D82 -> 276.14116 | F82: =F81-E82 -> 212604.61 | H82: =IF(Principal!$D$25="Anual",IF(MOD(B82+1,12)=0,$W$2*((1+$W$3)^M82),0),$W$2*((1+$W$3)^M82)/12) -> 361.85726 | I82: =C82+H82+$W$5 -> 2126.9747 | J82: =SUM($I$14:I82) -> 144206.18 | K82: =IF(J82>=$W$6,0,$W$5) -> 0 | L82: =IF(K82=$W$5,I82,I82-$W$5) -> 1879.8028 | M82: =ROUNDDOWN(B82/12,0) -> 5 | O82: =IF(Principal!$D$30="Anual",IF(MOD(B82+1,12)=0,VLOOKUP(M82,'Flujos Anuales'!$B$8:$K$39,9),0),VLOOKUP(M82,'Flujos Anuales'!$B$8:$K$39,9)/12) -> 260.35646 | P82: =VLOOKUP(M82,'Flujos Anuales'!$B$8:$K$39,10)/12 -> 36.522599 | Q82: =L82+O82+P82 -> 2176.6818
B83: 69 | C83: =$T$9 -> 1517.9455 | D83: =F82*$T$4 -> 1240.1935 | E83: =C83-D83 -> 277.75198 | F83: =F82-E83 -> 212326.86 | H83: =IF(Principal!$D$25="Anual",IF(MOD(B83+1,12)=0,$W$2*((1+$W$3)^M83),0),$W$2*((1+$W$3)^M83)/12) -> 361.85726 | I83: =C83+H83+$W$5 -> 2126.9747 | J83: =SUM($I$14:I83) -> 146333.15 | K83: =IF(J83>=$W$6,0,$W$5) -> 0 | L83: =IF(K83=$W$5,I83,I83-$W$5) -> 1879.8028 | M83: =ROUNDDOWN(B83/12,0) -> 5 | O83: =IF(Principal!$D$30="Anual",IF(MOD(B83+1,12)=0,VLOOKUP(M83,'Flujos Anuales'!$B$8:$K$39,9),0),VLOOKUP(M83,'Flujos Anuales'!$B$8:$K$39,9)/12) -> 260.35646 | P83: =VLOOKUP(M83,'Flujos Anuales'!$B$8:$K$39,10)/12 -> 36.522599 | Q83: =L83+O83+P83 -> 2176.6818
B84: 70 | C84: =$T$9 -> 1517.9455 | D84: =F83*$T$4 -> 1238.5733 | E84: =C84-D84 -> 279.3722 | F84: =F83-E84 -> 212047.48 | H84: =IF(Principal!$D$25="Anual",IF(MOD(B84+1,12)=0,$W$2*((1+$W$3)^M84),0),$W$2*((1+$W$3)^M84)/12) -> 361.85726 | I84: =C84+H84+$W$5 -> 2126.9747 | J84: =SUM($I$14:I84) -> 148460.13 | K84: =IF(J84>=$W$6,0,$W$5) -> 0 | L84: =IF(K84=$W$5,I84,I84-$W$5) -> 1879.8028 | M84: =ROUNDDOWN(B84/12,0) -> 5 | O84: =IF(Principal!$D$30="Anual",IF(MOD(B84+1,12)=0,VLOOKUP(M84,'Flujos Anuales'!$B$8:$K$39,9),0),VLOOKUP(M84,'Flujos Anuales'!$B$8:$K$39,9)/12) -> 260.35646 | P84: =VLOOKUP(M84,'Flujos Anuales'!$B$8:$K$39,10)/12 -> 36.522599 | Q84: =L84+O84+P84 -> 2176.6818
B85: 71 | C85: =$T$9 -> 1517.9455 | D85: =F84*$T$4 -> 1236.9437 | E85: =C85-D85 -> 281.00187 | F85: =F84-E85 -> 211766.48 | H85: =IF(Principal!$D$25="Anual",IF(MOD(B85+1,12)=0,$W$2*((1+$W$3)^M85),0),$W$2*((1+$W$3)^M85)/12) -> 361.85726 | I85: =C85+H85+$W$5 -> 2126.9747 | J85: =SUM($I$14:I85) -> 150587.1 | K85: =IF(J85>=$W$6,0,$W$5) -> 0 | L85: =IF(K85=$W$5,I85,I85-$W$5) -> 1879.8028 | M85: =ROUNDDOWN(B85/12,0) -> 5 | O85: =IF(Principal!$D$30="Anual",IF(MOD(B85+1,12)=0,VLOOKUP(M85,'Flujos Anuales'!$B$8:$K$39,9),0),VLOOKUP(M85,'Flujos Anuales'!$B$8:$K$39,9)/12) -> 260.35646 | P85: =VLOOKUP(M85,'Flujos Anuales'!$B$8:$K$39,10)/12 -> 36.522599 | Q85: =L85+O85+P85 -> 2176.6818
B86: 72 | C86: =$T$9 -> 1517.9455 | D86: =F85*$T$4 -> 1235.3045 | E86: =C86-D86 -> 282.64105 | F86: =F85-E86 -> 211483.84 | H86: =IF(Principal!$D$25="Anual",IF(MOD(B86+1,12)=0,$W$2*((1+$W$3)^M86),0),$W$2*((1+$W$3)^M86)/12) -> 364.34253 | I86: =C86+H86+$W$5 -> 2129.46 | J86: =SUM($I$14:I86) -> 152716.56 | K86: =IF(J86>=$W$6,0,$W$5) -> 0 | L86: =IF(K86=$W$5,I86,I86-$W$5) -> 1882.2881 | M86: =ROUNDDOWN(B86/12,0) -> 6 | N86: =SUM(L86:L97) -> 22587.457 | O86: =IF(Principal!$D$30="Anual",IF(MOD(B86+1,12)=0,VLOOKUP(M86,'Flujos Anuales'!$B$8:$K$39,9),0),VLOOKUP(M86,'Flujos Anuales'!$B$8:$K$39,9)/12) -> 272.2482 | P86: =VLOOKUP(M86,'Flujos Anuales'!$B$8:$K$39,10)/12 -> 36.887825 | Q86: =L86+O86+P86 -> 2191.4241
B87: 73 | C87: =$T$9 -> 1517.9455 | D87: =F86*$T$4 -> 1233.6557 | E87: =C87-D87 -> 284.28979 | F87: =F86-E87 -> 211199.55 | H87: =IF(Principal!$D$25="Anual",IF(MOD(B87+1,12)=0,$W$2*((1+$W$3)^M87),0),$W$2*((1+$W$3)^M87)/12) -> 364.34253 | I87: =C87+H87+$W$5 -> 2129.46 | J87: =SUM($I$14:I87) -> 154846.02 | K87: =IF(J87>=$W$6,0,$W$5) -> 0 | L87: =IF(K87=$W$5,I87,I87-$W$5) -> 1882.2881 | M87: =ROUNDDOWN(B87/12,0) -> 6 | O87: =IF(Principal!$D$30="Anual",IF(MOD(B87+1,12)=0,VLOOKUP(M87,'Flujos Anuales'!$B$8:$K$39,9),0),VLOOKUP(M87,'Flujos Anuales'!$B$8:$K$39,9)/12) -> 272.2482 | P87: =VLOOKUP(M87,'Flujos Anuales'!$B$8:$K$39,10)/12 -> 36.887825 | Q87: =L87+O87+P87 -> 2191.4241
B88: 74 | C88: =$T$9 -> 1517.9455 | D88: =F87*$T$4 -> 1231.9974 | E88: =C88-D88 -> 285.94815 | F88: =F87-E88 -> 210913.6 | H88: =IF(Principal!$D$25="Anual",IF(MOD(B88+1,12)=0,$W$2*((1+$W$3)^M88),0),$W$2*((1+$W$3)^M88)/12) -> 364.34253 | I88: =C88+H88+$W$5 -> 2129.46 | J88: =SUM($I$14:I88) -> 156975.48 | K88: =IF(J88>=$W$6,0,$W$5) -> 0 | L88: =IF(K88=$W$5,I88,I88-$W$5) -> 1882.2881 | M88: =ROUNDDOWN(B88/12,0) -> 6 | O88: =IF(Principal!$D$30="Anual",IF(MOD(B88+1,12)=0,VLOOKUP(M88,'Flujos Anuales'!$B$8:$K$39,9),0),VLOOKUP(M88,'Flujos Anuales'!$B$8:$K$39,9)/12) -> 272.2482 | P88: =VLOOKUP(M88,'Flujos Anuales'!$B$8:$K$39,10)/12 -> 36.887825 | Q88: =L88+O88+P88 -> 2191.4241
B89: 75 | C89: =$T$9 -> 1517.9455 | D89: =F88*$T$4 -> 1230.3293 | E89: =C89-D89 -> 287.61618 | F89: =F88-E89 -> 210625.99 | H89: =IF(Principal!$D$25="Anual",IF(MOD(B89+1,12)=0,$W$2*((1+$W$3)^M89),0),$W$2*((1+$W$3)^M89)/12) -> 364.34253 | I89: =C89+H89+$W$5 -> 2129.46 | J89: =SUM($I$14:I89) -> 159104.94 | K89: =IF(J89>=$W$6,0,$W$5) -> 0 | L89: =IF(K89=$W$5,I89,I89-$W$5) -> 1882.2881 | M89: =ROUNDDOWN(B89/12,0) -> 6 | O89: =IF(Principal!$D$30="Anual",IF(MOD(B89+1,12)=0,VLOOKUP(M89,'Flujos Anuales'!$B$8:$K$39,9),0),VLOOKUP(M89,'Flujos Anuales'!$B$8:$K$39,9)/12) -> 272.2482 | P89: =VLOOKUP(M89,'Flujos Anuales'!$B$8:$K$39,10)/12 -> 36.887825 | Q89: =L89+O89+P89 -> 2191.4241
B90: 76 | C90: =$T$9 -> 1517.9455 | D90: =F89*$T$4 -> 1228.6516 | E90: =C90-D90 -> 289.29394 | F90: =F89-E90 -> 210336.69 | H90: =IF(Principal!$D$25="Anual",IF(MOD(B90+1,12)=0,$W$2*((1+$W$3)^M90),0),$W$2*((1+$W$3)^M90)/12) -> 364.34253 | I90: =C90+H90+$W$5 -> 2129.46 | J90: =SUM($I$14:I90) -> 161234.4 | K90: =IF(J90>=$W$6,0,$W$5) -> 0 | L90: =IF(K90=$W$5,I90,I90-$W$5) -> 1882.2881 | M90: =ROUNDDOWN(B90/12,0) -> 6 | O90: =IF(Principal!$D$30="Anual",IF(MOD(B90+1,12)=0,VLOOKUP(M90,'Flujos Anuales'!$B$8:$K$39,9),0),VLOOKUP(M90,'Flujos Anuales'!$B$8:$K$39,9)/12) -> 272.2482 | P90: =VLOOKUP(M90,'Flujos Anuales'!$B$8:$K$39,10)/12 -> 36.887825 | Q90: =L90+O90+P90 -> 2191.4241
B91: 77 | C91: =$T$9 -> 1517.9455 | D91: =F90*$T$4 -> 1226.964 | E91: =C91-D91 -> 290.98148 | F91: =F90-E91 -> 210045.71 | H91: =IF(Principal!$D$25="Anual",IF(MOD(B91+1,12)=0,$W$2*((1+$W$3)^M91),0),$W$2*((1+$W$3)^M91)/12) -> 364.34253 | I91: =C91+H91+$W$5 -> 2129.46 | J91: =SUM($I$14:I91) -> 163363.86 | K91: =IF(J91>=$W$6,0,$W$5) -> 0 | L91: =IF(K91=$W$5,I91,I91-$W$5) -> 1882.2881 | M91: =ROUNDDOWN(B91/12,0) -> 6 | O91: =IF(Principal!$D$30="Anual",IF(MOD(B91+1,12)=0,VLOOKUP(M91,'Flujos Anuales'!$B$8:$K$39,9),0),VLOOKUP(M91,'Flujos Anuales'!$B$8:$K$39,9)/12) -> 272.2482 | P91: =VLOOKUP(M91,'Flujos Anuales'!$B$8:$K$39,10)/12 -> 36.887825 | Q91: =L91+O91+P91 -> 2191.4241
B92: 78 | C92: =$T$9 -> 1517.9455 | D92: =F91*$T$4 -> 1225.2666 | E92: =C92-D92 -> 292.67888 | F92: =F91-E92 -> 209753.03 | H92: =IF(Principal!$D$25="Anual",IF(MOD(B92+1,12)=0,$W$2*((1+$W$3)^M92),0),$W$2*((1+$W$3)^M92)/12) -> 364.34253 | I92: =C92+H92+$W$5 -> 2129.46 | J92: =SUM($I$14:I92) -> 165493.32 | K92: =IF(J92>=$W$6,0,$W$5) -> 0 | L92: =IF(K92=$W$5,I92,I92-$W$5) -> 1882.2881 | M92: =ROUNDDOWN(B92/12,0) -> 6 | O92: =IF(Principal!$D$30="Anual",IF(MOD(B92+1,12)=0,VLOOKUP(M92,'Flujos Anuales'!$B$8:$K$39,9),0),VLOOKUP(M92,'Flujos Anuales'!$B$8:$K$39,9)/12) -> 272.2482 | P92: =VLOOKUP(M92,'Flujos Anuales'!$B$8:$K$39,10)/12 -> 36.887825 | Q92: =L92+O92+P92 -> 2191.4241
B93: 79 | C93: =$T$9 -> 1517.9455 | D93: =F92*$T$4 -> 1223.5594 | E93: =C93-D93 -> 294.38617 | F93: =F92-E93 -> 209458.65 | H93: =IF(Principal!$D$25="Anual",IF(MOD(B93+1,12)=0,$W$2*((1+$W$3)^M93),0),$W$2*((1+$W$3)^M93)/12) -> 364.34253 | I93: =C93+H93+$W$5 -> 2129.46 | J93: =SUM($I$14:I93) -> 167622.78 | K93: =IF(J93>=$W$6,0,$W$5) -> 0 | L93: =IF(K93=$W$5,I93,I93-$W$5) -> 1882.2881 | M93: =ROUNDDOWN(B93/12,0) -> 6 | O93: =IF(Principal!$D$30="Anual",IF(MOD(B93+1,12)=0,VLOOKUP(M93,'Flujos Anuales'!$B$8:$K$39,9),0),VLOOKUP(M93,'Flujos Anuales'!$B$8:$K$39,9)/12) -> 272.2482 | P93: =VLOOKUP(M93,'Flujos Anuales'!$B$8:$K$39,10)/12 -> 36.887825 | Q93: =L93+O93+P93 -> 2191.4241
B94: 80 | C94: =$T$9 -> 1517.9455 | D94: =F93*$T$4 -> 1221.8421 | E94: =C94-D94 -> 296.10342 | F94: =F93-E94 -> 209162.54 | H94: =IF(Principal!$D$25="Anual",IF(MOD(B94+1,12)=0,$W$2*((1+$W$3)^M94),0),$W$2*((1+$W$3)^M94)/12) -> 364.34253 | I94: =C94+H94+$W$5 -> 2129.46 | J94: =SUM($I$14:I94) -> 169752.24 | K94: =IF(J94>=$W$6,0,$W$5) -> 0 | L94: =IF(K94=$W$5,I94,I94-$W$5) -> 1882.2881 | M94: =ROUNDDOWN(B94/12,0) -> 6 | O94: =IF(Principal!$D$30="Anual",IF(MOD(B94+1,12)=0,VLOOKUP(M94,'Flujos Anuales'!$B$8:$K$39,9),0),VLOOKUP(M94,'Flujos Anuales'!$B$8:$K$39,9)/12) -> 272.2482 | P94: =VLOOKUP(M94,'Flujos Anuales'!$B$8:$K$39,10)/12 -> 36.887825 | Q94: =L94+O94+P94 -> 2191.4241
B95: 81 | C95: =$T$9 -> 1517.9455 | D95: =F94*$T$4 -> 1220.1148 | E95: =C95-D95 -> 297.83069 | F95: =F94-E95 -> 208864.71 | H95: =IF(Principal!$D$25="Anual",IF(MOD(B95+1,12)=0,$W$2*((1+$W$3)^M95),0),$W$2*((1+$W$3)^M95)/12) -> 364.34253 | I95: =C95+H95+$W$5 -> 2129.46 | J95: =SUM($I$14:I95) -> 171881.7 | K95: =IF(J95>=$W$6,0,$W$5) -> 0 | L95: =IF(K95=$W$5,I95,I95-$W$5) -> 1882.2881 | M95: =ROUNDDOWN(B95/12,0) -> 6 | O95: =IF(Principal!$D$30="Anual",IF(MOD(B95+1,12)=0,VLOOKUP(M95,'Flujos Anuales'!$B$8:$K$39,9),0),VLOOKUP(M95,'Flujos Anuales'!$B$8:$K$39,9)/12) -> 272.2482 | P95: =VLOOKUP(M95,'Flujos Anuales'!$B$8:$K$39,10)/12 -> 36.887825 | Q95: =L95+O95+P95 -> 2191.4241
B96: 82 | C96: =$T$9 -> 1517.9455 | D96: =F95*$T$4 -> 1218.3775 | E96: =C96-D96 -> 299.56804 | F96: =F95-E96 -> 208565.14 | H96: =IF(Principal!$D$25="Anual",IF(MOD(B96+1,12)=0,$W$2*((1+$W$3)^M96),0),$W$2*((1+$W$3)^M96)/12) -> 364.34253 | I96: =C96+H96+$W$5 -> 2129.46 | J96: =SUM($I$14:I96) -> 174011.16 | K96: =IF(J96>=$W$6,0,$W$5) -> 0 | L96: =IF(K96=$W$5,I96,I96-$W$5) -> 1882.2881 | M96: =ROUNDDOWN(B96/12,0) -> 6 | O96: =IF(Principal!$D$30="Anual",IF(MOD(B96+1,12)=0,VLOOKUP(M96,'Flujos Anuales'!$B$8:$K$39,9),0),VLOOKUP(M96,'Flujos Anuales'!$B$8:$K$39,9)/12) -> 272.2482 | P96: =VLOOKUP(M96,'Flujos Anuales'!$B$8:$K$39,10)/12 -> 36.887825 | Q96: =L96+O96+P96 -> 2191.4241
B97: 83 | C97: =$T$9 -> 1517.9455 | D97: =F96*$T$4 -> 1216.63 | E97: =C97-D97 -> 301.31552 | F97: =F96-E97 -> 208263.83 | H97: =IF(Principal!$D$25="Anual",IF(MOD(B97+1,12)=0,$W$2*((1+$W$3)^M97),0),$W$2*((1+$W$3)^M97)/12) -> 364.34253 | I97: =C97+H97+$W$5 -> 2129.46 | J97: =SUM($I$14:I97) -> 176140.62 | K97: =IF(J97>=$W$6,0,$W$5) -> 0 | L97: =IF(K97=$W$5,I97,I97-$W$5) -> 1882.2881 | M97: =ROUNDDOWN(B97/12,0) -> 6 | O97: =IF(Principal!$D$30="Anual",IF(MOD(B97+1,12)=0,VLOOKUP(M97,'Flujos Anuales'!$B$8:$K$39,9),0),VLOOKUP(M97,'Flujos Anuales'!$B$8:$K$39,9)/12) -> 272.2482 | P97: =VLOOKUP(M97,'Flujos Anuales'!$B$8:$K$39,10)/12 -> 36.887825 | Q97: =L97+O97+P97 -> 2191.4241
B98: 84 | C98: =$T$9 -> 1517.9455 | D98: =F97*$T$4 -> 1214.8723 | E98: =C98-D98 -> 303.07319 | F98: =F97-E98 -> 207960.76 | H98: =IF(Principal!$D$25="Anual",IF(MOD(B98+1,12)=0,$W$2*((1+$W$3)^M98),0),$W$2*((1+$W$3)^M98)/12) -> 366.84486 | I98: =C98+H98+$W$5 -> 2131.9623 | J98: =SUM($I$14:I98) -> 178272.58 | K98: =IF(J98>=$W$6,0,$W$5) -> 0 | L98: =IF(K98=$W$5,I98,I98-$W$5) -> 1884.7904 | M98: =ROUNDDOWN(B98/12,0) -> 7 | N98: =SUM(L98:L109) -> 22617.485 | O98: =IF(Principal!$D$30="Anual",IF(MOD(B98+1,12)=0,VLOOKUP(M98,'Flujos Anuales'!$B$8:$K$39,9),0),VLOOKUP(M98,'Flujos Anuales'!$B$8:$K$39,9)/12) -> 284.6831 | P98: =VLOOKUP(M98,'Flujos Anuales'!$B$8:$K$39,10)/12 -> 37.256703 | Q98: =L98+O98+P98 -> 2206.7302
B99: 85 | C99: =$T$9 -> 1517.9455 | D99: =F98*$T$4 -> 1213.1044 | E99: =C99-D99 -> 304.84112 | F99: =F98-E99 -> 207655.91 | H99: =IF(Principal!$D$25="Anual",IF(MOD(B99+1,12)=0,$W$2*((1+$W$3)^M99),0),$W$2*((1+$W$3)^M99)/12) -> 366.84486 | I99: =C99+H99+$W$5 -> 2131.9623 | J99: =SUM($I$14:I99) -> 180404.55 | K99: =IF(J99>=$W$6,0,$W$5) -> 0 | L99: =IF(K99=$W$5,I99,I99-$W$5) -> 1884.7904 | M99: =ROUNDDOWN(B99/12,0) -> 7 | O99: =IF(Principal!$D$30="Anual",IF(MOD(B99+1,12)=0,VLOOKUP(M99,'Flujos Anuales'!$B$8:$K$39,9),0),VLOOKUP(M99,'Flujos Anuales'!$B$8:$K$39,9)/12) -> 284.6831 | P99: =VLOOKUP(M99,'Flujos Anuales'!$B$8:$K$39,10)/12 -> 37.256703 | Q99: =L99+O99+P99 -> 2206.7302
B100: 86 | C100: =$T$9 -> 1517.9455 | D100: =F99*$T$4 -> 1211.3262 | E100: =C100-D100 -> 306.61936 | F100: =F99-E100 -> 207349.29 | H100: =IF(Principal!$D$25="Anual",IF(MOD(B100+1,12)=0,$W$2*((1+$W$3)^M100),0),$W$2*((1+$W$3)^M100)/12) -> 366.84486 | I100: =C100+H100+$W$5 -> 2131.9623 | J100: =SUM($I$14:I100) -> 182536.51 | K100: =IF(J100>=$W$6,0,$W$5) -> 0 | L100: =IF(K100=$W$5,I100,I100-$W$5) -> 1884.7904 | M100: =ROUNDDOWN(B100/12,0) -> 7 | O100: =IF(Principal!$D$30="Anual",IF(MOD(B100+1,12)=0,VLOOKUP(M100,'Flujos Anuales'!$B$8:$K$39,9),0),VLOOKUP(M100,'Flujos Anuales'!$B$8:$K$39,9)/12) -> 284.6831 | P100: =VLOOKUP(M100,'Flujos Anuales'!$B$8:$K$39,10)/12 -> 37.256703 | Q100: =L100+O100+P100 -> 2206.7302
B101: 87 | C101: =$T$9 -> 1517.9455 | D101: =F100*$T$4 -> 1209.5376 | E101: =C101-D101 -> 308.40797 | F101: =F100-E101 -> 207040.89 | H101: =IF(Principal!$D$25="Anual",IF(MOD(B101+1,12)=0,$W$2*((1+$W$3)^M101),0),$W$2*((1+$W$3)^M101)/12) -> 366.84486 | I101: =C101+H101+$W$5 -> 2131.9623 | J101: =SUM($I$14:I101) -> 184668.47 | K101: =IF(J101>=$W$6,0,$W$5) -> 0 | L101: =IF(K101=$W$5,I101,I101-$W$5) -> 1884.7904 | M101: =ROUNDDOWN(B101/12,0) -> 7 | O101: =IF(Principal!$D$30="Anual",IF(MOD(B101+1,12)=0,VLOOKUP(M101,'Flujos Anuales'!$B$8:$K$39,9),0),VLOOKUP(M101,'Flujos Anuales'!$B$8:$K$39,9)/12) -> 284.6831 | P101: =VLOOKUP(M101,'Flujos Anuales'!$B$8:$K$39,10)/12 -> 37.256703 | Q101: =L101+O101+P101 -> 2206.7302
...

Sheet Flujos Anuales
E6: =Plusvalia!J8 -> 0.045674865 | J6: 0.01 | K6: 0.01 | O6: Discounted Cash Flow (DCF) | U6: Ecuacion de Valor: Deudas = Pagos | AB6: Discount Factor
E7: crecimiento annual | J7: del valor de la propiedad | K7: crecimiento annual | Q7: DCF = NPV | W7: NPV | AC7: APV
B8: Periodo t=T | C8: Año | E8: Home Value | F8: Remaining Principal | G8: Home Equity | I8: ='Flujos Mensuales'!N13 -> Pago Annual Mortgage (Intereses, Capital, impuestos, seguro del credito) | J8: Mantenimiento Mayor | K8: Utilities y otros | L8: Pago Total Anual en cada periodo | M8: Cumulative Cash Outflow | O8: Cash Flows por periodo t=T | P8: PV CFs | Q8: DCF =sum(PV CFs) | S8: Yield Curve r | T8: Valor Presente Pagos anuales (usando r) | U8: Valor Presente Equity | V8: Valor Presente Pagos de 30 años | W8: Valor Presente Neto (VPN) del proyecto | Y8: IRR: Internal Rate of Return | Z8: Comprobacion | AB8: 1) WACC WACC = [E/V x Ce] + [D/V x Cd x (1-T)] | AC8: 2) APV Adjusted Present Value | AE8: D/E Ratio
B9: 0 | C9: =Plusvalia!C11 -> 2025 | E9: =Plusvalia!D11 -> 249900 | F9: =VLOOKUP((B9*12)+11,'Flujos Mensuales'!$B$13:$F$374,5,FALSE) -> 226040.42 | G9: =E9-F9 -> 23859.582 | I9: =VLOOKUP(B9,'Flujos Mensuales'!$M$13:$N$374,2,FALSE) -> 23262.804 | J9: 0 | K9: =(Principal!$D$44*12)*(1+$K$6*B9) -> 417 | L9: =SUM(I9:K9)+Principal!E19 -> 70411.104 | M9: =SUM(I9:K9)+Principal!E19 -> 70411.104 | O9: =-L9 -> -70411.104 | P9: =O9 -> -70411.104 | Q9: =SUM(P9:P49) -> -281811.43 | S9: ='Yield Curve'!I128/100 -> 0.0408 | T9: =SUM(I9:K9)+Principal!E19 -> 70411.104 | U9: =G39*(1+S39)^-B39 -> 225900.85 | V9: =SUM(T9:T39) -> 507712.28 | W9: =U9-V9 -> -281811.43 | Y9: =IRR(O9:O49) -> 0.00270476 | Z9: =O9/((1+$Y$9)^B9) -> -70411.104 | AB9: =(Principal!E19/Principal!D17*'Flujos Anuales'!AB14)+(Principal!D21/Principal!D17*'Flujos Anuales'!AB16*(1-'Flujos Anuales'!AB18)) -> 0.054752 | AC9: Pending | AE9: =Principal!D21/Principal!E19 -> 4.8823529
B10: 1 | C10: =C9+1 -> 2026 | E10: =Plusvalia!D12 -> 261314.15 | F10: =VLOOKUP((B10*12)+11,'Flujos Mensuales'!$B$13:$F$374,5,FALSE) -> 223569.63 | G10: =E10-F10 -> 37744.52 | I10: =VLOOKUP(B10,'Flujos Mensuales'!$M$13:$N$374,2,FALSE) -> 25406.424 | J10: =$J$6*E10 -> 2613.1415 | K10: =K9*(1+$K$6*1) -> 421.17 | L10: =SUM(I10:K10) -> 28440.736 | M10: =M9+L10 -> 98851.84 | O10: =-L10 -> -28440.736 | P10: =O10*(1+S10)^-B10 -> -27325.841 | S10: ='Yield Curve'!I128/100 -> 0.0408 | T10: =SUM(I10:K10)*((1+S10)^-B10) -> 27325.841 | Y10: Comprobacion de IRR, NPV=0 | Z10: =O10/((1+$Y$9)^B10) -> -28364.018 | AB10: WACC resulta mayor que la plusvalia del 4.57% por lo que | AE10: Alto D/E ratio.
B11: 2 | C11: =C10+1 -> 2027 | E11: =Plusvalia!D13 -> 273249.64 | F11: =VLOOKUP((B11*12)+11,'Flujos Mensuales'!$B$13:$F$374,5,FALSE) -> 220920.23 | G11: =E11-F11 -> 52329.412 | I11: =VLOOKUP(B11,'Flujos Mensuales'!$M$13:$N$374,2,FALSE) -> 22963.723 | J11: =$J$6*E11 -> 2732.4964 | K11: =K10*(1+$K$6*1) -> 425.3817 | L11: =SUM(I11:K11) -> 26121.601 | M11: =M10+L11 -> 124973.44 | O11: =-L11 -> -26121.601 | P11: =O11*(1+S11)^-B11 -> -24197.399 | S11: ='Yield Curve'!J128/100 -> 0.039 | T11: =SUM(I11:K11)*((1+S11)^-B11) -> 24197.399 | Y11: =SUM(Z9:Z49) -> 1.1641532e-09 | Z11: =O11/((1+$Y$9)^B11) -> -25980.867 | AB11: convendria invertir el Capital en otra opcion mejor.
B12: 3 | C12: =C11+1 -> 2028 | E12: =Plusvalia!D14 -> 285730.28 | F12: =VLOOKUP((B12*12)+11,'Flujos Mensuales'!$B$13:$F$374,5,FALSE) -> 218079.3 | G12: =E12-F12 -> 67650.98 | I12: =VLOOKUP(B12,'Flujos Mensuales'!$M$13:$N$374,2,FALSE) -> 22498.596 | J12: =$J$6*E12 -> 2857.3028 | K12: =K11*(1+$K$6*1) -> 429.63552 | L12: =SUM(I12:K12) -> 25785.534 | M12: =M11+L12 -> 150758.97 | O12: =-L12 -> -25785.534 | P12: =O12*(1+S12)^-B12 -> -23022.72 | S12: ='Yield Curve'!K128/100 -> 0.0385 | T12: =SUM(I12:K12)*((1+S12)^-B12) -> 23022.72 | V12: VPN > 0 se acepta el Proyecto | Y12: =NPV(Y9,O9:O49) -> 3.4830389e-10 | Z12: =O12/((1+$Y$9)^B12) -> -25577.43
B13: 4 | C13: =C12+1 -> 2029 | E13: =Plusvalia!D15 -> 298780.97 | F13: =VLOOKUP((B13*12)+11,'Flujos Mensuales'!$B$13:$F$374,5,FALSE) -> 215033 | G13: =E13-F13 -> 83747.972 | I13: =VLOOKUP(B13,'Flujos Mensuales'!$M$13:$N$374,2,FALSE) -> 22528.014 | J13: =$J$6*E13 -> 2987.8097 | K13: =K12*(1+$K$6*1) -> 433.93187 | L13: =SUM(I13:K13) -> 25949.755 | M13: =M12+L13 -> 176708.73 | O13: =-L13 -> -25949.755 | P13: =O13*(1+S13)^-B13 -> -22216.118 | S13: ='Yield Curve'!L128/100 -> 0.0396 | T13: =SUM(I13:K13)*((1+S13)^-B13) -> 22216.118 | V13: VPN = 0 indiferente | Z13: =O13/((1+$Y$9)^B13) -> -25670.892 | AB13: Ce: Cost of Equity*
B14: 5 | C14: =C13+1 -> 2030 | E14: =Plusvalia!D16 -> 312427.75 | F14: =VLOOKUP((B14*12)+11,'Flujos Mensuales'!$B$13:$F$374,5,FALSE) -> 211766.48 | G14: =E14-F14 -> 100661.27 | I14: =VLOOKUP(B14,'Flujos Mensuales'!$M$13:$N$374,2,FALSE) -> 22557.633 | J14: =$J$6*E14 -> 3124.2775 | K14: =K13*(1+$K$6*1) -> 438.27119 | L14: =SUM(I14:K14) -> 26120.182 | M14: =M13+L14 -> 202828.91 | O14: =-L14 -> -26120.182 | P14: =O14*(1+S14)^-B14 -> -21510.22 | S14: ='Yield Curve'!L128/100 -> 0.0396 | T14: =SUM(I14:K14)*((1+S14)^-B14) -> 21510.22 | V14: VPN < 0 se rechaza el Proyecto | Z14: =O14/((1+$Y$9)^B14) -> -25769.786 | AB14: ='Opciones de Inversion'!H9 -> 0.076
B15: 6 | C15: =C14+1 -> 2031 | E15: =Plusvalia!D17 -> 326697.85 | F15: =VLOOKUP((B15*12)+11,'Flujos Mensuales'!$B$13:$F$374,5,FALSE) -> 208263.83 | G15: =E15-F15 -> 118434.02 | I15: =VLOOKUP(B15,'Flujos Mensuales'!$M$13:$N$374,2,FALSE) -> 22587.457 | J15: =$J$6*E15 -> 3266.9785 | K15: =K14*(1+$K$6*1) -> 442.6539 | L15: =SUM(I15:K15) -> 26297.089 | M15: =M14+L15 -> 229126 | O15: =-L15 -> -26297.089 | P15: =O15*(1+S15)^-B15 -> -20592.157 | S15: ='Yield Curve'!M128/100 -> 0.0416 | T15: =SUM(I15:K15)*((1+S15)^-B15) -> 20592.157 | Y15: k = costo de capital o deduda: | Z15: =O15/((1+$Y$9)^B15) -> -25874.336 | AB15: Cd: Cost of Debt
B16: 7 | C16: =C15+1 -> 2032 | E16: =Plusvalia!D18 -> 341619.73 | F16: =VLOOKUP((B16*12)+11,'Flujos Mensuales'!$B$13:$F$374,5,FALSE) -> 204507.97 | G16: =E16-F16 -> 137111.76 | I16: =VLOOKUP(B16,'Flujos Mensuales'!$M$13:$N$374,2,FALSE) -> 22617.485 | J16: =$J$6*E16 -> 3416.1973 | K16: =K15*(1+$K$6*1) -> 447.08044 | L16: =SUM(I16:K16) -> 26480.762 | M16: =M15+L16 -> 255606.76 | O16: =-L16 -> -26480.762 | P16: =O16*(1+S16)^-B16 -> -19907.819 | S16: ='Yield Curve'!M128/100 -> 0.0416 | T16: =SUM(I16:K16)*((1+S16)^-B16) -> 19907.819 | Y16: =Principal!D13 -> 0.07 | Z16: =O16/((1+$Y$9)^B16) -> -25984.774 | AB16: =Principal!D13 -> 0.07
B17: 8 | C17: =C16+1 -> 2033 | E17: =Plusvalia!D19 -> 357223.16 | F17: =VLOOKUP((B17*12)+11,'Flujos Mensuales'!$B$13:$F$374,5,FALSE) -> 200480.6 | G17: =E17-F17 -> 156742.56 | I17: =VLOOKUP(B17,'Flujos Mensuales'!$M$13:$N$374,2,FALSE) -> 22647.719 | J17: =$J$6*E17 -> 3572.2316 | K17: =K16*(1+$K$6*1) -> 451.55125 | L17: =SUM(I17:K17) -> 26671.502 | M17: =M16+L17 -> 282278.26 | O17: =-L17 -> -26671.502 | P17: =O17*(1+S17)^-B17 -> -18899.203 | S17: ='Yield Curve'!N128/100 -> 0.044 | T17: =SUM(I17:K17)*((1+S17)^-B17) -> 18899.203 | Y17: IRR > k se acepta el Proyecto | Z17: =O17/((1+$Y$9)^B17) -> -26101.343 | AB17: T: Tax Rate
B18: 9 | C18: =C17+1 -> 2034 | E18: =Plusvalia!D20 -> 373539.28 | F18: =VLOOKUP((B18*12)+11,'Flujos Mensuales'!$B$13:$F$374,5,FALSE) -> 196162.09 | G18: =E18-F18 -> 177377.2 | I18: =VLOOKUP(B18,'Flujos Mensuales'!$M$13:$N$374,2,FALSE) -> 22678.161 | J18: =$J$6*E18 -> 3735.3928 | K18: =K17*(1+$K$6*1) -> 456.06676 | L18: =SUM(I18:K18) -> 26869.62 | M18: =M17+L18 -> 309147.89 | O18: =-L18 -> -26869.62 | P18: =O18*(1+S18)^-B18 -> -18237.153 | S18: ='Yield Curve'!N128/100 -> 0.044 | T18: =SUM(I18:K18)*((1+S18)^-B18) -> 18237.153 | Y18: IRR < k se rechaza el Proyecto | Z18: =O18/((1+$Y$9)^B18) -> -26224.296 | AB18: 0.28
B19: 10 | C19: =C18+1 -> 2035 | E19: =Plusvalia!D21 -> 390600.64 | F19: =VLOOKUP((B19*12)+11,'Flujos Mensuales'!$B$13:$F$374,5,FALSE) -> 191531.39 | G19: =E19-F19 -> 199069.25 | I19: =VLOOKUP(B19,'Flujos Mensuales'!$M$13:$N$374,2,FALSE) -> 22708.812 | J19: =$J$6*E19 -> 3906.0064 | K19: =K18*(1+$K$6*1) -> 460.62743 | L19: =SUM(I19:K19) -> 27075.446 | M19: =M18+L19 -> 336223.33 | O19: =-L19 -> -27075.446 | P19: =O19*(1+S19)^-B19 -> -17602.349 | S19: ='Yield Curve'!N128/100 -> 0.044 | T19: =SUM(I19:K19)*((1+S19)^-B19) -> 17602.349 | Y19: IRR = k indiferente | Z19: =O19/((1+$Y$9)^B19) -> -26353.897
B20: 11 | C20: =C19+1 -> 2036 | E20: =Plusvalia!D22 -> 408441.27 | F20: =VLOOKUP((B20*12)+11,'Flujos Mensuales'!$B$13:$F$374,5,FALSE) -> 186565.94 | G20: =E20-F20 -> 221875.33 | I20: =VLOOKUP(B20,'Flujos Mensuales'!$M$13:$N$374,2,FALSE) -> 22739.673 | J20: =$J$6*E20 -> 4084.4127 | K20: =K19*(1+$K$6*1) -> 465.2337 | L20: =SUM(I20:K20) -> 27289.32 | M20: =M19+L20 -> 363512.65 | O20: =-L20 -> -27289.32 | P20: =O20*(1+S20)^-B20 -> -16072.976 | S20: ='Yield Curve'!O128/100 -> 0.0493 | T20: =SUM(I20:K20)*((1+S20)^-B20) -> 16072.976 | Z20: =O20/((1+$Y$9)^B20) -> -26490.421 | AB20: Podriamos descontar todos
B21: 12 | C21: =C20+1 -> 2037 | E21: =Plusvalia!D23 -> 427096.77 | F21: =VLOOKUP((B21*12)+11,'Flujos Mensuales'!$B$13:$F$374,5,FALSE) -> 181241.54 | G21: =E21-F21 -> 245855.23 | I21: =VLOOKUP(B21,'Flujos Mensuales'!$M$13:$N$374,2,FALSE) -> 22770.747 | J21: =$J$6*E21 -> 4270.9677 | K21: =K20*(1+$K$6*1) -> 469.88604 | L21: =SUM(I21:K21) -> 27511.601 | M21: =M20+L21 -> 391024.25 | O21: =-L21 -> -27511.601 | P21: =O21*(1+S21)^-B21 -> -15442.577 | S21: ='Yield Curve'!O128/100 -> 0.0493 | T21: =SUM(I21:K21)*((1+S21)^-B21) -> 15442.577 | Z21: =O21/((1+$Y$9)^B21) -> -26634.156 | AB21: los Cashflow a Valor Presente
B22: 13 | C22: =C21+1 -> 2038 | E22: =Plusvalia!D24 -> 446604.36 | F22: =VLOOKUP((B22*12)+11,'Flujos Mensuales'!$B$13:$F$374,5,FALSE) -> 175532.23 | G22: =E22-F22 -> 271072.12 | I22: =VLOOKUP(B22,'Flujos Mensuales'!$M$13:$N$374,2,FALSE) -> 22802.034 | J22: =$J$6*E22 -> 4466.0436 | K22: =K21*(1+$K$6*1) -> 474.5849 | L22: =SUM(I22:K22) -> 27742.662 | M22: =M21+L22 -> 418766.91 | O22: =-L22 -> -27742.662 | P22: =O22*(1+S22)^-B22 -> -14840.632 | S22: ='Yield Curve'!O128/100 -> 0.0493 | T22: =SUM(I22:K22)*((1+S22)^-B22) -> 14840.632 | Y22: "IRR Es la MAXIMA tasa de Interes | Z22: =O22/((1+$Y$9)^B22) -> -26785.4 | AB22: usando una sola tasa de
B23: 14 | C23: =C22+1 -> 2039 | E23: =Plusvalia!D25 -> 467002.95 | F23: =VLOOKUP((B23*12)+11,'Flujos Mensuales'!$B$13:$F$374,5,FALSE) -> 169410.2 | G23: =E23-F23 -> 297592.75 | I23: =VLOOKUP(B23,'Flujos Mensuales'!$M$13:$N$374,2,FALSE) -> 22833.536 | J23: =$J$6*E23 -> 4670.0295 | K23: =K22*(1+$K$6*1) -> 479.33075 | L23: =SUM(I23:K23) -> 27982.896 | M23: =M22+L23 -> 446749.81 | O23: =-L23 -> -27982.896 | P23: =O23*(1+S23)^-B23 -> -14265.836 | S23: ='Yield Curve'!O128/100 -> 0.0493 | T23: =SUM(I23:K23)*((1+S23)^-B23) -> 14265.836 | Y23: a la que podemos aceptar creditos o | Z23: =O23/((1+$Y$9)^B23) -> -26944.466 | AB23: descuento que en este caso
B24: 15 | C24: =C23+1 -> 2040 | E24: =Plusvalia!D26 -> 488333.25 | F24: =VLOOKUP((B24*12)+11,'Flujos Mensuales'!$B$13:$F$374,5,FALSE) -> 162845.61 | G24: =E24-F24 -> 325487.64 | I24: =VLOOKUP(B24,'Flujos Mensuales'!$M$13:$N$374,2,FALSE) -> 22865.254 | J24: =$J$6*E24 -> 4883.3325 | K24: =K23*(1+$K$6*1) -> 484.12405 | L24: =SUM(I24:K24) -> 28232.71 | M24: =M23+L24 -> 474982.52 | O24: =-L24 -> -28232.71 | P24: =O24*(1+S24)^-B24 -> -13716.948 | S24: ='Yield Curve'!O128/100 -> 0.0493 | T24: =SUM(I24:K24)*((1+S24)^-B24) -> 13716.948 | Y24: emitir deuda para el proyecto | Z24: =O24/((1+$Y$9)^B24) -> -27111.679 | AB24: seria el WACC, que es el
B25: 16 | C25: =C24+1 -> 2041 | E25: =Plusvalia!D27 -> 510637.8 | F25: =VLOOKUP((B25*12)+11,'Flujos Mensuales'!$B$13:$F$374,5,FALSE) -> 155806.46 | G25: =E25-F25 -> 354831.34 | I25: =VLOOKUP(B25,'Flujos Mensuales'!$M$13:$N$374,2,FALSE) -> 22897.19 | J25: =$J$6*E25 -> 5106.378 | K25: =K24*(1+$K$6*1) -> 488.96529 | L25: =SUM(I25:K25) -> 28492.533 | M25: =M24+L25 -> 503475.05 | O25: =-L25 -> -28492.533 | P25: =O25*(1+S25)^-B25 -> -13192.779 | S25: ='Yield Curve'!O128/100 -> 0.0493 | T25: =SUM(I25:K25)*((1+S25)^-B25) -> 13192.779 | Y25: (costo de capital) dados los flujos de | Z25: =O25/((1+$Y$9)^B25) -> -27287.38 | AB25: costo de capital o financiamiento.
B26: 17 | C26: =C25+1 -> 2042 | E26: =Plusvalia!D28 -> 533961.11 | F26: =VLOOKUP((B26*12)+11,'Flujos Mensuales'!$B$13:$F$374,5,FALSE) -> 148258.46 | G26: =E26-F26 -> 385702.66 | I26: =VLOOKUP(B26,'Flujos Mensuales'!$M$13:$N$374,2,FALSE) -> 22929.345 | J26: =$J$6*E26 -> 5339.6111 | K26: =K25*(1+$K$6*1) -> 493.85495 | L26: =SUM(I26:K26) -> 28762.811 | M26: =M25+L26 -> 532237.86 | O26: =-L26 -> -28762.811 | P26: =O26*(1+S26)^-B26 -> -12692.2 | S26: ='Yield Curve'!O128/100 -> 0.0493 | T26: =SUM(I26:K26)*((1+S26)^-B26) -> 12692.2 | Y26: efectivo y que el NPV sea cero, o sea | Z26: =O26/((1+$Y$9)^B26) -> -27471.921 | AB26: El WACC ya considera las
B27: 18 | C27: =C26+1 -> 2043 | E27: =Plusvalia!D29 -> 558349.72 | F27: =VLOOKUP((B27*12)+11,'Flujos Mensuales'!$B$13:$F$374,5,FALSE) -> 140164.8 | G27: =E27-F27 -> 418184.91 | I27: =VLOOKUP(B27,'Flujos Mensuales'!$M$13:$N$374,2,FALSE) -> 22961.721 | J27: =$J$6*E27 -> 5583.4972 | K27: =K26*(1+$K$6*1) -> 498.7935 | L27: =SUM(I27:K27) -> 29044.012 | M27: =M26+L27 -> 561281.88 | O27: =-L27 -> -29044.012 | P27: =O27*(1+S27)^-B27 -> -12214.129 | S27: ='Yield Curve'!O128/100 -> 0.0493 | T27: =SUM(I27:K27)*((1+S27)^-B27) -> 12214.129 | Y27: para evitar perdidas.. | Z27: =O27/((1+$Y$9)^B27) -> -27665.672 | AB27: deducciones de impuestos.
B28: 19 | C28: =C27+1 -> 2044 | E28: =Plusvalia!D30 -> 583852.26 | F28: =VLOOKUP((B28*12)+11,'Flujos Mensuales'!$B$13:$F$374,5,FALSE) -> 131486.06 | G28: =E28-F28 -> 452366.21 | I28: =VLOOKUP(B28,'Flujos Mensuales'!$M$13:$N$374,2,FALSE) -> 22994.32 | J28: =$J$6*E28 -> 5838.5226 | K28: =K27*(1+$K$6*1) -> 503.78143 | L28: =SUM(I28:K28) -> 29336.624 | M28: =M27+L28 -> 590618.5 | O28: =-L28 -> -29336.624 | P28: =O28*(1+S28)^-B28 -> -11757.537 | S28: ='Yield Curve'!O128/100 -> 0.0493 | T28: =SUM(I28:K28)*((1+S28)^-B28) -> 11757.537 | Z28: =O28/((1+$Y$9)^B28) -> -27869.019
B29: 20 | C29: =C28+1 -> 2045 | E29: =Plusvalia!D31 -> 610519.64 | F29: =VLOOKUP((B29*12)+11,'Flujos Mensuales'!$B$13:$F$374,5,FALSE) -> 122179.93 | G29: =E29-F29 -> 488339.71 | I29: =VLOOKUP(B29,'Flujos Mensuales'!$M$13:$N$374,2,FALSE) -> 23027.142 | J29: =$J$6*E29 -> 6105.1964 | K29: =K28*(1+$K$6*1) -> 508.81925 | L29: =SUM(I29:K29) -> 29641.158 | M29: =M28+L29 -> 620259.66 | O29: =-L29 -> -29641.158 | P29: =O29*(1+S29)^-B29 -> -11321.441 | S29: ='Yield Curve'!O128/100 -> 0.0493 | T29: =SUM(I29:K29)*((1+S29)^-B29) -> 11321.441 | Z29: =O29/((1+$Y$9)^B29) -> -28082.362 | AB29: Weighted average cost of capital (WACC)
B30: 21 | C30: =C29+1 -> 2046 | E30: =Plusvalia!D32 -> 638405.04 | F30: =VLOOKUP((B30*12)+11,'Flujos Mensuales'!$B$13:$F$374,5,FALSE) -> 112201.05 | G30: =E30-F30 -> 526203.99 | I30: =VLOOKUP(B30,'Flujos Mensuales'!$M$13:$N$374,2,FALSE) -> 23060.19 | J30: =$J$6*E30 -> 6384.0504 | K30: =K29*(1+$K$6*1) -> 513.90744 | L30: =SUM(I30:K30) -> 29958.148 | M30: =M29+L30 -> 650217.8 | O30: =-L30 -> -29958.148 | P30: =O30*(1+S30)^-B30 -> -10926.751 | S30: ='Yield Curve'!P128/100 -> 0.0492 | T30: =SUM(I30:K30)*((1+S30)^-B30) -> 10926.751 | Z30: =O30/((1+$Y$9)^B30) -> -28306.12 | AB30: is a company's average after-tax
B31: 22 | C31: =C30+1 -> 2047 | E31: =Plusvalia!D33 -> 667564.1 | F31: =VLOOKUP((B31*12)+11,'Flujos Mensuales'!$B$13:$F$374,5,FALSE) -> 101500.81 | G31: =E31-F31 -> 566063.3 | I31: =VLOOKUP(B31,'Flujos Mensuales'!$M$13:$N$374,2,FALSE) -> 23093.465 | J31: =$J$6*E31 -> 6675.641 | K31: =K30*(1+$K$6*1) -> 519.04651 | L31: =SUM(I31:K31) -> 30288.152 | M31: =M30+L31 -> 680505.96 | O31: =-L31 -> -30288.152 | P31: =O31*(1+S31)^-B31 -> -10529.084 | S31: ='Yield Curve'!P128/100 -> 0.0492 | T31: =SUM(I31:K31)*((1+S31)^-B31) -> 10529.084 | Z31: =O31/((1+$Y$9)^B31) -> -28540.731 | AB31: cost of capital from all sources, including
B32: 23 | C32: =C31+1 -> 2048 | E32: =Plusvalia!D34 -> 698055 | F32: =VLOOKUP((B32*12)+11,'Flujos Mensuales'!$B$13:$F$374,5,FALSE) -> 90027.039 | G32: =E32-F32 -> 608027.97 | I32: =VLOOKUP(B32,'Flujos Mensuales'!$M$13:$N$374,2,FALSE) -> 23126.968 | J32: =$J$6*E32 -> 6980.55 | K32: =K31*(1+$K$6*1) -> 524.23698 | L32: =SUM(I32:K32) -> 30631.755 | M32: =M31+L32 -> 711137.71 | O32: =-L32 -> -30631.755 | P32: =O32*(1+S32)^-B32 -> -10149.19 | S32: ='Yield Curve'!P128/100 -> 0.0492 | T32: =SUM(I32:K32)*((1+S32)^-B32) -> 10149.19 | Z32: =O32/((1+$Y$9)^B32) -> -28786.649 | AB32: common stock, preferred stock, bonds,
B33: 24 | C33: =C32+1 -> 2049 | E33: =Plusvalia!D35 -> 729938.57 | F33: =VLOOKUP((B33*12)+11,'Flujos Mensuales'!$B$13:$F$374,5,FALSE) -> 77723.831 | G33: =E33-F33 -> 652214.74 | I33: =VLOOKUP(B33,'Flujos Mensuales'!$M$13:$N$374,2,FALSE) -> 23160.702 | J33: =$J$6*E33 -> 7299.3857 | K33: =K32*(1+$K$6*1) -> 529.47935 | L33: =SUM(I33:K33) -> 30989.567 | M33: =M32+L33 -> 742127.28 | O33: =-L33 -> -30989.567 | P33: =O33*(1+S33)^-B33 -> -9786.2597 | S33: ='Yield Curve'!P128/100 -> 0.0492 | T33: =SUM(I33:K33)*((1+S33)^-B33) -> 9786.2597 | Z33: =O33/((1+$Y$9)^B33) -> -29044.35 | AB33: and other forms of debt. It represents
B34: 25 | C34: =C33+1 -> 2050 | E34: =Plusvalia!D36 -> 763278.42 | F34: =VLOOKUP((B34*12)+11,'Flujos Mensuales'!$B$13:$F$374,5,FALSE) -> 64531.224 | G34: =E34-F34 -> 698747.19 | I34: =VLOOKUP(B34,'Flujos Mensuales'!$M$13:$N$374,2,FALSE) -> 23194.667 | J34: =$J$6*E34 -> 7632.7842 | K34: =K33*(1+$K$6*1) -> 534.77414 | L34: =SUM(I34:K34) -> 31362.225 | M34: =M33+L34 -> 773489.5 | O34: =-L34 -> -31362.225 | P34: =O34*(1+S34)^-B34 -> -9439.518 | S34: ='Yield Curve'!P128/100 -> 0.0492 | T34: =SUM(I34:K34)*((1+S34)^-B34) -> 9439.518 | Z34: =O34/((1+$Y$9)^B34) -> -29314.329 | AB34: the average rate that a company expects
B35: 26 | C35: =C34+1 -> 2051 | E35: =Plusvalia!D37 -> 798141.06 | F35: =VLOOKUP((B35*12)+11,'Flujos Mensuales'!$B$13:$F$374,5,FALSE) -> 50384.922 | G35: =E35-F35 -> 747756.14 | I35: =VLOOKUP(B35,'Flujos Mensuales'!$M$13:$N$374,2,FALSE) -> 23228.865 | J35: =$J$6*E35 -> 7981.4106 | K35: =K34*(1+$K$6*1) -> 540.12188 | L35: =SUM(I35:K35) -> 31750.398 | M35: =M34+L35 -> 805239.9 | O35: =-L35 -> -31750.398 | P35: =O35*(1+S35)^-B35 -> -9108.2268 | S35: ='Yield Curve'!P128/100 -> 0.0492 | T35: =SUM(I35:K35)*((1+S35)^-B35) -> 9108.2268 | Z35: =O35/((1+$Y$9)^B35) -> -29597.101 | AB35: to pay to finance its business.
B36: 27 | C36: =C35+1 -> 2052 | E36: =Plusvalia!D38 -> 834596.04 | F36: =VLOOKUP((B36*12)+11,'Flujos Mensuales'!$B$13:$F$374,5,FALSE) -> 35215.983 | G36: =E36-F36 -> 799380.06 | I36: =VLOOKUP(B36,'Flujos Mensuales'!$M$13:$N$374,2,FALSE) -> 23263.298 | J36: =$J$6*E36 -> 8345.9604 | K36: =K35*(1+$K$6*1) -> 545.5231 | L36: =SUM(I36:K36) -> 32154.782 | M36: =M35+L36 -> 837394.68 | O36: =-L36 -> -32154.782 | P36: =O36*(1+S36)^-B36 -> -8791.6817 | S36: ='Yield Curve'!P128/100 -> 0.0492 | T36: =SUM(I36:K36)*((1+S36)^-B36) -> 8791.6817 | Z36: =O36/((1+$Y$9)^B36) -> -29893.206
B37: 28 | C37: =C36+1 -> 2053 | E37: =Plusvalia!D39 -> 872716.11 | F37: =VLOOKUP((B37*12)+11,'Flujos Mensuales'!$B$13:$F$374,5,FALSE) -> 18950.48 | G37: =E37-F37 -> 853765.63 | I37: =VLOOKUP(B37,'Flujos Mensuales'!$M$13:$N$374,2,FALSE) -> 23297.968 | J37: =$J$6*E37 -> 8727.1611 | K37: =K36*(1+$K$6*1) -> 550.97833 | L37: =SUM(I37:K37) -> 32576.108 | M37: =M36+L37 -> 869970.79 | O37: =-L37 -> -32576.108 | P37: =O37*(1+S37)^-B37 -> -8489.2104 | S37: ='Yield Curve'!P128/100 -> 0.0492 | T37: =SUM(I37:K37)*((1+S37)^-B37) -> 8489.2104 | Z37: =O37/((1+$Y$9)^B37) -> -30203.206
B38: 29 | C38: =C37+1 -> 2054 | E38: =Plusvalia!D40 -> 912577.3 | F38: =VLOOKUP((B38*12)+11,'Flujos Mensuales'!$B$13:$F$374,5,FALSE) -> 1509.1422 | G38: =E38-F38 -> 911068.15 | I38: =VLOOKUP(B38,'Flujos Mensuales'!$M$13:$N$374,2,FALSE) -> 23332.876 | J38: =$J$6*E38 -> 9125.773 | K38: =K37*(1+$K$6*1) -> 556.48812 | L38: =SUM(I38:K38) -> 33015.137 | M38: =M37+L38 -> 902985.93 | O38: =-L38 -> -33015.137 | P38: =O38*(1+S38)^-B38 -> -8200.1714 | S38: ='Yield Curve'!P128/100 -> 0.0492 | T38: =SUM(I38:K38)*((1+S38)^-B38) -> 8200.1714 | Z38: =O38/((1+$Y$9)^B38) -> -30527.686
B39: 30 | C39: =C38+1 -> 2055 | E39: =Plusvalia!D41 -> 954259.14 | F39: 0 | G39: =E39-F39 -> 954259.14 | I39: =VLOOKUP(B39,'Flujos Mensuales'!$M$13:$N$374,2,FALSE) -> 1947.3353 | J39: =$J$6*E39 -> 9542.5914 | K39: =K38*(1+$K$6*1) -> 562.053 | L39: =SUM(I39:K39) -> 12051.98 | M39: =M38+L39 -> 915037.91 | O39: =G39-L39 -> 942207.16 | P39: =O39*(1+S39)^-B39 -> 223047.8 | S39: ='Yield Curve'!P128/100 -> 0.0492 | T39: =SUM(I39:K39)*((1+S39)^-B39) -> 2853.0536 | U39: <- Suponiendo la venta en el anio 30 | Z39: =O39/((1+$Y$9)^B39) -> 868868.6
B40: 31 | C40: =C39+1 -> 2056 | E40: =Plusvalia!D42 -> 997844.8 | F40: 0 | G40: =E40-F40 -> 997844.8 | I40: 0 | J40: =$J$6*E40 -> 9978.448 | K40: =K39*(1+$K$6*1) -> 567.67353 | L40: =SUM(I40:K40) -> 10546.122 | M40: =M39+L40 -> 925584.03 | O40: 0 | P40: =O40*(1+S40)^-B40 -> 0 | S40: =S39 -> 0.0492 | T40: =SUM(I40:K40)*((1+S40)^-B40) -> 2379.5018 | U40: lo que daria un flujo de efectivo positivo | Z40: =O40/((1+$Y$9)^B40) -> 0
B41: 32 | C41: =C40+1 -> 2057 | E41: =Plusvalia!D43 -> 1043421.2 | F41: 0 | G41: =E41-F41 -> 1043421.2 | I41: 0 | J41: =$J$6*E41 -> 10434.212 | K41: =K40*(1+$K$6*1) -> 573.35026 | L41: =SUM(I41:K41) -> 11007.563 | M41: =M40+L41 -> 936591.59 | O41: 0 | P41: =O41*(1+S41)^-B41 -> 0 | S41: =S40 -> 0.0492 | T41: =SUM(I41:K41)*((1+S41)^-B41) -> 2367.152 | U41: en ese anio. | Z41: =O41/((1+$Y$9)^B41) -> 0
B42: 33 | C42: =C41+1 -> 2058 | E42: =Plusvalia!D44 -> 1091079.3 | F42: 0 | G42: =E42-F42 -> 1091079.3 | I42: 0 | J42: =$J$6*E42 -> 10910.793 | K42: =K41*(1+$K$6*1) -> 579.08377 | L42: =SUM(I42:K42) -> 11489.877 | M42: =M41+L42 -> 948081.47 | O42: 0 | P42: =O42*(1+S42)^-B42 -> 0 | S42: =S41 -> 0.0492 | T42: =SUM(I42:K42)*((1+S42)^-B42) -> 2355.0064 | Z42: =O42/((1+$Y$9)^B42) -> 0
B43: 34 | C43: =C42+1 -> 2059 | E43: =Plusvalia!D45 -> 1140914.3 | F43: 0 | G43: =E43-F43 -> 1140914.3 | I43: 0 | J43: =$J$6*E43 -> 11409.143 | K43: =K42*(1+$K$6*1) -> 584.8746 | L43: =SUM(I43:K43) -> 11994.017 | M43: =M42+L43 -> 960075.49 | O43: 0 | P43: =O43*(1+S43)^-B43 -> 0 | S43: =S42 -> 0.0492 | T43: =SUM(I43:K43)*((1+S43)^-B43) -> 2343.0582 | Z43: =O43/((1+$Y$9)^B43) -> 0
B44: 35 | C44: =C43+1 -> 2060 | E44: =Plusvalia!D46 -> 1193025.4 | F44: 0 | G44: =E44-F44 -> 1193025.4 | I44: 0 | J44: =$J$6*E44 -> 11930.254 | K44: =K43*(1+$K$6*1) -> 590.72335 | L44: =SUM(I44:K44) -> 12520.977 | M44: =M43+L44 -> 972596.46 | O44: 0 | P44: =O44*(1+S44)^-B44 -> 0 | S44: =S43 -> 0.0492 | T44: =SUM(I44:K44)*((1+S44)^-B44) -> 2331.301 | Z44: =O44/((1+$Y$9)^B44) -> 0
B45: 36 | C45: =C44+1 -> 2061 | E45: =Plusvalia!D47 -> 1247516.6 | F45: 0 | G45: =E45-F45 -> 1247516.6 | I45: 0 | J45: =$J$6*E45 -> 12475.166 | K45: =K44*(1+$K$6*1) -> 596.63058 | L45: =SUM(I45:K45) -> 13071.797 | M45: =M44+L45 -> 985668.26 | O45: 0 | P45: =O45*(1+S45)^-B45 -> 0 | S45: =S44 -> 0.0492 | T45: =SUM(I45:K45)*((1+S45)^-B45) -> 2319.7284 | Z45: =O45/((1+$Y$9)^B45) -> 0
B46: 37 | C46: =C45+1 -> 2062 | E46: =Plusvalia!D48 -> 1304496.8 | F46: 0 | G46: =E46-F46 -> 1304496.8 | I46: 0 | J46: =$J$6*E46 -> 13044.968 | K46: =K45*(1+$K$6*1) -> 602.59689 | L46: =SUM(I46:K46) -> 13647.565 | M46: =M45+L46 -> 999315.83 | O46: 0 | P46: =O46*(1+S46)^-B46 -> 0 | S46: =S45 -> 0.0492 | T46: =SUM(I46:K46)*((1+S46)^-B46) -> 2308.3344 | Z46: =O46/((1+$Y$9)^B46) -> 0
B47: 38 | C47: =C46+1 -> 2063 | E47: =Plusvalia!D49 -> 1364079.5 | F47: 0 | G47: =E47-F47 -> 1364079.5 | I47: 0 | J47: =$J$6*E47 -> 13640.795 | K47: =K46*(1+$K$6*1) -> 608.62286 | L47: =SUM(I47:K47) -> 14249.418 | M47: =M46+L47 -> 1013565.2 | O47: 0 | P47: =O47*(1+S47)^-B47 -> 0 | S47: =S46 -> 0.0492 | T47: =SUM(I47:K47)*((1+S47)^-B47) -> 2297.1133 | Z47: =O47/((1+$Y$9)^B47) -> 0
B48: 39 | C48: =C47+1 -> 2064 | E48: =Plusvalia!D50 -> 1426383.6 | F48: 0 | G48: =E48-F48 -> 1426383.6 | I48: 0 | J48: =$J$6*E48 -> 14263.836 | K48: =K47*(1+$K$6*1) -> 614.70909 | L48: =SUM(I48:K48) -> 14878.546 | M48: =M47+L48 -> 1028443.8 | O48: 0 | P48: =O48*(1+S48)^-B48 -> 0 | S48: =S47 -> 0.0492 | T48: =SUM(I48:K48)*((1+S48)^-B48) -> 2286.0593 | Z48: =O48/((1+$Y$9)^B48) -> 0
B49: 40 | C49: =C48+1 -> 2065 | E49: =Plusvalia!D51 -> 1491533.5 | F49: 0 | G49: =E49-F49 -> 1491533.5 | I49: 0 | J49: =$J$6*E49 -> 14915.335 | K49: =K48*(1+$K$6*1) -> 620.85618 | L49: =SUM(I49:K49) -> 15536.191 | M49: =M48+L49 -> 1043980 | O49: 0 | P49: =O49*(1+S49)^-B49 -> 0 | S49: =S48 -> 0.0492 | T49: =SUM(I49:K49)*((1+S49)^-B49) -> 2275.167 | Z49: =O49/((1+$Y$9)^B49) -> 0

Sheet catalogos
B2: Tax Property
B3: 1 | C3: Zillow | D3: =281*12 -> 3372
B4: 2 | C4: Calculada Logaritmica - zillow | D4: ='Property Tax Zillow'!D15 -> 4196.1949
B5: 3 | C5: Calculada Lineal - zillow | D5: ='Property Tax Zillow'!D21 -> 3912.563
B6: 4 | C6: Calculada Expopnencial - zillow | D6: ='Property Tax Zillow'!D18 -> 3975.8445
B7: 5 | C7: 2024 Property Tax Rates in Michigan | D7: ='Property Tax Millage'!N7 -> 3835.5652
B8: 6 | C8: Median Macomb County | D8: ='Michigan Property Tax'!T5 -> 3467
C11: Pago de Impuestos
C12: Anual
C13: Mensual

Sheet Calculadoras Online
C2: Calculadores Online
C4: Calculadora de préstamos hipotecarios
C5: https://www.guidestone.org/Resources/Education/Calculators/Spanish/SPMortgageLoan

Sheet Property Tax Zillow
C3: Property Tax Estimado con base en datos de Zillow
C5: Source: Zillow | D5: Propery Tax Annual
C6: 2017 | D6: 2069
C7: 2018 | D7: 3733
C8: 2019 | D8: 7012
C9: 2020 | D9: 2847
C10: 2021 | D10: 2847
C11: 2022 | D11: 4865
C12: 2023 | D12: 2979
C14: 2024 | D14: =(440.69*LN(8))+3227.9 -> 4144.2891 | E14: Estimacion Logaritmica
C15: 2025 | D15: =(440.69*LN(9))+3227.9 -> 4196.1949 | E15: Estimacion Logaritmica
C17: 2024 | D17: =3152*EXP(0.0258*8) -> 3874.5796 | E17: Estimacion Exponencial
C18: 2025 | D18: =3152*EXP(0.0258*9) -> 3975.8445 | E18: Estimacion Exponencial
C20: 2024 | D20: =(29.607*(C20-$C$6+1))+3646.1 -> 3882.956 | E20: Estimacion Lineal
B21: 0 | C21: 2025 | D21: =(29.607*(C21-$C$6+1))+3646.1 -> 3912.563 | E21: =(D21-D20)/D20 -> 0.0076248611
B22: 1 | C22: 2026 | D22: =(29.607*(C22-$C$6+1))+3646.1 -> 3942.17 | E22: =(D22-D21)/D21 -> 0.0075671625
B23: 2 | C23: 2027 | D23: =(29.607*(C23-$C$6+1))+3646.1 -> 3971.777 | E23: =(D23-D22)/D22 -> 0.0075103306
B24: 3 | C24: 2028 | D24: =(29.607*(C24-$C$6+1))+3646.1 -> 4001.384 | E24: =(D24-D23)/D23 -> 0.007454346
B25: 4 | C25: 2029 | D25: =(29.607*(C25-$C$6+1))+3646.1 -> 4030.991 | E25: =(D25-D24)/D24 -> 0.0073991899
B26: 5 | C26: 2030 | D26: =(29.607*(C26-$C$6+1))+3646.1 -> 4060.598 | E26: =(D26-D25)/D25 -> 0.007344844 | G26: Promedio de Incremento de Impuestos Annual
B27: 6 | C27: 2031 | D27: =(29.607*(C27-$C$6+1))+3646.1 -> 4090.205 | E27: =(D27-D26)/D26 -> 0.0072912906 | G27: =AVERAGE(E21:E51) -> 0.0068680893
B28: 7 | C28: 2032 | D28: =(29.607*(C28-$C$6+1))+3646.1 -> 4119.812 | E28: =(D28-D27)/D27 -> 0.0072385125
B29: 8 | C29: 2033 | D29: =(29.607*(C29-$C$6+1))+3646.1 -> 4149.419 | E29: =(D29-D28)/D28 -> 0.007186493
B30: 9 | C30: 2034 | D30: =(29.607*(C30-$C$6+1))+3646.1 -> 4179.026 | E30: =(D30-D29)/D29 -> 0.0071352158
B31: 10 | C31: 2035 | D31: =(29.607*(C31-$C$6+1))+3646.1 -> 4208.633 | E31: =(D31-D30)/D30 -> 0.0070846652
B32: 11 | C32: 2036 | D32: =(29.607*(C32-$C$6+1))+3646.1 -> 4238.24 | E32: =(D32-D31)/D31 -> 0.0070348258
B33: 12 | C33: 2037 | D33: =(29.607*(C33-$C$6+1))+3646.1 -> 4267.847 | E33: =(D33-D32)/D32 -> 0.0069856827
B34: 13 | C34: 2038 | D34: =(29.607*(C34-$C$6+1))+3646.1 -> 4297.454 | E34: =(D34-D33)/D33 -> 0.0069372215
B35: 14 | C35: 2039 | D35: =(29.607*(C35-$C$6+1))+3646.1 -> 4327.061 | E35: =(D35-D34)/D34 -> 0.006889428
B36: 15 | C36: 2040 | D36: =(29.607*(C36-$C$6+1))+3646.1 -> 4356.668 | E36: =(D36-D35)/D35 -> 0.0068422886
B37: 16 | C37: 2041 | D37: =(29.607*(C37-$C$6+1))+3646.1 -> 4386.275 | E37: =(D37-D36)/D36 -> 0.0067957898
B38: 17 | C38: 2042 | D38: =(29.607*(C38-$C$6+1))+3646.1 -> 4415.882 | E38: =(D38-D37)/D37 -> 0.0067499188
B39: 18 | C39: 2043 | D39: =(29.607*(C39-$C$6+1))+3646.1 -> 4445.489 | E39: =(D39-D38)/D38 -> 0.0067046629
... B51: 30 | C51: 2055 | D51: =(29.607*(C51-$C$6+1))+3646.1 -> 4800.773 | E51: =(D51-D50)/D50 -> 0.0062054014

Sheet Michigan Property Tax
T3: Macomb County
T4: with Mortgage
T5: 3467
A37: Source: | B37: https://worldpopulationreview.com/states/michigan/property-tax

Sheet Property Tax Millage
B2: 2024 Michigan Property Tax Millage Rates by County | M2: Datos
M4: Selling Price | N4: =Principal!D9 -> 249900
B5: Source (web): | C5: https://www.treadstonemortgage.com/blog/michigan-property-tax-millage-rates-by-county/ | M5: Assessed Value | N5: =N4*0.5 -> 124950
M6: Millage | N6: 30.6968
M7: Tax to pay | N7: =N5*N6/1000 -> 3835.5652
M14: Source (pdf): | N14: https://www.michigan.gov/taxes/-/media/Project/Websites/taxes/4029/Total-Rates-Reports/2024-Total-Rates.pdf?rev=b670f0fd0ca04193af5abc9cb17462e3&hash=A501588AFDC2F8E68DC7A57109C2C1DE

Sheet Amortizacion Gradual Frances A
B1: SISTEMA DE AMORTIZACION GRADUAL o "frances" - ANNUAL
B3: tasa de interes annual | C3: =Principal!D13 -> 0.07
B4: frecuencia de capitalizacion | C4: 1 | D4: =IF(C4=1,"Anual",IF(C4=12,"Mensual")) -> Anual
B5: tasa efectiva | C5: =C3/C4 -> 0.07
B6: periodos (n de pagos) | C6: =Principal!D11 -> 30
B7: credito | C7: =Principal!D9 -> 249900
B8: factor de descuento (V) | C8: =1/(1+C5) -> 0.93457944
B9: anualidad (a_n) | C9: =(1-C8^C6)/C5 -> 12.409041 | D9: anualidades vencidas
B10: rentas | C10: =C7/C9 -> 20138.542 | D10: rentas fijas
B12: periodo (mes) | C12: Renta (Mensual) (pagos iguales) | D12: Interes (van bajando) | E12: Amortizacion (va aumentando) Pago a Capital | F12: Saldo Insoluto (va bajando)
B13: 0 | C13: 0 | D13: 0 | E13: 0 | F13: =C7 -> 249900 | H13: =SUM(C13:C42) -> 584017.72 | I13: =SUM(D13:D42) -> 352938.79 | J13: =SUM(E13:E42) -> 231078.93
B14: 1 | C14: =$C$10 -> 20138.542 | D14: =F13*$C$5 -> 17493 | E14: =C14-D14 -> 2645.5422 | F14: =F13-E14 -> 247254.46 | H14: El total de lo | I14: Los intereses pagados | J14: El capital pagado
B15: 2 | C15: =$C$10 -> 20138.542 | D15: =F14*$C$5 -> 17307.812 | E15: =C15-D15 -> 2830.7302 | F15: =F14-E15 -> 244423.73 | H15: pagado al banco
B16: 3 | C16: =$C$10 -> 20138.542 | D16: =F15*$C$5 -> 17109.661 | E16: =C16-D16 -> 3028.8813 | F16: =F15-E16 -> 241394.85 | H16: incluye capital | J16: Comprobacion
B17: 4 | C17: =$C$10 -> 20138.542 | D17: =F16*$C$5 -> 16897.639 | E17: =C17-D17 -> 3240.903 | F17: =F16-E17 -> 238153.94 | H17: e intereses | J17: =J13+I13 -> 584017.72 | K17: capital + intereses
B18: 5 | C18: =$C$10 -> 20138.542 | D18: =F17*$C$5 -> 16670.776 | E18: =C18-D18 -> 3467.7662 | F18: =F17-E18 -> 234686.18
B19: 6 | C19: =$C$10 -> 20138.542 | D19: =F18*$C$5 -> 16428.032 | E19: =C19-D19 -> 3710.5098 | F19: =F18-E19 -> 230975.67
B20: 7 | C20: =$C$10 -> 20138.542 | D20: =F19*$C$5 -> 16168.297 | E20: =C20-D20 -> 3970.2455 | F20: =F19-E20 -> 227005.42
B21: 8 | C21: =$C$10 -> 20138.542 | D21: =F20*$C$5 -> 15890.38 | E21: =C21-D21 -> 4248.1627 | F21: =F20-E21 -> 222757.26
B22: 9 | C22: =$C$10 -> 20138.542 | D22: =F21*$C$5 -> 15593.008 | E22: =C22-D22 -> 4545.5341 | F22: =F21-E22 -> 218211.72
B23: 10 | C23: =$C$10 -> 20138.542 | D23: =F22*$C$5 -> 15274.821 | E23: =C23-D23 -> 4863.7215 | F23: =F22-E23 -> 213348
B24: 11 | C24: =$C$10 -> 20138.542 | D24: =F23*$C$5 -> 14934.36 | E24: =C24-D24 -> 5204.182 | F24: =F23-E24 -> 208143.82
B25: 12 | C25: =$C$10 -> 20138.542 | D25: =F24*$C$5 -> 14570.067 | E25: =C25-D25 -> 5568.4747 | F25: =F24-E25 -> 202575.35
B26: 13 | C26: =$C$10 -> 20138.542 | D26: =F25*$C$5 -> 14180.274 | E26: =C26-D26 -> 5958.268 | F26: =F25-E26 -> 196617.08
B27: 14 | C27: =$C$10 -> 20138.542 | D27: =F26*$C$5 -> 13763.196 | E27: =C27-D27 -> 6375.3467 | F27: =F26-E27 -> 190241.73
B28: 15 | C28: =$C$10 -> 20138.542 | D28: =F27*$C$5 -> 13316.921 | E28: =C28-D28 -> 6821.621 | F28: =F27-E28 -> 183420.11
B29: 16 | C29: =$C$10 -> 20138.542 | D29: =F28*$C$5 -> 12839.408 | E29: =C29-D29 -> 7299.1345 | F29: =F28-E29 -> 176120.98
... B43: 30 | C43: =$C$10 -> 20138.542 | D43: =F42*$C$5 -> 1317.4747 | E43: =C43-D43 -> 18821.068 | F43: =F42-E43 -> -3.6379788e-11

Sheet Tax Calculator links
C3: Links
C5: Michigan Property Tax Calculator & Interest Rate
C6: https://smartasset.com/taxes/michigan-property-tax-calculator#f7T5JD21xn
C8: Property Taxes by State and County, 2025
C9: https://taxfoundation.org/data/all/state/property-taxes-by-state-county/
C11: Property Tax Estimator
C12: https://treas-secure.state.mi.us/ptestimator

Sheet Plusvalia
G2: Source: | H2: https://www.zillow.com/homedetails/22024-Lester-St-Clinton-Township-MI-48035/170345534_zpid/
C3: Plusvaila Estimada con base en datos de Zillow
H4: Interes | I4: Interes | J4: Interes
C5: Market Value | D5: Total | E5: Costo/sqft | F5: Crecmiento Annual | H5: Compuesto | I5: Simple | J5: Continuo
C6: 2014 | D6: 104000 | E6: 61
C7: 2022 | D7: 217900 | E7: 127 | F7: =((D7-D6)/D6)/(C7-C6) -> 0.13689904 | H7: =((D7/D6)^(1/(C7-C6)))-1 -> 0.096864514 | I7: =((D7/D6)-1)/(C7-C6) -> 0.13689904 | J7: =LN(D7/D6)/(C7-C6) -> 0.092455668
C8: 2025 | D8: 249900 | E8: 146 | F8: =((D8-D7)/D7)/(C8-C7) -> 0.048952119 | H8: =((D8/D7)^(1/(C8-C7)))-1 -> 0.046734026 | I8: =((D8/D7)-1)/(C8-C7) -> 0.048952119 | J8: =LN(D8/D7)/(C8-C7) -> 0.045674865
B10: Periodo | C10: Anio | D10: Plusvalia Estimada | E10: Crecmiento
B11: 0 | C11: 2025 | D11: =D8 -> 249900
B12: 1 | C12: 2026 | D12: =$D$11*(1+$J$8)^B12 -> 261314.15 | E12: =(D12-D11)/D11 -> 0.045674865
B13: 2 | C13: 2027 | D13: =$D$11*(1+$J$8)^B13 -> 273249.64 | E13: =(D13-D12)/D12 -> 0.045674865
B14: 3 | C14: 2028 | D14: =$D$11*(1+$J$8)^B14 -> 285730.28 | E14: =(D14-D13)/D13 -> 0.045674865
B15: 4 | C15: 2029 | D15: =$D$11*(1+$J$8)^B15 -> 298780.97 | E15: =(D15-D14)/D14 -> 0.045674865
B16: 5 | C16: 2030 | D16: =$D$11*(1+$J$8)^B16 -> 312427.75 | E16: =(D16-D15)/D15 -> 0.045674865
B17: 6 | C17: 2031 | D17: =$D$11*(1+$J$8)^B17 -> 326697.85 | E17: =(D17-D16)/D16 -> 0.045674865
B18: 7 | C18: 2032 | D18: =$D$11*(1+$J$8)^B18 -> 341619.73 | E18: =(D18-D17)/D17 -> 0.045674865
B19: 8 | C19: 2033 | D19: =$D$11*(1+$J$8)^B19 -> 357223.16 | E19: =(D19-D18)/D18 -> 0.045674865
B20: 9 | C20: 2034 | D20: =$D$11*(1+$J$8)^B20 -> 373539.28 | E20: =(D20-D19)/D19 -> 0.045674865
B21: 10 | C21: 2035 | D21: =$D$11*(1+$J$8)^B21 -> 390600.64 | E21: =(D21-D20)/D20 -> 0.045674865
B22: 11 | C22: 2036 | D22: =$D$11*(1+$J$8)^B22 -> 408441.27 | E22: =(D22-D21)/D21 -> 0.045674865
B23: 12 | C23: 2037 | D23: =$D$11*(1+$J$8)^B23 -> 427096.77 | E23: =(D23-D22)/D22 -> 0.045674865
... B51: 40 | C51: 2065 | D51: =$D$11*(1+$J$8)^B51 -> 1491533.5 | E51: =(D51-D50)/D50 -> 0.045674865

Sheet Opciones de Inversion
G5: Escenario 1 | K5: Escenario 2
G6: Invertir el mismo "Cash Outflow" en un Fondo Indexado | K6: Rentar una Casa e Invertir la diferencia del "Cash Outflow" en
K7: un Fondo Indexado i.e. VOO.
G8: Annual Return S&P 500 | H8: 0.103 | I8: including dividends | K8: Incremento de Renta annual | M8: 0.03
H9: 0.076 | I9: adjusted for inflation | K9: Renta Mensual Inicial | M9: 1300
B12: Periodo t | C12: ='Flujos Anuales'!C8 -> Año | E12: ='Flujos Anuales'!G8 -> Home Equity | G12: Inversion Anual | H12: Invertir 100% | I12: Diferencia | K12: Renta Annual | L12: Inversion Annual | M12: Rentar e Invertir | N12: Diferencia
B13: ='Flujos Anuales'!B9 -> 0 | C13: ='Flujos Anuales'!C9 -> 2025 | E13: ='Flujos Anuales'!G9 -> 23859.582 | G13: ='Flujos Anuales'!L9 -> 70411.104 | H13: =G13 -> 70411.104 | I13: =H43-E43 -> 2575603.8 | K13: =($M$9*12) -> 15600 | L13: =IF(G13-K13<0,0,G13-K13) -> 54811.104 | M13: =L13 -> 54811.104 | N13: =M43-E43 -> 180725.58
B14: ='Flujos Anuales'!B10 -> 1 | C14: ='Flujos Anuales'!C10 -> 2026 | E14: ='Flujos Anuales'!G10 -> 37744.52 | G14: ='Flujos Anuales'!L10 -> 28440.736 | H14: =G14+(H13*((1+$H$9)^1)) -> 104203.08 | I14: en t=30 años | K14: =K13*(1+($M$8*1)) -> 16068 | L14: =IF(G14-K14<0,0,G14-K14) -> 12372.736 | M14: =L14+(M13*(1+$H$9)^1) -> 71349.483 | N14: en t=30 años
B15: ='Flujos Anuales'!B11 -> 2 | C15: ='Flujos Anuales'!C11 -> 2027 | E15: ='Flujos Anuales'!G11 -> 52329.412 | G15: ='Flujos Anuales'!L11 -> 26121.601 | H15: =G15+(H14*((1+$H$9)^1)) -> 138244.12 | K15: =K14*(1+($M$8*1)) -> 16550.04 | L15: =IF(G15-K15<0,0,G15-K15) -> 9571.5607 | M15: =L15+(M14*(1+$H$9)^1) -> 86343.605
B16: ='Flujos Anuales'!B12 -> 3 | C16: ='Flujos Anuales'!C12 -> 2028 | E16: ='Flujos Anuales'!G12 -> 67650.98 | G16: ='Flujos Anuales'!L12 -> 25785.534 | H16: =G16+(H15*((1+$H$9)^1)) -> 174536.21 | K16: =K15*(1+($M$8*1)) -> 17046.541 | L16: =IF(G16-K16<0,0,G16-K16) -> 8738.993 | M16: =L16+(M15*(1+$H$9)^1) -> 101644.71
B17: ='Flujos Anuales'!B13 -> 4 | C17: ='Flujos Anuales'!C13 -> 2029 | E17: ='Flujos Anuales'!G13 -> 83747.972 | G17: ='Flujos Anuales'!L13 -> 25949.755 | H17: =G17+(H16*((1+$H$9)^1)) -> 213750.71 | K17: =K16*(1+($M$8*1)) -> 17557.937 | L17: =IF(G17-K17<0,0,G17-K17) -> 8391.8178 | M17: =L17+(M16*(1+$H$9)^1) -> 117761.53
B18: ='Flujos Anuales'!B14 -> 5 | C18: ='Flujos Anuales'!C14 -> 2030 | E18: ='Flujos Anuales'!G14 -> 100661.27 | G18: ='Flujos Anuales'!L14 -> 26120.182 | H18: =G18+(H17*((1+$H$9)^1)) -> 256115.95 | K18: =K17*(1+($M$8*1)) -> 18084.676 | L18: =IF(G18-K18<0,0,G18-K18) -> 8035.5065 | M18: =L18+(M17*(1+$H$9)^1) -> 134746.91
B19: ='Flujos Anuales'!B15 -> 6 | C19: ='Flujos Anuales'!C15 -> 2031 | E19: ='Flujos Anuales'!G15 -> 118434.02 | G19: ='Flujos Anuales'!L15 -> 26297.089 | H19: =G19+(H18*((1+$H$9)^1)) -> 301877.85 | K19: =K18*(1+($M$8*1)) -> 18627.216 | L19: =IF(G19-K19<0,0,G19-K19) -> 7669.8732 | M19: =L19+(M18*(1+$H$9)^1) -> 152657.55
B20: ='Flujos Anuales'!B16 -> 7 | C20: ='Flujos Anuales'!C16 -> 2032 | E20: ='Flujos Anuales'!G16 -> 137111.76 | G20: ='Flujos Anuales'!L16 -> 26480.762 | H20: =G20+(H19*((1+$H$9)^1)) -> 351301.33 | K20: =K19*(1+($M$8*1)) -> 19186.032 | L20: =IF(G20-K20<0,0,G20-K20) -> 7294.7301 | M20: =L20+(M19*(1+$H$9)^1) -> 171554.25
B21: ='Flujos Anuales'!B17 -> 8 | C21: ='Flujos Anuales'!C17 -> 2033 | E21: ='Flujos Anuales'!G17 -> 156742.56 | G21: ='Flujos Anuales'!L17 -> 26671.502 | H21: =G21+(H20*((1+$H$9)^1)) -> 404671.73 | K21: =K20*(1+($M$8*1)) -> 19761.613 | L21: =IF(G21-K21<0,0,G21-K21) -> 6909.8885 | M21: =L21+(M20*(1+$H$9)^1) -> 191502.26
B22: ='Flujos Anuales'!B18 -> 9 | C22: ='Flujos Anuales'!C18 -> 2034 | E22: ='Flujos Anuales'!G18 -> 177377.2 | G22: ='Flujos Anuales'!L18 -> 26869.62 | H22: =G22+(H21*((1+$H$9)^1)) -> 462296.4 | K22: =K21*(1+($M$8*1)) -> 20354.462 | L22: =IF(G22-K22<0,0,G22-K22) -> 6515.1588 | M22: =L22+(M21*(1+$H$9)^1) -> 212571.6
B23: ='Flujos Anuales'!B19 -> 10 | C23: ='Flujos Anuales'!C19 -> 2035 | E23: ='Flujos Anuales'!G19 -> 199069.25 | G23: ='Flujos Anuales'!L19 -> 27075.446 | H23: =G23+(H22*((1+$H$9)^1)) -> 524506.38 | K23: =K22*(1+($M$8*1)) -> 20965.096 | L23: =IF(G23-K23<0,0,G23-K23) -> 6110.3502 | M23: =L23+(M22*(1+$H$9)^1) -> 234837.39
B24: ='Flujos Anuales'!B20 -> 11 | C24: ='Flujos Anuales'!C20 -> 2036 | E24: ='Flujos Anuales'!G20 -> 221875.33 | G24: ='Flujos Anuales'!L20 -> 27289.32 | H24: =G24+(H23*((1+$H$9)^1)) -> 591658.18 | K24: =K23*(1+($M$8*1)) -> 21594.048 | L24: =IF(G24-K24<0,0,G24-K24) -> 5695.2714 | M24: =L24+(M23*(1+$H$9)^1) -> 258380.3
B25: ='Flujos Anuales'!B21 -> 12 | C25: ='Flujos Anuales'!C21 -> 2037 | E25: ='Flujos Anuales'!G21 -> 245855.23 | G25: ='Flujos Anuales'!L21 -> 27511.601 | H25: =G25+(H24*((1+$H$9)^1)) -> 664135.8 | K25: =K24*(1+($M$8*1)) -> 22241.87 | L25: =IF(G25-K25<0,0,G25-K25) -> 5269.7308 | M25: =L25+(M24*(1+$H$9)^1) -> 283286.93
B26: ='Flujos Anuales'!B22 -> 13 | C26: ='Flujos Anuales'!C22 -> 2038 | E26: ='Flujos Anuales'!G22 -> 271072.12 | G26: ='Flujos Anuales'!L22 -> 27742.662 | H26: =G26+(H25*((1+$H$9)^1)) -> 742352.79 | K26: =K25*(1+($M$8*1)) -> 22909.126 | L26: =IF(G26-K26<0,0,G26-K26) -> 4833.5363 | M26: =L26+(M25*(1+$H$9)^1) -> 309650.28
... B43: ='Flujos Anuales'!B39 -> 30 | C43: ='Flujos Anuales'!C39 -> 2055 | E43: ='Flujos Anuales'!G39 -> 954259.14 | G43: ='Flujos Anuales'!L39 -> 12051.98 | H43: =G43+(H42*((1+$H$9)^1)) -> 3529863 | K43: =K42*(1+($M$8*1)) -> 37865.295 | L43: =IF(G43-K43<0,0,G43-K43) -> 0 | M43: =L43+(M42*(1+$H$9)^1) -> 1134984.7

Sheet Yield Curve
B1: Date | C1: 1 Mo | D1: 1.5 Mo | E1: 2 Mo | F1: 3 Mo | G1: 4 Mo | H1: 6 Mo | I1: 1 Yr | J1: 2 Yr | K1: 3 Yr | L1: 5 Yr | M1: 7 Yr | N1: 10 Yr | O1: 20 Yr | P1: 30 Yr | R1: Daily Treasury Par Yield Curve Rates | Y1: Source: | Z1: https://home.treasury.gov/resource-center/data-chart-center/interest-rates/TextView?type=daily_treasury_yield_curve&field_tdr_date_value=2025
B2: 45659 | C2: 4.45 | D2: N/A | E2: 4.36 | F2: 4.36 | G2: 4.31 | H2: 4.25 | I2: 4.17 | J2: 4.25 | K2: 4.29 | L2: 4.38 | M2: 4.47 | N2: 4.57 | O2: 4.86 | P2: 4.79
B3: 45660 | C3: 4.44 | D3: N/A | E3: 4.35 | F3: 4.34 | G3: 4.31 | H3: 4.25 | I3: 4.18 | J3: 4.28 | K3: 4.32 | L3: 4.41 | M3: 4.51 | N3: 4.6 | O3: 4.88 | P3: 4.82
B4: 45663 | C4: 4.43 | D4: N/A | E4: 4.36 | F4: 4.35 | G4: 4.31 | H4: 4.24 | I4: 4.17 | J4: 4.28 | K4: 4.3 | L4: 4.42 | M4: 4.52 | N4: 4.62 | O4: 4.91 | P4: 4.85
B5: 45664 | C5: 4.42 | D5: N/A | E5: 4.35 | F5: 4.35 | G5: 4.31 | H5: 4.24 | I5: 4.19 | J5: 4.3 | K5: 4.33 | L5: 4.46 | M5: 4.57 | N5: 4.67 | O5: 4.97 | P5: 4.91
B6: 45665 | C6: 4.41 | D6: N/A | E6: 4.34 | F6: 4.35 | G6: 4.31 | H6: 4.25 | I6: 4.19 | J6: 4.28 | K6: 4.31 | L6: 4.45 | M6: 4.56 | N6: 4.67 | O6: 4.97 | P6: 4.91
B7: 45666 | C7: 4.44 | D7: N/A | E7: 4.36 | F7: 4.35 | G7: 4.31 | H7: 4.24 | I7: 4.16 | J7: 4.27 | K7: 4.31 | L7: 4.46 | M7: 4.57 | N7: 4.68 | O7: 4.98 | P7: 4.92
B8: 45667 | C8: 4.42 | D8: N/A | E8: 4.35 | F8: 4.36 | G8: 4.33 | H8: 4.27 | I8: 4.25 | J8: 4.4 | K8: 4.46 | L8: 4.59 | M8: 4.7 | N8: 4.77 | O8: 5.04 | P8: 4.96
B9: 45670 | C9: 4.42 | D9: N/A | E9: 4.36 | F9: 4.37 | G9: 4.34 | H9: 4.3 | I9: 4.24 | J9: 4.4 | K9: 4.49 | L9: 4.61 | M9: 4.71 | N9: 4.79 | O9: 5.05 | P9: 4.97
B10: 45671 | C10: 4.42 | D10: N/A | E10: 4.35 | F10: 4.36 | G10: 4.33 | H10: 4.29 | I10: 4.22 | J10: 4.37 | K10: 4.46 | L10: 4.59 | M10: 4.7 | N10: 4.78 | O10: 5.06 | P10: 4.98
B11: 45672 | C11: 4.4 | D11: N/A | E11: 4.34 | F11: 4.35 | G11: 4.32 | H11: 4.26 | I11: 4.19 | J11: 4.27 | K11: 4.34 | L11: 4.45 | M11: 4.55 | N11: 4.66 | O11: 4.95 | P11: 4.88
B12: 45673 | C12: 4.43 | D12: N/A | E12: 4.36 | F12: 4.34 | G12: 4.32 | H12: 4.26 | I12: 4.18 | J12: 4.23 | K12: 4.29 | L12: 4.39 | M12: 4.5 | N12: 4.61 | O12: 4.91 | P12: 4.84
B13: 45674 | C13: 4.43 | D13: N/A | E13: 4.35 | F13: 4.34 | G13: 4.32 | H13: 4.28 | I13: 4.21 | J13: 4.27 | K13: 4.33 | L13: 4.42 | M13: 4.52 | N13: 4.61 | O13: 4.91 | P13: 4.84
... B32: 45702 | C32: 4.37 | D32: N/A | E32: 4.38 | F32: 4.34 | G32: 4.35 | H32: 4.32 | I32: 4.23 | J32: 4.26 | K32: 4.26 | L32: 4.33 | M32: 4.41 | N32: 4.47 | O32: 4.75 | P32: 4.69
B33: 45706 | C33: 4.38 | D33: 4.41 | E33: 4.38 | F33: 4.34 | G33: 4.37 | H33: 4.34 | I33: 4.24 | J33: 4.29 | K33: 4.33 | L33: 4.4 | M33: 4.48 | N33: 4.55 | O33: 4.83 | P33: 4.77
B34: 45707 | C34: 4.38 | D34: 4.42 | E34: 4.38 | F34: 4.34 | G34: 4.35 | H34: 4.34 | I34: 4.22 | J34: 4.28 | K34: 4.3 | L34: 4.37 | M34: 4.46 | N34: 4.53 | O34: 4.79 | P34: 4.76
B35: 45708 | C35: 4.37 | D35: 4.4 | E35: 4.38 | F35: 4.33 | G35: 4.35 | H35: 4.33 | I35: 4.2 | J35: 4.28 | K35: 4.27 | L35: 4.34 | M35: 4.43 | N35: 4.5 | O35: 4.77 | P35: 4.74
B36: 45709 | C36: 4.36 | D36: 4.39 | E36: 4.38 | F36: 4.32 | G36: 4.34 | H36: 4.3 | I36: 4.15 | J36: 4.19 | K36: 4.19 | L36: 4.26 | M36: 4.35 | N36: 4.42 | O36: 4.69 | P36: 4.67
B37: 45712 | C37: 4.36 | D37: 4.38 | E37: 4.37 | F37: 4.31 | G37: 4.34 | H37: 4.3 | I37: 4.15 | J37: 4.13 | K37: 4.17 | L37: 4.23 | M37: 4.32 | N37: 4.4 | O37: 4.69 | P37: 4.66
B38: 45713 | C38: 4.34 | D38: 4.37 | E38: 4.37 | F38: 4.3 | G38: 4.33 | H38: 4.28 | I38: 4.12 | J38: 4.07 | K38: 4.08 | L38: 4.12 | M38: 4.21 | N38: 4.3 | O38: 4.59 | P38: 4.55
B39: 45714 | C39: 4.35 | D39: 4.38 | E39: 4.37 | F39: 4.31 | G39: 4.32 | H39: 4.28 | I39: 4.12 | J39: 4.05 | K39: 4.04 | L39: 4.06 | M39: 4.16 | N39: 4.25 | O39: 4.55 | P39: 4.51
B40: 45715 | C40: 4.38 | D40: 4.38 | E40: 4.38 | F40: 4.32 | G40: 4.32 | H40: 4.28 | I40: 4.13 | J40: 4.07 | K40: 4.05 | L40: 4.09 | M40: 4.19 | N40: 4.29 | O40: 4.59 | P40: 4.56
B41: 45716 | C41: 4.38 | D41: 4.37 | E41: 4.38 | F41: 4.32 | G41: 4.32 | H41: 4.25 | I41: 4.08 | J41: 3.99 | K41: 3.99 | L41: 4.03 | M41: 4.14 | N41: 4.24 | O41: 4.55 | P41: 4.51
B42: 45719 | C42: 4.38 | D42: 4.38 | E42: 4.37 | F42: 4.35 | G42: 4.31 | H42: 4.31 | I42: 4.06 | J42: 3.96 | K42: 3.93 | L42: 3.97 | M42: 4.06 | N42: 4.16 | O42: 4.49 | P42: 4.45
B43: 45720 | C43: 4.39 | D43: 4.38 | E43: 4.37 | F43: 4.34 | G43: 4.31 | H43: 4.28 | I43: 4.04 | J43: 3.96 | K43: 3.94 | L43: 4.01 | M43: 4.11 | N43: 4.22 | O43: 4.56 | P43: 4.53
B44: 45721 | C44: 4.38 | D44: 4.38 | E44: 4.36 | F44: 4.35 | G44: 4.3 | H44: 4.3 | I44: 4.06 | J44: 3.99 | K44: 4.01 | L44: 4.08 | M44: 4.18 | N44: 4.28 | O44: 4.61 | P44: 4.57
... B128: 45845 | C128: 4.37 | D128: 4.43 | E128: 4.45 | F128: 4.42 | G128: 4.41 | H128: 4.33 | I128: 4.08 | J128: 3.9 | K128: 3.85 | L128: 3.96 | M128: 4.16 | N128: 4.4 | O128: 4.93 | P128: 4.92

Sheet Amortizacion Constante Aleman A
B1: SISTEMA DE AMORTIZACION CONSTANTE o "aleman" - ANNUAL
B3: tasa de interes annual | C3: =Principal!D13 -> 0.07
B4: frecuencia de capitalizacion | C4: 1 | D4: annual
B5: tasa efectiva | C5: =C3/C4 -> 0.07
B6: periodos (n de pagos) | C6: =Principal!D11 -> 30
B7: credito | C7: =Principal!D9 -> 249900
B8: factor de descuento (V) | C8: =1/(1+C5) -> 0.93457944
B9: anualidad (a_n) | C9: =(1-C8^C6)/C5 -> 12.409041 | D9: anualidades vencidas
B10: Amortizacion | C10: =C7/C6 -> 8330 | D10: Amortizacion Constante Annual
B12: periodo (anios) | C12: Renta (Annual) (va bajando) | D12: Pago Mensual (Mensualidades Vencidas o a fin de mes) | E12: Interes (van bajando) | F12: Amortizacion (es igual) Pago a Capital | G12: Saldo Insoluto (va bajando) | I12: d: la diferencia entre dos rentas en la formula | J12: R_n (comprobacion)
B13: 0 | C13: 0 | D13: =C13/12 -> 0 | E13: 0 | F13: 0 | G13: =C7 -> 249900 | J13: 0
B14: 1 | C14: =E14+F14 -> 25823 | D14: =C14/12 -> 2151.9167 | E14: =G13*$C$5 -> 17493 | F14: =$C$10 -> 8330 | G14: =G13-F14 -> 241570 | J14: =C10*(1+(C6*C5)) -> 25823
B15: 2 | C15: =E15+F15 -> 25239.9 | D15: =C15/12 -> 2103.325 | E15: =G14*$C$5 -> 16909.9 | F15: =$C$10 -> 8330 | G15: =G14-F15 -> 233240 | I15: =C14-C15 -> 583.1 | J15: =$J$14-((B15-1)*I15) -> 25239.9
B16: 3 | C16: =E16+F16 -> 24656.8 | D16: =C16/12 -> 2054.7333 | E16: =G15*$C$5 -> 16326.8 | F16: =$C$10 -> 8330 | G16: =G15-F16 -> 224910 | I16: =C15-C16 -> 583.1 | J16: =$J$14-((B16-1)*I16) -> 24656.8
B17: 4 | C17: =E17+F17 -> 24073.7 | D17: =C17/12 -> 2006.1417 | E17: =G16*$C$5 -> 15743.7 | F17: =$C$10 -> 8330 | G17: =G16-F17 -> 216580 | I17: =C16-C17 -> 583.1 | J17: =$J$14-((B17-1)*I17) -> 24073.7
B18: 5 | C18: =E18+F18 -> 23490.6 | D18: =C18/12 -> 1957.55 | E18: =G17*$C$5 -> 15160.6 | F18: =$C$10 -> 8330 | G18: =G17-F18 -> 208250 | I18: =C17-C18 -> 583.1 | J18: =$J$14-((B18-1)*I18) -> 23490.6
B19: 6 | C19: =E19+F19 -> 22907.5 | D19: =C19/12 -> 1908.9583 | E19: =G18*$C$5 -> 14577.5 | F19: =$C$10 -> 8330 | G19: =G18-F19 -> 199920 | I19: =C18-C19 -> 583.1 | J19: =$J$14-((B19-1)*I19) -> 22907.5
B20: 7 | C20: =E20+F20 -> 22324.4 | D20: =C20/12 -> 1860.3667 | E20: =G19*$C$5 -> 13994.4 | F20: =$C$10 -> 8330 | G20: =G19-F20 -> 191590 | I20: =C19-C20 -> 583.1 | J20: =$J$14-((B20-1)*I20) -> 22324.4
B21: 8 | C21: =E21+F21 -> 21741.3 | D21: =C21/12 -> 1811.775 | E21: =G20*$C$5 -> 13411.3 | F21: =$C$10 -> 8330 | G21: =G20-F21 -> 183260 | I21: =C20-C21 -> 583.1 | J21: =$J$14-((B21-1)*I21) -> 21741.3
B22: 9 | C22: =E22+F22 -> 21158.2 | D22: =C22/12 -> 1763.1833 | E22: =G21*$C$5 -> 12828.2 | F22: =$C$10 -> 8330 | G22: =G21-F22 -> 174930 | I22: =C21-C22 -> 583.1 | J22: =$J$14-((B22-1)*I22) -> 21158.2
B23: 10 | C23: =E23+F23 -> 20575.1 | D23: =C23/12 -> 1714.5917 | E23: =G22*$C$5 -> 12245.1 | F23: =$C$10 -> 8330 | G23: =G22-F23 -> 166600 | I23: =C22-C23 -> 583.1 | J23: =$J$14-((B23-1)*I23) -> 20575.1
B24: 11 | C24: =E24+F24 -> 19992 | D24: =C24/12 -> 1666 | E24: =G23*$C$5 -> 11662 | F24: =$C$10 -> 8330 | G24: =G23-F24 -> 158270 | I24: =C23-C24 -> 583.1 | J24: =$J$14-((B24-1)*I24) -> 19992
B25: 12 | C25: =E25+F25 -> 19408.9 | D25: =C25/12 -> 1617.4083 | E25: =G24*$C$5 -> 11078.9 | F25: =$C$10 -> 8330 | G25: =G24-F25 -> 149940 | I25: =C24-C25 -> 583.1 | J25: =$J$14-((B25-1)*I25) -> 19408.9
B26: 13 | C26: =E26+F26 -> 18825.8 | D26: =C26/12 -> 1568.8167 | E26: =G25*$C$5 -> 10495.8 | F26: =$C$10 -> 8330 | G26: =G25-F26 -> 141610 | I26: =C25-C26 -> 583.1 | J26: =$J$14-((B26-1)*I26) -> 18825.8
... B43: 30 | C43: =E43+F43 -> 8913.1 | D43: =C43/12 -> 742.75833 | E43: =G42*$C$5 -> 583.1 | F43: =$C$10 -> 8330 | G43: =G42-F43 -> 0 | I43: =C42-C43 -> 583.1 | J43: =$J$14-((B43-1)*I43) -> 8913.1
C45: =SUM(C13:C37) -> 458816.4 | E45: =SUM(E13:E37) -> 258896.4 | F45: =SUM(F13:F37) -> 199920
C46: El total de lo | E46: Los intereses pagados | F46: El capital pagado
C47: pagado al banco
C48: incluye capital
C49: e intereses | F49: =F45+E45 -> 458816.4 | G49: capital + intereses

Sheet Amortizacion Constante Aleman M
B1: SISTEMA DE AMORTIZACION CONSTANTE o "aleman" - MENSUAL
B3: tasa de interes annual | C3: =Principal!D13 -> 0.07
B4: frecuencia de capitalizacion | C4: 12 | D4: Mensual
B5: tasa efectiva | C5: =C3/C4 -> 0.0058333333
B6: periodos (n de pagos) | C6: =Principal!D11*12 -> 360
B7: credito | C7: =Principal!D9 -> 249900
B8: factor de descuento (V) | C8: =1/(1+C5) -> 0.9942005
B9: anualidad (a_n*12) | C9: =(1-C8^C6)/C5 -> 150.30757 | D9: anualidades vencidas
B10: Amortizacion | C10: =C7/C6 -> 694.16667 | D10: Amortizacion Constante Annual
B12: periodo (Meses) | C12: Renta (Mensual) (va bajando) | D12: Interes (van bajando) | E12: Amortizacion (es igual) Pago a Capital | F12: Saldo Insoluto (va bajando) | H12: d: la diferencia entre dos rentas en la formula | I12: R_n (comprobacion) | K12: =SUM(C13:C373) -> 513023.88 | L12: =SUM(D13:D373) -> 263123.88 | M12: =SUM(E13:E373) -> 249900
B13: 0 | C13: 0 | D13: 0 | E13: 0 | F13: =C7 -> 249900 | I13: 0 | K13: El total de lo | L13: Los intereses pagados | M13: El capital pagado
B14: 1 | C14: =D14+E14 -> 2151.9167 | D14: =F13*$C$5 -> 1457.75 | E14: =$C$10 -> 694.16667 | F14: =F13-E14 -> 249205.83 | I14: =C10*(1+(C6*C5)) -> 2151.9167 | K14: pagado al banco
B15: 2 | C15: =D15+E15 -> 2147.8674 | D15: =F14*$C$5 -> 1453.7007 | E15: =$C$10 -> 694.16667 | F15: =F14-E15 -> 248511.67 | H15: =C14-C15 -> 4.0493056 | I15: =$I$14-((B15-1)*H15) -> 2147.8674 | K15: incluye capital
B16: 3 | C16: =D16+E16 -> 2143.8181 | D16: =F15*$C$5 -> 1449.6514 | E16: =$C$10 -> 694.16667 | F16: =F15-E16 -> 247817.5 | H16: =C15-C16 -> 4.0493056 | I16: =$I$14-((B16-1)*H16) -> 2143.8181 | K16: e intereses | M16: =M12+L12 -> 513023.88 | N16: capital + intereses
B17: 4 | C17: =D17+E17 -> 2139.7688 | D17: =F16*$C$5 -> 1445.6021 | E17: =$C$10 -> 694.16667 | F17: =F16-E17 -> 247123.33 | H17: =C16-C17 -> 4.0493056 | I17: =$I$14-((B17-1)*H17) -> 2139.7688
B18: 5 | C18: =D18+E18 -> 2135.7194 | D18: =F17*$C$5 -> 1441.5528 | E18: =$C$10 -> 694.16667 | F18: =F17-E18 -> 246429.17 | H18: =C17-C18 -> 4.0493056 | I18: =$I$14-((B18-1)*H18) -> 2135.7194
B19: 6 | C19: =D19+E19 -> 2131.6701 | D19: =F18*$C$5 -> 1437.5035 | E19: =$C$10 -> 694.16667 | F19: =F18-E19 -> 245735 | H19: =C18-C19 -> 4.0493056 | I19: =$I$14-((B19-1)*H19) -> 2131.6701
B20: 7 | C20: =D20+E20 -> 2127.6208 | D20: =F19*$C$5 -> 1433.4542 | E20: =$C$10 -> 694.16667 | F20: =F19-E20 -> 245040.83 | H20: =C19-C20 -> 4.0493056 | I20: =$I$14-((B20-1)*H20) -> 2127.6208
B21: 8 | C21: =D21+E21 -> 2123.5715 | D21: =F20*$C$5 -> 1429.4049 | E21: =$C$10 -> 694.16667 | F21: =F20-E21 -> 244346.67 | H21: =C20-C21 -> 4.0493056 | I21: =$I$14-((B21-1)*H21) -> 2123.5715
B22: 9 | C22: =D22+E22 -> 2119.5222 | D22: =F21*$C$5 -> 1425.3556 | E22: =$C$10 -> 694.16667 | F22: =F21-E22 -> 243652.5 | H22: =C21-C22 -> 4.0493056 | I22: =$I$14-((B22-1)*H22) -> 2119.5222
B23: 10 | C23: =D23+E23 -> 2115.4729 | D23: =F22*$C$5 -> 1421.3063 | E23: =$C$10 -> 694.16667 | F23: =F22-E23 -> 242958.33 | H23: =C22-C23 -> 4.0493056 | I23: =$I$14-((B23-1)*H23) -> 2115.4729
B24: 11 | C24: =D24+E24 -> 2111.4236 | D24: =F23*$C$5 -> 1417.2569 | E24: =$C$10 -> 694.16667 | F24: =F23-E24 -> 242264.17 | H24: =C23-C24 -> 4.0493056 | I24: =$I$14-((B24-1)*H24) -> 2111.4236
B25: 12 | C25: =D25+E25 -> 2107.3743 | D25: =F24*$C$5 -> 1413.2076 | E25: =$C$10 -> 694.16667 | F25: =F24-E25 -> 241570 | H25: =C24-C25 -> 4.0493056 | I25: =$I$14-((B25-1)*H25) -> 2107.3743
B26: 13 | C26: =D26+E26 -> 2103.325 | D26: =F25*$C$5 -> 1409.1583 | E26: =$C$10 -> 694.16667 | F26: =F25-E26 -> 240875.83 | H26: =C25-C26 -> 4.0493056 | I26: =$I$14-((B26-1)*H26) -> 2103.325
B27: 14 | C27: =D27+E27 -> 2099.2757 | D27: =F26*$C$5 -> 1405.109 | E27: =$C$10 -> 694.16667 | F27: =F26-E27 -> 240181.67 | H27: =C26-C27 -> 4.0493056 | I27: =$I$14-((B27-1)*H27) -> 2099.2757
B28: 15 | C28: =D28+E28 -> 2095.2264 | D28: =F27*$C$5 -> 1401.0597 | E28: =$C$10 -> 694.16667 | F28: =F27-E28 -> 239487.5 | H28: =C27-C28 -> 4.0493056 | I28: =$I$14-((B28-1)*H28) -> 2095.2264
... B373: 360 | C373: =D373+E373 -> 698.21597 | D373: =F372*$C$5 -> 4.0493056 | E373: =$C$10 -> 694.16667 | F373: =F372-E373 -> 1.2939836e-09 | H373: =C372-C373 -> 4.0493056 | I373: =$I$14-((B373-1)*H373) -> 698.21597
